Workbook

Sheet 起源
A1: 人物背景 Background
B3: 角色名 | O3: 背景获利 | AP3: 背景描述
B4: 玩家 | O4: 属性值 | S4: =背景!J2 -> 见注释，或自选至多三项 | AB4: 专长 | AF4: =背景!K2 -> 自选一项起源专长 | AP4: =背景!O2 -> 角色的背景代表了这个角色在成为冒险者之前的经历。通过创建一个独特的背景或对玩家手册中现有的背景进行修改，你可以反映战役的特定主题或是你世界中的独特元素。你也可以通过创建新的背景来帮助玩家为他们的角色制作心目中的起源故事。
B5: 故乡 | O5: 技能熟练 | S5: =背景!L2 -> 自选两个适合背景的技能
B6: 背景 | E6: 工匠 | O6: 工具熟练 | S6: =背景!M2 -> 选择一个工具，它与该背景有关，或是经常被该背景的人使用
O7: 背景装备 | S7: =背景!N2 -> 组合一套价值50GP的装备（购买完毕后多余的钱也会包含在其内）。不要将包含军用武器和护甲包含在背景给予的装备中，角色会从其职业中获得这两样装备。
B8: 年龄 | H8: 身高
B9: 性别 | H9: 体重
B11: 人物形象 | O11: 个性 | AV11: 人物立绘
O13: 理念
O14: 羁绊
O15: 缺陷
O17: 背景故事
B23: 语言
B30: 熟练工具
B31: 选择一种工匠工具（参见第六章）

Sheet 主要
A1: DND 5.5E 人物卡<悲灵ver.>（2024） | AV1: =".st"& " 力量"&IF($B$13="O","*","")&":"&$F$13& " 敏捷"&IF($B$14="O","*","")&":"&$F$14& " 体质"&IF($B$15="O","*","")&":"&$F$15& " 智力"&IF($B$16="O","*","")&":"&$F$16& " 感知"&IF($B$17="O","*","")&":"&$F$17& " 魅力"&IF($B$18="O","*","")&":"&$F$18& " hp"&":"&R22&" hpmax"&":"&V22& " 先攻"&":"&D22&" ac"&":"&D23&" dc"&":"&D24&" pp"&":"&$L$23&" 熟练"&":"&S3& " 运动"&IF($B$41="O","*",IF($B$41="🅞","*2",IF($H$39="O","*0.5","")))&":"&IF($F$41+$X$11="",0,$F$41+$X$11)& " 特技"&IF($B$43="O","*",IF($B$43="🅞","*2",IF($H$39="O","*0.5","")))&":"&IF($F$43+$X$11="",0,$F$43+$X$11)& " 巧手"&IF($B$44="O","*",IF($B$44="🅞","*2",IF($H$39="O","*0.5","")))&":"&IF($F$44+$X$11="",0,$F$44+$X$11)& " 隐匿"&IF($B$45="O","*",IF($B$45="🅞","*2",IF($H$39="O","*0.5","")))&":"&IF($F$45+$X$11="",0,$F$45+$X$11)& " 调查"&IF($B$47="O","*",IF($B$47="🅞","*2",IF($H$39="O","*0.5","")))&":"&IF($F$47+$X$11="",0,$F$47+$X$11)& " 奥秘"&IF($B$48="O","*",IF($B$48="🅞","*2",IF($H$39="O","*0.5","")))&":"&IF($F$48+$X$11="",0,$F$48+$X$11)& " 历史"&IF($B$49="O","*",IF($B$49="🅞","*2",IF($H$39="O","*0.5","")))&":"&IF($F$49+$X$11="",0,$F$49+$X$11)& " 自然"&IF($B$50="O","*",IF($B$50="🅞","*2",IF($H$39="O","*0.5","")))&":"&IF($F$50+$X$11="",0,$F$50+$X$11)& " 宗教"&IF($B$51="O","*",IF($B$51="🅞","*2",IF($H$39="O","*0.5","")))&":"&IF($F$51+$X$11="",0,$F$51+$X$11)& " 察觉"&IF($B$53="O","*",IF($B$53="🅞","*2",IF($H$39="O","*0.5","")))&":"&IF($F$53+$X$11="",0,$F$53+$X$11)& " 洞悉"&IF($B$54="O","*",IF($B$54="🅞","*2",IF($H$39="O","*0.5","")))&":"&IF($F$54+$X$11="",0,$F$54+$X$11)& " 驯兽"&IF($B$55="O","*",IF($B$55="🅞","*2",IF($H$39="O","*0.5","")))&":"&IF($F$55+$X$11="",0,$F$55+$X$11)& " 医疗"&IF($B$56="O","*",IF($B$56="🅞","*2",IF($H$39="O","*0.5","")))&":"&IF($F$56+$X$11="",0,$F$56+$X$11)& " 求生"&IF($B$57="O","*",IF($B$57="🅞","*2",IF($H$39="O","*0.5","")))&":"&IF($F$57+$X$11="",0,$F$57+$X$11)& " 游说"&IF($B$59="O","*",IF($B$59="🅞","*2",IF($H$39="O","*0.5","")))&":"&IF($F$59+$X$11="",0,$F$59+$X$11)& " 欺瞒"&IF($B$60="O","*",IF($B$60="🅞","*2",IF($H$39="O","*0.5","")))&":"&IF($F$60+$X$11="",0,$F$60+$X$11)& " 威吓"&IF($B$61="O","*",IF($B$61="🅞","*2",IF($H$39="O","*0.5","")))&":"&IF($F$61+$X$11="",0,$F$61+$X$11)& " 表演"&IF($B$62="O","*",IF($B$62="🅞","*2",IF($H$39="O","*0.5","")))&":"&IF($F$62+$X$11="",0,$F$62+$X$11) -> .st 力量:10 敏捷:10 体质:10 智力:10 感知:10 魅力:10 hp:0 hpmax:0 先攻:0 ac:10 dc:10 pp:10 熟练:2 运动:0 特技:0 巧手:0 隐匿:0 调查:0 奥秘:0 历史:0 自然:0 宗教:0 察觉:0 洞悉:0 驯兽:0 医疗:0 求生:0 游说:0 欺瞒:0 威吓:0 表演:0 | AW1: 生命值小工具 | BJ1: 生命骰使用期望 | BQ1: 是 | BT1: 种族特性
AX2: 1级 | AZ2: 2级 | BB2: 3级 | BD2: 4级 | BF2: 5级 | BH2: 6级 | BJ2: 7级 | BL2: 8级 | BN2: 9级 | BP2: 10级 | BT2: 名称 | BZ2: 描述
B3: 角色名 | E3: 琼脂糖 | Q3: 熟练 | S3: =IFERROR(VLOOKUP(SUM(O6,O7,O8),数据表!CM2:CN21,2,FALSE)+W4,IF(SUM(O6,O7,O8)>=20,6,2)) -> 2 | W3: 修正 | AW3: 生命值小工具 | BT3: 生物种类
B4: 玩家 | E4: 悲灵 | V4: < | AX4: 11级 | AZ4: 12级 | BB4: 13级 | BD4: 14级 | BF4: 15级 | BH4: 16级 | BJ4: 17级 | BL4: 18级 | BN4: 19级 | BP4: 20级 | BT4: 体型
E5: 主职 | I5: 子职 | O5: Lv | BT5: 速度
B6: 主职业 | E6: 野蛮人 | I6: 狂战士道途 | O6: 8 | R6: 种族 | T6: 半身人 | AX6: 额外调整值 | BB6: 修正 | BF6: 生命总值 | BI6: 仅需填入每级生命骰结果 自动结算等级与体质调整值 | BT6: 勇气
B7: 兼职1 | R7: 亚种 | BF7: =IF(BQ1="否",SUM(AX3:BQ3,AX5:BQ5,(R15+AX7)*(O6+O7+O8),BB7), SUM(O6*职业!AT2,O7*职业!AT3,O8*职业!AT4,职业!AT7,(R15+AX7)*(O6+O7+O8),BB7)) -> 0 | BT7: 半身人灵巧
B8: 兼职2 | R8: 阵营 | T8: 守序善良 | BT8: 天生善匿
B9: 经验值 | O9: =IF(E9="","","Lv "&VLOOKUP(E9,数据表!CI3:CJ22,2,TRUE)) | R9: 信仰 | BJ9: 职业能力 | BT9: 幸运
AW10: Lv | AX10: 名称 | BC10: 描述
B11: 属性 | R11: 全局检定修正 | AW11: =职业!CV2 | AX11: 豁免熟练
B12: 熟练 | F12: 总值 | H12: 初始值 | K12: 背景 | M12: 成长 | O12: 修正 | Q12: 调整值 | T12: 豁免 | W12: 修正 | AW12: =职业!CV3 | AX12: 技能熟练
B13: X | C13: 力量 | F13: =I13+K13+M13+O13 -> 10 | H13: < | I13: 10 | Q13: > | R13: =INT(F13/2-5) -> 0 | T13: =INT(F13/2-5)+IF(B13="O",$S$3,0)+W13 -> 0 | V13: < | AW13: =职业!CV4 | AX13: 武器熟练
B14: X | C14: 敏捷 | F14: =I14+K14+M14+O14 -> 10 | H14: < | I14: 10 | Q14: > | R14: =INT(F14/2-5) -> 0 | T14: =INT(F14/2-5)+IF(B14="O",$S$3,0)+W14 -> 0 | V14: < | AW14: =职业!CV5 | AX14: 工具熟练
B15: X | C15: 体质 | F15: =I15+K15+M15+O15 -> 10 | H15: < | I15: 10 | Q15: > | R15: =INT(F15/2-5) -> 0 | T15: =INT(F15/2-5)+IF(B15="O",$S$3,0)+W15 -> 0 | V15: < | AW15: =职业!CV6 | AX15: 护甲受训
B16: X | C16: 智力 | F16: =I16+K16+M16+O16 -> 10 | H16: < | I16: 10 | Q16: > | R16: =INT(F16/2-5) -> 0 | T16: =INT(F16/2-5)+IF(B16="O",$S$3,0)+W16 -> 0 | V16: < | AW16: =职业!CV7 | AX16: 起始装备
B17: X | C17: 感知 | F17: =I17+K17+M17+O17 -> 10 | H17: < | I17: 10 | Q17: > | R17: =INT(F17/2-5) -> 0 | T17: =INT(F17/2-5)+IF(B17="O",$S$3,0)+W17 -> 0 | V17: < | AW17: =职业!CV8 | BT17: 专长
B18: X | C18: 魅力 | F18: =I18+K18+M18+O18 -> 10 | H18: < | I18: 10 | Q18: > | R18: =INT(F18/2-5) -> 0 | T18: =INT(F18/2-5)+IF(B18="O",$S$3,0)+W18 -> 0 | V18: < | AW18: =职业!CV9 | BT18: Lv | BU18: 名称 | BZ18: 描述
AW19: =职业!CV10 | BT19: 1 | BU19: 专注重击
B20: 战斗 | R20: 持有英雄激励 | X20: 否 | AW20: =职业!CV11 | BT20: 4 | BU20: 云端漫步者
G21: 修正 | S21: Now | V21: Max | AA21: 画像 | AW21: =职业!CV12 | BT21: 8 | BU21: 巧匠
B22: 先攻 | D22: =SUM(R14+G22) -> 0 | F22: < | P22: HP | R22: =V22 -> 0 | U22: / | V22: =BF7 -> 0 | AA22: 抗性 | AO22: 黑视 | AW22: =职业!CV13 | BT22: 12
B23: AC | D23: =SUM(AF40,AI40,G23,+IF(AS40="是",AQ40,0)) -> 10 | F23: < | J23: 被察 | L23: =SUM(10+I53) -> 10 | P23: HD | R23: =U23 -> 1 | T23: / | U23: =O6+O7+O8 -> 1 | W23: =IF(E7="",IF(E8="",IFERROR(VLOOKUP(E6,职业!AO2:AP21,2,0),""),""),"") | AA23: 免疫 | AO23: 体型 | AR23: 中型 | AW23: =职业!CV14 | BT23: 16
B24: DC | D24: =SUM(8+S3+G24+VLOOKUP(L24,C13:S18,16,FALSE)) -> 10 | F24: < | I24: < | J24: 属性 | L24: 魅力 | P24: 临时生命 | AA24: 优势 | AO24: 速度 | AR24: 30 | AW24: =职业!CV15 | BT24: 19
B25: 名称 | F25: 描述 | J25: Now | M25: Max | O25: 回复 | Q25: 名称 | U25: 描述 | Y25: Now | AB25: Max | AD25: 回复 | AF25: 名称 | AJ25: 描述 | AN25: Now | AQ25: Max | AS25: 回复 | AW25: =职业!CV16 | BT25: 6
B26: 特殊能力 | L26: / | Q26: 特殊能力 | AA26: / | AF26: 特殊能力 | AP26: / | AW26: =职业!CV17 | BT26: 10
B27: 特殊能力 | L27: / | Q27: 特殊能力 | AA27: / | AF27: 特殊能力 | AP27: / | AW27: =职业!CV18
B28: 特殊能力 | L28: / | Q28: 特殊能力 | AA28: / | AF28: 特殊能力 | AP28: / | AW28: =职业!CV19
AW29: =职业!CV20
B30: 武器 | U30: 攻击属性 | AA30: 默认 | AE30: 弹药 | AK30: 箭矢 | AP30: 数量 | AS30: 0 | AW30: =职业!CV21
B31: 武器类型 | F31: 同调 | H31: 名称 | L31: 加值 | N31: 特性 | W31: 熟练 | X31: 攻击骰 | AB31: 伤害骰 | AF31: 类型 | AH31: 附加伤害骰 | AL31: 类型 | AN31: 精通 | AP31: 效果 | AW31: =职业!CV22 | BT31: 战斗风格专长
G32: > | M32: =装备!AS2 | V32: > | W32: O | X32: D20 | Z32: =装备!AU2 | AB32: =装备!AQ2 | AD32: =IF(装备!AW2="","",IF(装备!AZ2=1,"",IF(装备!AW2>=0,CONCATENATE("+",装备!AW2),装备!AW2))) | AF32: =装备!AR2 | AN32: =装备!AT2 | AP32: =装备!AC2 | AW32: =职业!CV23 | BT32: 名称 | BZ32: 描述
G33: > | M33: =装备!AS3 | V33: > | W33: O | X33: D20 | Z33: =装备!AU3 | AB33: =装备!AQ3 | AD33: =IF(装备!AW3="","",IF(装备!AZ3=1,"",IF(装备!AW3>=0,CONCATENATE("+",装备!AW3),装备!AW3))) | AF33: =装备!AR3 | AN33: =装备!AT3 | AP33: =装备!AC3 | AW33: =职业!CV24
G34: > | M34: =装备!AS4 | V34: > | W34: O | X34: D20 | Z34: =装备!AU4 | AB34: =装备!AQ4 | AD34: =IF(装备!AW4="","",IF(装备!AZ4=1,"",IF(装备!AW4>=0,CONCATENATE("+",装备!AW4),装备!AW4))) | AF34: =装备!AR4 | AN34: =装备!AT4 | AP34: =装备!AC4 | AW34: =职业!CV25
G35: > | M35: =装备!AS5 | V35: > | W35: O | X35: D20 | Z35: =装备!AU5 | AB35: =装备!AQ5 | AD35: =IF(装备!AW5="","",IF(装备!AZ5=1,"",IF(装备!AW5>=0,CONCATENATE("+",装备!AW5),装备!AW5))) | AF35: =装备!AR5 | AN35: =装备!AT5 | AP35: =装备!AC5 | AW35: =职业!CV26
G36: > | M36: =装备!AS6 | V36: > | W36: O | X36: D20 | Z36: =装备!AU6 | AB36: =装备!AQ6 | AD36: =IF(装备!AW6="","",IF(装备!AZ6=1,"",IF(装备!AW6>=0,CONCATENATE("+",装备!AW6),装备!AW6))) | AF36: =装备!AR6 | AN36: =装备!AT6 | AP36: =装备!AC6 | AW36: =职业!CV27
AW37: =职业!CV28
B38: 技能 | L38: 装备 | AM38: 已同调的装备 | AS38: =SUM(装备!T20:T36) -> 0 | AW38: =职业!CV29 | BT38: 特殊能力
B39: 万事通 | H39: X | L39: 护甲类型 | P39: 同调 | R39: 名称 | U39: 加值 | V39: 特性 | AF39: AC | AH39: 敏捷加值 | AL39: 盾牌 | AP39: 同调 | AQ39: AC | AS39: 着装 | AW39: =职业!CV30 | BT39: 名称 | BZ39: 描述
B40: 熟练 | D40: 力量 | F40: 修正 | I40: 总值 | V40: =装备!AY12 | AE40: > | AF40: =装备!AV12+U40 -> 10 | AH40: + | AI40: =装备!AW12 -> 0 | AQ40: 2 | AS40: 否 | AW40: =职业!CV31
B41: X | C41: 运动 | H41: > | I41: =R13+F41+IF(B41="O",S3,(IF(B41="🅞",S3*2,IF(H39="O",INT(S3/2),0))))+X11 -> 0 | L41: 奇物 | P41: 同调 | R41: 稀有度 | U41: 部位 | W41: 特性 | AW41: =职业!CV32
B42: 敏捷 | Q42: > | AW42: =职业!CV33
B43: O | C43: 特技 | H43: > | I43: =R14+F43+IF(B43="O",S3,(IF(B43="🅞",S3*2,IF(H39="O",INT(S3/2),0))))+X11 -> 0 | Q43: > | AW43: =职业!CV34
B44: X | C44: 巧手 | H44: > | I44: =R14+F44+IF(B44="O",S3,(IF(B44="🅞",S3*2,IF(H39="O",INT(S3/2),0))))+X11 -> 0 | Q44: > | AW44: =职业!CV35
B45: X | C45: 隐匿 | H45: > | I45: =R14+F45+IF(B45="O",S3,(IF(B45="🅞",S3*2,IF(H39="O",INT(S3/2),0))))+X11 -> 0 | Q45: > | AW45: =职业!CV36
B46: 智力 | Q46: > | AW46: =职业!CV37 | BT46: 寻获魔宠速查
B47: O | C47: 调查 | H47: > | I47: =R16+F47+IF(B47="O",S3,(IF(B47="🅞",S3*2,IF(H39="O",INT(S3/2),0))))+X11 -> 0 | Q47: > | AW47: =职业!CV38 | BT47: 名字 | BX47: 魔宠类型 | CD47: AC | CF47: HP | CK47: HD | CN47: 先攻
B48: X | C48: 奥秘 | H48: > | I48: =R16+F48+IF(B48="O",S3,(IF(B48="🅞",S3*2,IF(H39="O",INT(S3/2),0))))+X11 -> 0 | Q48: > | AW48: =职业!CV39 | CC48: > | CD48: =IFERROR(VLOOKUP($BX$48,魔宠!$A$3:$AD$21,5,FALSE),"") | CH48: / | CI48: =IFERROR(VLOOKUP($BX$48,魔宠!$A$3:$AD$21,6,FALSE),"") | CK48: =IFERROR(VLOOKUP($BX$48,魔宠!$A$3:$AD$21,7,FALSE),"") | CM48: > | CN48: =IFERROR(VLOOKUP($BX$48,魔宠!$A$3:$AD$21,8,FALSE),"")
B49: X | C49: 历史 | H49: > | I49: =R16+F49+IF(B49="O",S3,(IF(B49="🅞",S3*2,IF(H39="O",INT(S3/2),0))))+X11 -> 0 | Q49: > | AW49: =职业!CV40 | BT49: 体型 | BW49: 种类 | BZ49: 阵营 | CD49: 速度
B50: X | C50: 自然 | H50: > | I50: =R16+F50+IF(B50="O",S3,(IF(B50="🅞",S3*2,IF(H39="O",INT(S3/2),0))))+X11 -> 0 | Q50: > | AW50: =职业!CV41 | BT50: =IFERROR(VLOOKUP($BX$48,魔宠!$A$3:$AD$21,2,FALSE),"") | BW50: =IFERROR(VLOOKUP($BX$48,魔宠!$A$3:$AD$21,3,FALSE),"") | BZ50: =IFERROR(VLOOKUP($BX$48,魔宠!$A$3:$AD$21,4,FALSE),"") | CD50: =IFERROR(VLOOKUP($BX$48,魔宠!$A$3:$AD$21,9,FALSE),"")
B51: X | C51: 宗教 | H51: > | I51: =R16+F51+IF(B51="O",S3,(IF(B51="🅞",S3*2,IF(H39="O",INT(S3/2),0))))+X11 -> 0 | Q51: > | AW51: =职业!CV42 | BT51: 力量 | BV51: 调整 | BX51: 豁免 | CB51: 敏捷 | CD51: 调整 | CF51: 豁免 | CJ51: 体质 | CL51: 调整 | CN51: 豁免
B52: 感知 | L52: 消耗品 | R52: 稀有度 | U52: 描述 | AP52: 数量 | AW52: =职业!CV43 | BT52: =IFERROR(VLOOKUP($BX$48,魔宠!$A$3:$AD$21,10,FALSE),"") | BV52: =IFERROR(VLOOKUP($BX$48,魔宠!$A$3:$AD$21,11,FALSE),"") | BX52: =IFERROR(VLOOKUP($BX$48,魔宠!$A$3:$AD$21,12,FALSE),"") | CB52: =IFERROR(VLOOKUP($BX$48,魔宠!$A$3:$AD$21,13,FALSE),"") | CD52: =IFERROR(VLOOKUP($BX$48,魔宠!$A$3:$AD$21,14,FALSE),"") | CF52: =IFERROR(VLOOKUP($BX$48,魔宠!$A$3:$AD$21,15,FALSE),"") | CJ52: =IFERROR(VLOOKUP($BX$48,魔宠!$A$3:$AD$21,16,FALSE),"") | CL52: =IFERROR(VLOOKUP($BX$48,魔宠!$A$3:$AD$21,17,FALSE),"") | CN52: =IFERROR(VLOOKUP($BX$48,魔宠!$A$3:$AD$21,18,FALSE),"")
B53: X | C53: 察觉 | H53: > | I53: =R17+F53+IF(B53="O",S3,(IF(B53="🅞",S3*2,IF(H39="O",INT(S3/2),0))))+X11 -> 0 | Q53: > | AR53: / | AW53: =职业!CV44 | BT53: 智力 | BV53: 调整 | BX53: 豁免 | CB53: 感知 | CD53: 调整 | CF53: 豁免 | CJ53: 魅力 | CL53: 调整 | CN53: 豁免
B54: X | C54: 洞悉 | H54: > | I54: =R17+F54+IF(B54="O",S3,(IF(B54="🅞",S3*2,IF(H39="O",INT(S3/2),0))))+X11 -> 0 | Q54: > | AR54: / | AW54: =职业!CV45 | BT54: =IFERROR(VLOOKUP($BX$48,魔宠!$A$3:$AD$21,19,FALSE),"") | BV54: =IFERROR(VLOOKUP($BX$48,魔宠!$A$3:$AD$21,20,FALSE),"") | BX54: =IFERROR(VLOOKUP($BX$48,魔宠!$A$3:$AD$21,21,FALSE),"") | CB54: =IFERROR(VLOOKUP($BX$48,魔宠!$A$3:$AD$21,22,FALSE),"") | CD54: =IFERROR(VLOOKUP($BX$48,魔宠!$A$3:$AD$21,23,FALSE),"") | CF54: =IFERROR(VLOOKUP($BX$48,魔宠!$A$3:$AD$21,24,FALSE),"") | CJ54: =IFERROR(VLOOKUP($BX$48,魔宠!$A$3:$AD$21,25,FALSE),"") | CL54: =IFERROR(VLOOKUP($BX$48,魔宠!$A$3:$AD$21,26,FALSE),"") | CN54: =IFERROR(VLOOKUP($BX$48,魔宠!$A$3:$AD$21,27,FALSE),"")
B55: X | C55: 驯兽 | H55: > | I55: =R17+F55+IF(B55="O",S3,(IF(B55="🅞",S3*2,IF(H39="O",INT(S3/2),0))))+X11 -> 0 | Q55: > | AR55: / | AW55: =职业!CV46 | BT55: 概览
B56: O | C56: 医药 | H56: > | I56: =R17+F56+IF(B56="O",S3,(IF(B56="🅞",S3*2,IF(H39="O",INT(S3/2),0))))+X11 -> 0 | Q56: > | AR56: / | AW56: =职业!CV47 | BT56: =IFERROR(VLOOKUP($BX$48,魔宠!$A$3:$AD$21,28,FALSE),"")
B57: X | C57: 求生 | H57: > | I57: =R17+F57+IF(B57="O",S3,(IF(B57="🅞",S3*2,IF(H39="O",INT(S3/2),0))))+X11 -> 0 | Q57: > | AR57: / | AW57: =职业!CV48
B58: 魅力 | L58: ——负重—— | AG58: ———随身钱币——— | AW58: =职业!CV49
B59: O | C59: 游说 | H59: > | I59: =R18+F59+IF(B59="O",S3,(IF(B59="🅞",S3*2,IF(H39="O",INT(S3/2),0))))+X11 -> 0 | L59: 装备 | P59: 背包1 | T59: 背包2 | X59: > | Y59: 总负重 | AF59: < | AG59: GP | AN59: PP | AW59: =职业!CV50
B60: X | C60: 欺瞒 | H60: > | I60: =R18+F60+IF(B60="O",S3,(IF(B60="🅞",S3*2,IF(H39="O",INT(S3/2),0))))+X11 -> 0 | L60: =SUM(数据表!BP27,数据表!BS27,数据表!BV27:BW31,数据表!BY27:BZ36,数据表!CB27:CC31) -> 0 | P60: =背包!AS3 -> 0 | T60: =背包!V27 -> 0 | Y60: =SUM(L60:W60)+T62+L62 -> 0 | AG60: EP | AN60: 总财富 | AW60: =职业!CV51
B61: X | C61: 威吓 | H61: > | I61: =R18+F61+IF(B61="O",S3,(IF(B61="🅞",S3*2,IF(H39="O",INT(S3/2),0))))+X11 -> 0 | L61: 弹药 | P61: 次元袋 | T61: 钱包 | Y61: 最大载重 | AG61: SP | AN61: =CONCATENATE(SUM(AP59*10+AI60/2+AI59+AI61/10+AI62/100),"GP") -> 0GP | AW61: =职业!CV52 | BT61: 特质
B62: X | C62: 表演 | H62: > | I62: =R18+F62+IF(B62="O",S3,(IF(B62="🅞",S3*2,IF(H39="O",INT(S3/2),0))))+X11 -> 0 | L62: =装备!AC34 -> 0 | P62: =IF(背包!AV27="有",15,背包!BG48) -> 0 | T62: =SUM(AI59:AM62,AP59)/50 -> 0 | Y62: =F13*VLOOKUP(AR23,装备!S39:T44,2,FALSE) -> 150 | AG62: CP | AW62: =职业!CV53 | BT62: =IFERROR(VLOOKUP($BX$48,魔宠!$A$3:$AD$21,29,FALSE),"")
AW63: =职业!CV54
B64: 法术 | P64: 无消耗法术 | X64: 准备法术 | AW64: =职业!CV55
B65: 关键属性 | E65: 修正 | G65: 法术DC | I65: 修正 | K65: 法术攻击骰 | P65: Lv | Q65: 法术名称 | X65: Lv | Y65: 法术名称 | AF65: Lv | AG65: 法术名称 | AN65: Lv | AO65: 法术名称 | AW65: =职业!CV56
B66: 智力 | G66: =IFERROR(SUM(8+S3+E66+R16),"×") -> 10 | K66: =IFERROR(CONCATENATE("D20+",SUM(R16+S3+I66)),"x") -> D20+2 | P66: =CONCATENATE(IFERROR(VLOOKUP(Q66,法术大全!$A:$Z,2,FALSE),""),IFERROR(IF(VLOOKUP(Q66,法术大全!$A:$Z,5,FALSE)="√"," ",""),"")) | X66: =CONCATENATE(IFERROR(VLOOKUP(Y66,法术大全!$A:$Z,2,FALSE),""),IFERROR(IF(VLOOKUP(Y66,法术大全!$A:$Z,5,FALSE)="√"," ",""),"")) | AF66: =CONCATENATE(IFERROR(VLOOKUP(AG66,法术大全!$A:$Z,2,FALSE),""),IFERROR(IF(VLOOKUP(AG66,法术大全!$A:$Z,5,FALSE)="√"," ",""),"")) | AN66: =CONCATENATE(IFERROR(VLOOKUP(AO66,法术大全!$A:$Z,2,FALSE),""),IFERROR(IF(VLOOKUP(AO66,法术大全!$A:$Z,5,FALSE)="√"," ",""),"")) | AW66: =职业!CV57
B67: 感知 | G67: =IFERROR(SUM(8+S3+E67+R17),"×") -> 10 | K67: =IFERROR(CONCATENATE("D20+",SUM(R17+S3+I67)),"x") -> D20+2 | P67: =CONCATENATE(IFERROR(VLOOKUP(Q67,法术大全!$A:$Z,2,FALSE),""),IFERROR(IF(VLOOKUP(Q67,法术大全!$A:$Z,5,FALSE)="√"," ",""),"")) | X67: =CONCATENATE(IFERROR(VLOOKUP(Y67,法术大全!$A:$Z,2,FALSE),""),IFERROR(IF(VLOOKUP(Y67,法术大全!$A:$Z,5,FALSE)="√"," ",""),"")) | AF67: =CONCATENATE(IFERROR(VLOOKUP(AG67,法术大全!$A:$Z,2,FALSE),""),IFERROR(IF(VLOOKUP(AG67,法术大全!$A:$Z,5,FALSE)="√"," ",""),"")) | AN67: =CONCATENATE(IFERROR(VLOOKUP(AO67,法术大全!$A:$Z,2,FALSE),""),IFERROR(IF(VLOOKUP(AO67,法术大全!$A:$Z,5,FALSE)="√"," ",""),"")) | AW67: =职业!CV58 | BT67: 动作
B68: 魅力 | G68: =IFERROR(SUM(8+S3+E68+R18),"×") -> 10 | K68: =IFERROR(CONCATENATE("D20+",SUM(R18+S3+I68)),"x") -> D20+2 | P68: =CONCATENATE(IFERROR(VLOOKUP(Q68,法术大全!$A:$Z,2,FALSE),""),IFERROR(IF(VLOOKUP(Q68,法术大全!$A:$Z,5,FALSE)="√"," ",""),"")) | X68: =CONCATENATE(IFERROR(VLOOKUP(Y68,法术大全!$A:$Z,2,FALSE),""),IFERROR(IF(VLOOKUP(Y68,法术大全!$A:$Z,5,FALSE)="√"," ",""),"")) | AF68: =CONCATENATE(IFERROR(VLOOKUP(AG68,法术大全!$A:$Z,2,FALSE),""),IFERROR(IF(VLOOKUP(AG68,法术大全!$A:$Z,5,FALSE)="√"," ",""),"")) | AN68: =CONCATENATE(IFERROR(VLOOKUP(AO68,法术大全!$A:$Z,2,FALSE),""),IFERROR(IF(VLOOKUP(AO68,法术大全!$A:$Z,5,FALSE)="√"," ",""),"")) | AW68: =职业!CV59 | BT68: =IFERROR(VLOOKUP($BX$48,魔宠!$A$3:$AD$21,30,FALSE),"")
B69: 职业归属 | F69: 可以准备的法术数量 | P69: =CONCATENATE(IFERROR(VLOOKUP(Q69,法术大全!$A:$Z,2,FALSE),""),IFERROR(IF(VLOOKUP(Q69,法术大全!$A:$Z,5,FALSE)="√"," ",""),"")) | X69: =CONCATENATE(IFERROR(VLOOKUP(Y69,法术大全!$A:$Z,2,FALSE),""),IFERROR(IF(VLOOKUP(Y69,法术大全!$A:$Z,5,FALSE)="√"," ",""),"")) | AF69: =CONCATENATE(IFERROR(VLOOKUP(AG69,法术大全!$A:$Z,2,FALSE),""),IFERROR(IF(VLOOKUP(AG69,法术大全!$A:$Z,5,FALSE)="√"," ",""),"")) | AN69: =CONCATENATE(IFERROR(VLOOKUP(AO69,法术大全!$A:$Z,2,FALSE),""),IFERROR(IF(VLOOKUP(AO69,法术大全!$A:$Z,5,FALSE)="√"," ",""),"")) | AW69: =职业!CV60
F70: =数据表!P26 | P70: =CONCATENATE(IFERROR(VLOOKUP(Q70,法术大全!$A:$Z,2,FALSE),""),IFERROR(IF(VLOOKUP(Q70,法术大全!$A:$Z,5,FALSE)="√"," ",""),"")) | X70: =CONCATENATE(IFERROR(VLOOKUP(Y70,法术大全!$A:$Z,2,FALSE),""),IFERROR(IF(VLOOKUP(Y70,法术大全!$A:$Z,5,FALSE)="√"," ",""),"")) | AF70: =CONCATENATE(IFERROR(VLOOKUP(AG70,法术大全!$A:$Z,2,FALSE),""),IFERROR(IF(VLOOKUP(AG70,法术大全!$A:$Z,5,FALSE)="√"," ",""),"")) | AN70: =CONCATENATE(IFERROR(VLOOKUP(AO70,法术大全!$A:$Z,2,FALSE),""),IFERROR(IF(VLOOKUP(AO70,法术大全!$A:$Z,5,FALSE)="√"," ",""),"")) | AW70: =职业!CV61
B71: 环阶 | E71: 法术位 | J71: 法术值 | P71: =CONCATENATE(IFERROR(VLOOKUP(Q71,法术大全!$A:$Z,2,FALSE),""),IFERROR(IF(VLOOKUP(Q71,法术大全!$A:$Z,5,FALSE)="√"," ",""),"")) | X71: =CONCATENATE(IFERROR(VLOOKUP(Y71,法术大全!$A:$Z,2,FALSE),""),IFERROR(IF(VLOOKUP(Y71,法术大全!$A:$Z,5,FALSE)="√"," ",""),"")) | AF71: =CONCATENATE(IFERROR(VLOOKUP(AG71,法术大全!$A:$Z,2,FALSE),""),IFERROR(IF(VLOOKUP(AG71,法术大全!$A:$Z,5,FALSE)="√"," ",""),"")) | AN71: =CONCATENATE(IFERROR(VLOOKUP(AO71,法术大全!$A:$Z,2,FALSE),""),IFERROR(IF(VLOOKUP(AO71,法术大全!$A:$Z,5,FALSE)="√"," ",""),"")) | AW71: =职业!CV62
B72: 1 | G72: / | H72: =职业!AV1 | J72: 2 | P72: =CONCATENATE(IFERROR(VLOOKUP(Q72,法术大全!$A:$Z,2,FALSE),""),IFERROR(IF(VLOOKUP(Q72,法术大全!$A:$Z,5,FALSE)="√"," ",""),"")) | X72: =CONCATENATE(IFERROR(VLOOKUP(Y72,法术大全!$A:$Z,2,FALSE),""),IFERROR(IF(VLOOKUP(Y72,法术大全!$A:$Z,5,FALSE)="√"," ",""),"")) | AF72: =CONCATENATE(IFERROR(VLOOKUP(AG72,法术大全!$A:$Z,2,FALSE),""),IFERROR(IF(VLOOKUP(AG72,法术大全!$A:$Z,5,FALSE)="√"," ",""),"")) | AN72: =CONCATENATE(IFERROR(VLOOKUP(AO72,法术大全!$A:$Z,2,FALSE),""),IFERROR(IF(VLOOKUP(AO72,法术大全!$A:$Z,5,FALSE)="√"," ",""),"")) | AW72: =职业!CV63
B73: 2 | G73: / | H73: =职业!AV2 | J73: 3 | P73: =CONCATENATE(IFERROR(VLOOKUP(Q73,法术大全!$A:$Z,2,FALSE),""),IFERROR(IF(VLOOKUP(Q73,法术大全!$A:$Z,5,FALSE)="√"," ",""),"")) | X73: =CONCATENATE(IFERROR(VLOOKUP(Y73,法术大全!$A:$Z,2,FALSE),""),IFERROR(IF(VLOOKUP(Y73,法术大全!$A:$Z,5,FALSE)="√"," ",""),"")) | AF73: =CONCATENATE(IFERROR(VLOOKUP(AG73,法术大全!$A:$Z,2,FALSE),""),IFERROR(IF(VLOOKUP(AG73,法术大全!$A:$Z,5,FALSE)="√"," ",""),"")) | AN73: =CONCATENATE(IFERROR(VLOOKUP(AO73,法术大全!$A:$Z,2,FALSE),""),IFERROR(IF(VLOOKUP(AO73,法术大全!$A:$Z,5,FALSE)="√"," ",""),"")) | AW73: =职业!CV64
B74: 3 | G74: / | H74: =职业!AV3 | J74: 5 | AF74: =CONCATENATE(IFERROR(VLOOKUP(AG74,法术大全!$A:$Z,2,FALSE),""),IFERROR(IF(VLOOKUP(AG74,法术大全!$A:$Z,5,FALSE)="√"," ",""),"")) | AN74: =CONCATENATE(IFERROR(VLOOKUP(AO74,法术大全!$A:$Z,2,FALSE),""),IFERROR(IF(VLOOKUP(AO74,法术大全!$A:$Z,5,FALSE)="√"," ",""),"")) | AW74: =职业!CV65
B75: 4 | G75: / | H75: =职业!AV4 | J75: 6 | P75: 已知戏法 | AF75: =CONCATENATE(IFERROR(VLOOKUP(AG75,法术大全!$A:$Z,2,FALSE),""),IFERROR(IF(VLOOKUP(AG75,法术大全!$A:$Z,5,FALSE)="√"," ",""),"")) | AN75: =CONCATENATE(IFERROR(VLOOKUP(AO75,法术大全!$A:$Z,2,FALSE),""),IFERROR(IF(VLOOKUP(AO75,法术大全!$A:$Z,5,FALSE)="√"," ",""),"")) | AW75: =职业!CV66
B76: 5 | G76: / | H76: =职业!AV5 | J76: 7 | P76: Lv | Q76: 法术名称 | X76: Lv | Y76: 法术名称 | AF76: =CONCATENATE(IFERROR(VLOOKUP(AG76,法术大全!$A:$Z,2,FALSE),""),IFERROR(IF(VLOOKUP(AG76,法术大全!$A:$Z,5,FALSE)="√"," ",""),"")) | AN76: =CONCATENATE(IFERROR(VLOOKUP(AO76,法术大全!$A:$Z,2,FALSE),""),IFERROR(IF(VLOOKUP(AO76,法术大全!$A:$Z,5,FALSE)="√"," ",""),"")) | AW76: =职业!CV67
B77: 6 | G77: / | H77: =职业!AV6 | J77: 9 | P77: =CONCATENATE(IFERROR(VLOOKUP(Q77,法术大全!$A:$Z,2,FALSE),""),IFERROR(IF(VLOOKUP(Q77,法术大全!$A:$Z,5,FALSE)="√"," ",""),"")) | X77: =CONCATENATE(IFERROR(VLOOKUP(Y77,法术大全!$A:$Z,2,FALSE),""),IFERROR(IF(VLOOKUP(Y77,法术大全!$A:$Z,5,FALSE)="√"," ",""),"")) | AF77: =CONCATENATE(IFERROR(VLOOKUP(AG77,法术大全!$A:$Z,2,FALSE),""),IFERROR(IF(VLOOKUP(AG77,法术大全!$A:$Z,5,FALSE)="√"," ",""),"")) | AN77: =CONCATENATE(IFERROR(VLOOKUP(AO77,法术大全!$A:$Z,2,FALSE),""),IFERROR(IF(VLOOKUP(AO77,法术大全!$A:$Z,5,FALSE)="√"," ",""),"")) | AW77: =职业!CV68
B78: 7 | G78: / | H78: =职业!AV7 | J78: 10 | P78: =CONCATENATE(IFERROR(VLOOKUP(Q78,法术大全!$A:$Z,2,FALSE),""),IFERROR(IF(VLOOKUP(Q78,法术大全!$A:$Z,5,FALSE)="√"," ",""),"")) | X78: =CONCATENATE(IFERROR(VLOOKUP(Y78,法术大全!$A:$Z,2,FALSE),""),IFERROR(IF(VLOOKUP(Y78,法术大全!$A:$Z,5,FALSE)="√"," ",""),"")) | AF78: =CONCATENATE(IFERROR(VLOOKUP(AG78,法术大全!$A:$Z,2,FALSE),""),IFERROR(IF(VLOOKUP(AG78,法术大全!$A:$Z,5,FALSE)="√"," ",""),"")) | AN78: =CONCATENATE(IFERROR(VLOOKUP(AO78,法术大全!$A:$Z,2,FALSE),""),IFERROR(IF(VLOOKUP(AO78,法术大全!$A:$Z,5,FALSE)="√"," ",""),""))
B79: 8 | G79: / | H79: =职业!AV8 | J79: 11 | P79: =CONCATENATE(IFERROR(VLOOKUP(Q79,法术大全!$A:$Z,2,FALSE),""),IFERROR(IF(VLOOKUP(Q79,法术大全!$A:$Z,5,FALSE)="√"," ",""),"")) | X79: =CONCATENATE(IFERROR(VLOOKUP(Y79,法术大全!$A:$Z,2,FALSE),""),IFERROR(IF(VLOOKUP(Y79,法术大全!$A:$Z,5,FALSE)="√"," ",""),"")) | AF79: =CONCATENATE(IFERROR(VLOOKUP(AG79,法术大全!$A:$Z,2,FALSE),""),IFERROR(IF(VLOOKUP(AG79,法术大全!$A:$Z,5,FALSE)="√"," ",""),"")) | AN79: =CONCATENATE(IFERROR(VLOOKUP(AO79,法术大全!$A:$Z,2,FALSE),""),IFERROR(IF(VLOOKUP(AO79,法术大全!$A:$Z,5,FALSE)="√"," ",""),"")) | BL79: 笔记
B80: 9 | G80: / | H80: =职业!AV9 | J80: 13 | P80: =CONCATENATE(IFERROR(VLOOKUP(Q80,法术大全!$A:$Z,2,FALSE),""),IFERROR(IF(VLOOKUP(Q80,法术大全!$A:$Z,5,FALSE)="√"," ",""),"")) | X80: =CONCATENATE(IFERROR(VLOOKUP(Y80,法术大全!$A:$Z,2,FALSE),""),IFERROR(IF(VLOOKUP(Y80,法术大全!$A:$Z,5,FALSE)="√"," ",""),"")) | AF80: =CONCATENATE(IFERROR(VLOOKUP(AG80,法术大全!$A:$Z,2,FALSE),""),IFERROR(IF(VLOOKUP(AG80,法术大全!$A:$Z,5,FALSE)="√"," ",""),"")) | AN80: =CONCATENATE(IFERROR(VLOOKUP(AO80,法术大全!$A:$Z,2,FALSE),""),IFERROR(IF(VLOOKUP(AO80,法术大全!$A:$Z,5,FALSE)="√"," ",""),""))
B81: 法术值 | I81: / | J81: =职业!AR21 -> 0 | P81: =CONCATENATE(IFERROR(VLOOKUP(Q81,法术大全!$A:$Z,2,FALSE),""),IFERROR(IF(VLOOKUP(Q81,法术大全!$A:$Z,5,FALSE)="√"," ",""),"")) | X81: =CONCATENATE(IFERROR(VLOOKUP(Y81,法术大全!$A:$Z,2,FALSE),""),IFERROR(IF(VLOOKUP(Y81,法术大全!$A:$Z,5,FALSE)="√"," ",""),"")) | AF81: =CONCATENATE(IFERROR(VLOOKUP(AG81,法术大全!$A:$Z,2,FALSE),""),IFERROR(IF(VLOOKUP(AG81,法术大全!$A:$Z,5,FALSE)="√"," ",""),"")) | AN81: =CONCATENATE(IFERROR(VLOOKUP(AO81,法术大全!$A:$Z,2,FALSE),""),IFERROR(IF(VLOOKUP(AO81,法术大全!$A:$Z,5,FALSE)="√"," ",""),""))
B83: 法术简易速查 | R83: 法术效果
B84: 法术名 | I84: 施法距离 | R84: =IFERROR(VLOOKUP(B85,法术大全!$A:$Z,13,FALSE),"")
I85: =IFERROR(VLOOKUP(B85,法术大全!$A:$Z,7,FALSE),"")
B86: 施法时间 | G86: 法术系别 | L86: 持续时间
B87: =IFERROR(VLOOKUP(B85,法术大全!$A:$Z,6,FALSE),"") | G87: =IFERROR(VLOOKUP(B85,法术大全!$A:$Z,3,FALSE),"") | L87: =IFERROR(VLOOKUP(B85,法术大全!$A:$Z,12,FALSE),"")
B88: 法术成分 | G88: =IF(B85="","",CONCATENATE(IF(VLOOKUP(B85,法术大全!$A:$Z,8,0)="V","语言（V）",""),IF(VLOOKUP(B85,法术大全!$A:$Z,9,0)="S","姿势（S）",""),IF(VLOOKUP(B85,法术大全!$A:$Z,10,0)="M","材料(M)","")))
B89: =IFERROR(IF(VLOOKUP(B85,法术大全!$A:$Z,10,FALSE)="M",VLOOKUP(B85,法术大全!$A:$Z,11,FALSE),""),"")
B91: 适用职业
B92: =IF(B85="","",CONCATENATE( IF(VLOOKUP(B85,法术大全!$A:$Z,15,0)="√","吟游诗人 ",""), IF(VLOOKUP(B85,法术大全!$A:$Z,16,0)="√","牧师 ",""), IF(VLOOKUP(B85,法术大全!$A:$Z,17,0)="√","德鲁伊 ",""), IF(VLOOKUP(B85,法术大全!$A:$Z,18,0)="√","圣武士 ",""), IF(VLOOKUP(B85,法术大全!$A:$Z,19,0)="√","游侠 ",""), IF(VLOOKUP(B85,法术大全!$A:$Z,20,0)="√","术士 ",""), IF(VLOOKUP(B85,法术大全!$A:$Z,21,0)="√","魔契师 ",""), IF(VLOOKUP(B85,法术大全!$A:$Z,22,0)="√","法师 ",""), IF(VLOOKUP(B85,法术大全!$A:$Z,23,0)="√","奇械师 ",""), IF(VLOOKUP(B85,法术大全!$A:$Z,24,0)="√","灵能使 ",""), IF(VLOOKUP(B85,法术大全!$A:$Z,25,0)="√","药剂师 ","")))

Sheet 数据表
B1: 法术书 | C1: 专注 | D1: 仪式 | E1: 准备栏 | I1: 仪 | J1: 专 | K1: {=IFERROR(INDEX($H$1:$H$68,SMALL(IF($H$2:$H$68<>"",ROW($H$2:$H$68),4^8),ROW(1:1)))&"","")} | M1: 语言 | P1: 1 | Q1: 2 | R1: 3 | S1: 4 | T1: 5 | U1: 6 | V1: 7 | W1: 8 | X1: 9 | Y1: 10 | Z1: 11 | AA1: 12 | AB1: 13 | AC1: 14 | AD1: 15 | AE1: 16 | AF1: 17 | AG1: 18 | AH1: 19 | AI1: 20 | AJ1: 等级 | CI1: 经验值 | CM1: 等级 | CN1: 熟练加值 | CO1: CR | CP1: 熟练加值
A2: 1 | B2: =IF(法术书!X3="","",法术书!X3) | C2: =IFERROR(VLOOKUP(B2,法术大全!$A:$W,5,FALSE),"") | D2: =IFERROR(VLOOKUP(B2,法术大全!$A:$W,4,FALSE),"") | E2: 1 | F2: {=IFERROR(INDEX($B$1:$B$301,SMALL(IF($B$1:$B$301<>"",ROW($B$1:$B$301),4^8),ROW(2:2)))&"","")} | G2: 无消耗 | H2: =IF(主要!Q66<>"",主要!Q66,"") | I2: =IF(VLOOKUP(H2,法术大全!$A$3:$E$864,4,0)="√",1,0) -> 0 | J2: =IF(VLOOKUP(H2,法术大全!$A$3:$E$864,5,0)="√",1,0) -> 0 | K2: {=IFERROR(INDEX($H$1:$H$68,SMALL(IF($H$2:$H$68<>"",ROW($H$2:$H$68),4^8),ROW(2:2)))&"","")} | M2: —标准语言— | O2: 吟游诗人 | P2: 4 | Q2: 5 | R2: 6 | S2: 7 | T2: 9 | U2: 10 | V2: 11 | W2: 12 | X2: 14 | Y2: 15 | Z2: 16 | AA2: 16 | AB2: 17 | AC2: 17 | AD2: 18 | AE2: 18 | AF2: 19 | AG2: 20 | AH2: 21 | AI2: 22 | AJ2: =职业!$AZ$3 -> 0 | AL2: 笔记 | BP2: 笔记 | CI2: Exp | CJ2: Lv | CK2: 戏法 | CL2: 0 | CM2: 1 | CN2: 2 | CO2: 0 | CP2: 2
A3: 2 | B3: =IF(法术书!X4="","",法术书!X4) | C3: =IFERROR(VLOOKUP(B3,法术大全!$A:$W,5,FALSE),"") | D3: =IFERROR(VLOOKUP(B3,法术大全!$A:$W,4,FALSE),"") | E3: 2 | F3: {=IFERROR(INDEX($B$1:$B$301,SMALL(IF($B$1:$B$301<>"",ROW($B$1:$B$301),4^8),ROW(3:3)))&"","")} | H3: =IF(主要!Q67<>"",主要!Q67,"") | I3: =IF(VLOOKUP(H3,法术大全!$A$3:$E$864,4,0)="√",1,0) -> 0 | J3: =IF(VLOOKUP(H3,法术大全!$A$3:$E$864,5,0)="√",1,0) -> 0 | K3: {=IFERROR(INDEX($H$1:$H$68,SMALL(IF($H$2:$H$68<>"",ROW($H$2:$H$68),4^8),ROW(3:3)))&"","")} | M3: 通用语 | O3: 牧师 | P3: 4 | Q3: 5 | R3: 6 | S3: 7 | T3: 9 | U3: 10 | V3: 11 | W3: 12 | X3: 14 | Y3: 15 | Z3: 16 | AA3: 16 | AB3: 17 | AC3: 17 | AD3: 18 | AE3: 18 | AF3: 19 | AG3: 20 | AH3: 21 | AI3: 22 | AJ3: =职业!$AZ$4 -> 0 | CI3: 0 | CJ3: 1 | CK3: 1环 | CL3: 1 | CM3: 2 | CN3: 2 | CO3: 1/8 | CP3: 2
A4: 3 | B4: =IF(法术书!X5="","",法术书!X5) | C4: =IFERROR(VLOOKUP(B4,法术大全!$A:$W,5,FALSE),"") | D4: =IFERROR(VLOOKUP(B4,法术大全!$A:$W,4,FALSE),"") | E4: 3 | F4: {=IFERROR(INDEX($B$1:$B$301,SMALL(IF($B$1:$B$301<>"",ROW($B$1:$B$301),4^8),ROW(4:4)))&"","")} | H4: =IF(主要!Q68<>"",主要!Q68,"") | I4: =IF(VLOOKUP(H4,法术大全!$A$3:$E$864,4,0)="√",1,0) -> 0 | J4: =IF(VLOOKUP(H4,法术大全!$A$3:$E$864,5,0)="√",1,0) -> 0 | K4: {=IFERROR(INDEX($H$1:$H$68,SMALL(IF($H$2:$H$68<>"",ROW($H$2:$H$68),4^8),ROW(4:4)))&"","")} | M4: 通用手语 | O4: 德鲁伊 | P4: 4 | Q4: 5 | R4: 6 | S4: 7 | T4: 9 | U4: 10 | V4: 11 | W4: 12 | X4: 14 | Y4: 15 | Z4: 16 | AA4: 16 | AB4: 17 | AC4: 17 | AD4: 18 | AE4: 18 | AF4: 19 | AG4: 20 | AH4: 21 | AI4: 22 | AJ4: =职业!$AZ$5 -> 0 | CI4: 300 | CJ4: 2 | CK4: 2环 | CL4: 2 | CM4: 3 | CN4: 2 | CO4: 1/4 | CP4: 2
A5: 4 | B5: =IF(法术书!X6="","",法术书!X6) | C5: =IFERROR(VLOOKUP(B5,法术大全!$A:$W,5,FALSE),"") | D5: =IFERROR(VLOOKUP(B5,法术大全!$A:$W,4,FALSE),"") | E5: 4 | F5: {=IFERROR(INDEX($B$1:$B$301,SMALL(IF($B$1:$B$301<>"",ROW($B$1:$B$301),4^8),ROW(5:5)))&"","")} | H5: =IF(主要!Q69<>"",主要!Q69,"") | I5: =IF(VLOOKUP(H5,法术大全!$A$3:$E$864,4,0)="√",1,0) -> 0 | J5: =IF(VLOOKUP(H5,法术大全!$A$3:$E$864,5,0)="√",1,0) -> 0 | K5: {=IFERROR(INDEX($H$1:$H$68,SMALL(IF($H$2:$H$68<>"",ROW($H$2:$H$68),4^8),ROW(5:5)))&"","")} | M5: 龙语 | O5: 圣武士 | P5: 2 | Q5: 3 | R5: 4 | S5: 5 | T5: 6 | U5: 6 | V5: 7 | W5: 7 | X5: 9 | Y5: 9 | Z5: 10 | AA5: 10 | AB5: 11 | AC5: 11 | AD5: 12 | AE5: 12 | AF5: 14 | AG5: 14 | AH5: 15 | AI5: 15 | AJ5: =职业!$AZ$8 -> 0 | CI5: 900 | CJ5: 3 | CK5: 3环 | CL5: 3 | CM5: 4 | CN5: 2 | CO5: 1/2 | CP5: 2
A6: 5 | B6: =IF(法术书!X7="","",法术书!X7) | C6: =IFERROR(VLOOKUP(B6,法术大全!$A:$W,5,FALSE),"") | D6: =IFERROR(VLOOKUP(B6,法术大全!$A:$W,4,FALSE),"") | E6: 5 | F6: {=IFERROR(INDEX($B$1:$B$301,SMALL(IF($B$1:$B$301<>"",ROW($B$1:$B$301),4^8),ROW(6:6)))&"","")} | H6: =IF(主要!Q70<>"",主要!Q70,"") | I6: =IF(VLOOKUP(H6,法术大全!$A$3:$E$864,4,0)="√",1,0) -> 0 | J6: =IF(VLOOKUP(H6,法术大全!$A$3:$E$864,5,0)="√",1,0) -> 0 | K6: {=IFERROR(INDEX($H$1:$H$68,SMALL(IF($H$2:$H$68<>"",ROW($H$2:$H$68),4^8),ROW(6:6)))&"","")} | M6: 矮人语 | O6: 游侠 | P6: 2 | Q6: 3 | R6: 4 | S6: 5 | T6: 6 | U6: 6 | V6: 7 | W6: 7 | X6: 9 | Y6: 9 | Z6: 10 | AA6: 10 | AB6: 11 | AC6: 11 | AD6: 12 | AE6: 12 | AF6: 14 | AG6: 14 | AH6: 15 | AI6: 15 | AJ6: =职业!$AZ$9 -> 0 | CI6: =CI5*CJ5 -> 2700 | CJ6: 4 | CK6: 4环 | CL6: 4 | CM6: 5 | CN6: 3 | CO6: 1 | CP6: 2
A7: 6 | B7: =IF(法术书!X8="","",法术书!X8) | C7: =IFERROR(VLOOKUP(B7,法术大全!$A:$W,5,FALSE),"") | D7: =IFERROR(VLOOKUP(B7,法术大全!$A:$W,4,FALSE),"") | E7: 6 | F7: {=IFERROR(INDEX($B$1:$B$301,SMALL(IF($B$1:$B$301<>"",ROW($B$1:$B$301),4^8),ROW(7:7)))&"","")} | H7: =IF(主要!Q71<>"",主要!Q71,"") | I7: =IF(VLOOKUP(H7,法术大全!$A$3:$E$864,4,0)="√",1,0) -> 0 | J7: =IF(VLOOKUP(H7,法术大全!$A$3:$E$864,5,0)="√",1,0) -> 0 | K7: {=IFERROR(INDEX($H$1:$H$68,SMALL(IF($H$2:$H$68<>"",ROW($H$2:$H$68),4^8),ROW(7:7)))&"","")} | M7: 精灵语 | O7: 术士 | P7: 2 | Q7: 4 | R7: 6 | S7: 7 | T7: 9 | U7: 10 | V7: 11 | W7: 12 | X7: 14 | Y7: 15 | Z7: 16 | AA7: 16 | AB7: 17 | AC7: 17 | AD7: 18 | AE7: 18 | AF7: 19 | AG7: 20 | AH7: 21 | AI7: 22 | AJ7: =职业!$AZ$11 -> 0 | CI7: 6500 | CJ7: 5 | CK7: 5环 | CL7: 5 | CM7: 6 | CN7: 3 | CO7: 2 | CP7: 2
A8: 7 | B8: =IF(法术书!X9="","",法术书!X9) | C8: =IFERROR(VLOOKUP(B8,法术大全!$A:$W,5,FALSE),"") | D8: =IFERROR(VLOOKUP(B8,法术大全!$A:$W,4,FALSE),"") | E8: 7 | F8: {=IFERROR(INDEX($B$1:$B$301,SMALL(IF($B$1:$B$301<>"",ROW($B$1:$B$301),4^8),ROW(8:8)))&"","")} | H8: =IF(主要!Q72<>"",主要!Q72,"") | I8: =IF(VLOOKUP(H8,法术大全!$A$3:$E$864,4,0)="√",1,0) -> 0 | J8: =IF(VLOOKUP(H8,法术大全!$A$3:$E$864,5,0)="√",1,0) -> 0 | K8: {=IFERROR(INDEX($H$1:$H$68,SMALL(IF($H$2:$H$68<>"",ROW($H$2:$H$68),4^8),ROW(8:8)))&"","")} | M8: 巨人语 | O8: 魔契师 | P8: 2 | Q8: 3 | R8: 4 | S8: 5 | T8: 6 | U8: 7 | V8: 8 | W8: 9 | X8: 10 | Y8: 10 | Z8: 11 | AA8: 11 | AB8: 12 | AC8: 12 | AD8: 13 | AE8: 13 | AF8: 14 | AG8: 14 | AH8: 15 | AI8: 15 | AJ8: =职业!$AZ$12 -> 0 | CI8: 14000 | CJ8: 6 | CK8: 6环 | CL8: 6 | CM8: 7 | CN8: 3 | CO8: 3 | CP8: 2
A9: 8 | B9: =IF(法术书!X10="","",法术书!X10) | C9: =IFERROR(VLOOKUP(B9,法术大全!$A:$W,5,FALSE),"") | D9: =IFERROR(VLOOKUP(B9,法术大全!$A:$W,4,FALSE),"") | E9: 8 | F9: {=IFERROR(INDEX($B$1:$B$301,SMALL(IF($B$1:$B$301<>"",ROW($B$1:$B$301),4^8),ROW(9:9)))&"","")} | H9: =IF(主要!Q73<>"",主要!Q73,"") | I9: =IF(VLOOKUP(H9,法术大全!$A$3:$E$864,4,0)="√",1,0) -> 0 | J9: =IF(VLOOKUP(H9,法术大全!$A$3:$E$864,5,0)="√",1,0) -> 0 | K9: {=IFERROR(INDEX($H$1:$H$68,SMALL(IF($H$2:$H$68<>"",ROW($H$2:$H$68),4^8),ROW(9:9)))&"","")} | M9: 侏儒语 | O9: 法师 | P9: 4 | Q9: 5 | R9: 6 | S9: 7 | T9: 9 | U9: 10 | V9: 11 | W9: 12 | X9: 14 | Y9: 15 | Z9: 16 | AA9: 16 | AB9: 17 | AC9: 18 | AD9: 19 | AE9: 21 | AF9: 22 | AG9: 23 | AH9: 24 | AI9: 25 | AJ9: =职业!$AZ$13 -> 0 | CI9: 23000 | CJ9: 7 | CK9: 7环 | CL9: 7 | CM9: 8 | CN9: 3 | CO9: 4 | CP9: 2
A10: 9 | B10: =IF(法术书!X11="","",法术书!X11) | C10: =IFERROR(VLOOKUP(B10,法术大全!$A:$W,5,FALSE),"") | D10: =IFERROR(VLOOKUP(B10,法术大全!$A:$W,4,FALSE),"") | E10: 9 | F10: {=IFERROR(INDEX($B$1:$B$301,SMALL(IF($B$1:$B$301<>"",ROW($B$1:$B$301),4^8),ROW(10:10)))&"","")} | G10: 戏法1 | H10: =IF(主要!Q77<>"",主要!Q77,"") | I10: =IF(VLOOKUP(H10,法术大全!$A$3:$E$864,4,0)="√",1,0) -> 0 | J10: =IF(VLOOKUP(H10,法术大全!$A$3:$E$864,5,0)="√",1,0) -> 0 | K10: {=IFERROR(INDEX($H$1:$H$68,SMALL(IF($H$2:$H$68<>"",ROW($H$2:$H$68),4^8),ROW(10:10)))&"","")} | M10: 地精语 | O10: 奇械师 | P10: 2 | Q10: 3 | R10: 4 | S10: 5 | T10: 6 | U10: 6 | V10: 7 | W10: 7 | X10: 9 | Y10: 9 | Z10: 10 | AA10: 10 | AB10: 11 | AC10: 11 | AD10: 12 | AE10: 12 | AF10: 14 | AG10: 14 | AH10: 15 | AI10: 15 | AJ10: =职业!$AZ$14 -> 0 | CI10: 34000 | CJ10: 8 | CK10: 8环 | CL10: 8 | CM10: 9 | CN10: 4 | CO10: 5 | CP10: 3
A11: 10 | B11: =IF(法术书!X12="","",法术书!X12) | C11: =IFERROR(VLOOKUP(B11,法术大全!$A:$W,5,FALSE),"") | D11: =IFERROR(VLOOKUP(B11,法术大全!$A:$W,4,FALSE),"") | E11: 10 | F11: {=IFERROR(INDEX($B$1:$B$301,SMALL(IF($B$1:$B$301<>"",ROW($B$1:$B$301),4^8),ROW(11:11)))&"","")} | H11: =IF(主要!Q78<>"",主要!Q78,"") | I11: =IF(VLOOKUP(H11,法术大全!$A$3:$E$864,4,0)="√",1,0) -> 0 | J11: =IF(VLOOKUP(H11,法术大全!$A$3:$E$864,5,0)="√",1,0) -> 0 | K11: {=IFERROR(INDEX($H$1:$H$68,SMALL(IF($H$2:$H$68<>"",ROW($H$2:$H$68),4^8),ROW(11:11)))&"","")} | M11: 半身人语 | O11: 药剂师 | P11: =职业!$AZ$17+主要!$R$16 -> 0 | Q11: =职业!$AZ$17+主要!$R$16 -> 0 | R11: =职业!$AZ$17+主要!$R$16 -> 0 | S11: =职业!$AZ$17+主要!$R$16 -> 0 | T11: =职业!$AZ$17+主要!$R$16 -> 0 | U11: =职业!$AZ$17+主要!$R$16 -> 0 | V11: =职业!$AZ$17+主要!$R$16 -> 0 | W11: =职业!$AZ$17+主要!$R$16 -> 0 | ... AI11: =职业!$AZ$17+主要!$R$16 -> 0 | AJ11: =职业!$AZ$17 -> 0 | CI11: 48000 | CJ11: 9 | CK11: 9环 | CL11: 9 | CM11: 10 | CN11: 4 | CO11: 6 | CP11: 3
A12: 11 | B12: =IF(法术书!X13="","",法术书!X13) | C12: =IFERROR(VLOOKUP(B12,法术大全!$A:$W,5,FALSE),"") | D12: =IFERROR(VLOOKUP(B12,法术大全!$A:$W,4,FALSE),"") | E12: 11 | F12: {=IFERROR(INDEX($B$1:$B$301,SMALL(IF($B$1:$B$301<>"",ROW($B$1:$B$301),4^8),ROW(12:12)))&"","")} | H12: =IF(主要!Q79<>"",主要!Q79,"") | I12: =IF(VLOOKUP(H12,法术大全!$A$3:$E$864,4,0)="√",1,0) -> 0 | J12: =IF(VLOOKUP(H12,法术大全!$A$3:$E$864,5,0)="√",1,0) -> 0 | K12: {=IFERROR(INDEX($H$1:$H$68,SMALL(IF($H$2:$H$68<>"",ROW($H$2:$H$68),4^8),ROW(12:12)))&"","")} | M12: 兽人语 | O12: 灵能使 | P12: 4 | Q12: 5 | R12: 6 | S12: 7 | T12: 9 | U12: 10 | V12: 11 | W12: 12 | X12: 14 | Y12: 15 | Z12: 16 | AA12: 16 | AB12: 17 | AC12: 17 | AD12: 18 | AE12: 18 | AF12: 19 | AG12: 20 | AH12: 21 | AI12: 22 | AJ12: =职业!$AZ$15 -> 0 | CI12: 64000 | CJ12: 10 | CM12: 11 | CN12: 4 | CO12: 7 | CP12: 3
A13: 12 | B13: =IF(法术书!X14="","",法术书!X14) | C13: =IFERROR(VLOOKUP(B13,法术大全!$A:$W,5,FALSE),"") | D13: =IFERROR(VLOOKUP(B13,法术大全!$A:$W,4,FALSE),"") | E13: 12 | F13: {=IFERROR(INDEX($B$1:$B$301,SMALL(IF($B$1:$B$301<>"",ROW($B$1:$B$301),4^8),ROW(13:13)))&"","")} | H13: =IF(主要!Q80<>"",主要!Q80,"") | I13: =IF(VLOOKUP(H13,法术大全!$A$3:$E$864,4,0)="√",1,0) -> 0 | J13: =IF(VLOOKUP(H13,法术大全!$A$3:$E$864,5,0)="√",1,0) -> 0 | K13: {=IFERROR(INDEX($H$1:$H$68,SMALL(IF($H$2:$H$68<>"",ROW($H$2:$H$68),4^8),ROW(13:13)))&"","")} | M13: —稀有语言— | O13: 奥法骑士 | P13: 0 | Q13: 0 | R13: 3 | S13: 4 | T13: 4 | U13: 4 | V13: 5 | W13: 6 | X13: 6 | Y13: 7 | Z13: 8 | AA13: 8 | AB13: 9 | AC13: 10 | AD13: 10 | AE13: 11 | AF13: 11 | AG13: 11 | AH13: 12 | AI13: 13 | AJ13: =职业!$BB$6 -> 0 | CI13: 85000 | CJ13: 11 | CM13: 12 | CN13: 4 | CO13: 8 | CP13: 3
A14: 13 | B14: =IF(法术书!X15="","",法术书!X15) | C14: =IFERROR(VLOOKUP(B14,法术大全!$A:$W,5,FALSE),"") | D14: =IFERROR(VLOOKUP(B14,法术大全!$A:$W,4,FALSE),"") | E14: 13 | F14: {=IFERROR(INDEX($B$1:$B$301,SMALL(IF($B$1:$B$301<>"",ROW($B$1:$B$301),4^8),ROW(14:14)))&"","")} | H14: =IF(主要!Q81<>"",主要!Q81,"") | I14: =IF(VLOOKUP(H14,法术大全!$A$3:$E$864,4,0)="√",1,0) -> 0 | J14: =IF(VLOOKUP(H14,法术大全!$A$3:$E$864,5,0)="√",1,0) -> 0 | K14: {=IFERROR(INDEX($H$1:$H$68,SMALL(IF($H$2:$H$68<>"",ROW($H$2:$H$68),4^8),ROW(14:14)))&"","")} | M14: 深渊语 | O14: 诡术师 | P14: 0 | Q14: 0 | R14: 3 | S14: 4 | T14: 4 | U14: 4 | V14: 5 | W14: 6 | X14: 6 | Y14: 7 | Z14: 8 | AA14: 8 | AB14: 9 | AC14: 10 | AD14: 10 | AE14: 11 | AF14: 11 | AG14: 11 | AH14: 12 | AI14: 13 | AJ14: =职业!$BB$7 -> 0 | CI14: 100000 | CJ14: 12 | CM14: 13 | CN14: 5 | CO14: 9 | CP14: 4
A15: 14 | B15: =IF(法术书!X16="","",法术书!X16) | C15: =IFERROR(VLOOKUP(B15,法术大全!$A:$W,5,FALSE),"") | D15: =IFERROR(VLOOKUP(B15,法术大全!$A:$W,4,FALSE),"") | E15: 14 | F15: {=IFERROR(INDEX($B$1:$B$301,SMALL(IF($B$1:$B$301<>"",ROW($B$1:$B$301),4^8),ROW(15:15)))&"","")} | G15: 戏法2 | H15: =IF(主要!Y77<>"",主要!Y77,"") | I15: =IF(VLOOKUP(H15,法术大全!$A$3:$E$864,4,0)="√",1,0) -> 0 | J15: =IF(VLOOKUP(H15,法术大全!$A$3:$E$864,5,0)="√",1,0) -> 0 | K15: {=IFERROR(INDEX($H$1:$H$68,SMALL(IF($H$2:$H$68<>"",ROW($H$2:$H$68),4^8),ROW(15:15)))&"","")} | M15: 天界语 | O15: 渎魂圣约 | P15: 0 | Q15: 0 | R15: 2 | S15: 2 | T15: 3 | U15: 3 | V15: 4 | W15: 4 | X15: 5 | Y15: 5 | Z15: 6 | AA15: 6 | AB15: 7 | AC15: 7 | AD15: 8 | AE15: 8 | AF15: 9 | AG15: 9 | AH15: 10 | AI15: 11 | AJ15: =职业!$AX$17 -> 0 | AO15: 特性 | AX15: HD | AZ15: 数量 | CI15: 120000 | CJ15: 13 | CL15: 体型 | CM15: 14 | CN15: 5 | CO15: 10 | CP15: 4
A16: 15 | B16: =IF(法术书!X17="","",法术书!X17) | C16: =IFERROR(VLOOKUP(B16,法术大全!$A:$W,5,FALSE),"") | D16: =IFERROR(VLOOKUP(B16,法术大全!$A:$W,4,FALSE),"") | E16: 15 | F16: {=IFERROR(INDEX($B$1:$B$301,SMALL(IF($B$1:$B$301<>"",ROW($B$1:$B$301),4^8),ROW(16:16)))&"","")} | H16: =IF(主要!Y78<>"",主要!Y78,"") | I16: =IF(VLOOKUP(H16,法术大全!$A$3:$E$864,4,0)="√",1,0) -> 0 | J16: =IF(VLOOKUP(H16,法术大全!$A$3:$E$864,5,0)="√",1,0) -> 0 | K16: {=IFERROR(INDEX($H$1:$H$68,SMALL(IF($H$2:$H$68<>"",ROW($H$2:$H$68),4^8),ROW(16:16)))&"","")} | M16: 深潜语 | O16: 筑灭师 | P16: 0 | Q16: 0 | R16: 3 | S16: 4 | T16: 4 | U16: 4 | V16: 5 | W16: 6 | X16: 6 | Y16: 7 | Z16: 8 | AA16: 8 | AB16: 9 | AC16: 10 | AD16: 10 | AE16: 11 | AF16: 11 | AG16: 11 | AH16: 12 | AI16: 13 | AJ16: =职业!$BB$8 -> 0 | AX16: D6 | CI16: 140000 | CJ16: 14 | CL16: 微型 | CM16: 15 | CN16: 5 | CO16: 11 | CP16: 4
A17: 16 | B17: =IF(法术书!X18="","",法术书!X18) | C17: =IFERROR(VLOOKUP(B17,法术大全!$A:$W,5,FALSE),"") | D17: =IFERROR(VLOOKUP(B17,法术大全!$A:$W,4,FALSE),"") | E17: 16 | F17: {=IFERROR(INDEX($B$1:$B$301,SMALL(IF($B$1:$B$301<>"",ROW($B$1:$B$301),4^8),ROW(17:17)))&"","")} | H17: =IF(主要!Y79<>"",主要!Y79,"") | I17: =IF(VLOOKUP(H17,法术大全!$A$3:$E$864,4,0)="√",1,0) -> 0 | J17: =IF(VLOOKUP(H17,法术大全!$A$3:$E$864,5,0)="√",1,0) -> 0 | K17: {=IFERROR(INDEX($H$1:$H$68,SMALL(IF($H$2:$H$68<>"",ROW($H$2:$H$68),4^8),ROW(17:17)))&"","")} | M17: 德鲁伊语 | O17: 魔弹客 | P17: 0 | Q17: 0 | R17: 3 | S17: 4 | T17: 4 | U17: 4 | V17: 5 | W17: 6 | X17: 6 | Y17: 7 | Z17: 8 | AA17: 8 | AB17: 9 | AC17: 10 | AD17: 10 | AE17: 11 | AF17: 11 | AG17: 11 | AH17: 12 | AI17: 13 | AJ17: =职业!$BB$9 -> 0 | AX17: D8 | CI17: 165000 | CJ17: 15 | CL17: 小型 | CM17: 16 | CN17: 5 | CO17: 12 | CP17: 4
A18: 17 | B18: =IF(法术书!X19="","",法术书!X19) | C18: =IFERROR(VLOOKUP(B18,法术大全!$A:$W,5,FALSE),"") | D18: =IFERROR(VLOOKUP(B18,法术大全!$A:$W,4,FALSE),"") | E18: 17 | F18: {=IFERROR(INDEX($B$1:$B$301,SMALL(IF($B$1:$B$301<>"",ROW($B$1:$B$301),4^8),ROW(18:18)))&"","")} | H18: =IF(主要!Y80<>"",主要!Y80,"") | I18: =IF(VLOOKUP(H18,法术大全!$A$3:$E$864,4,0)="√",1,0) -> 0 | J18: =IF(VLOOKUP(H18,法术大全!$A$3:$E$864,5,0)="√",1,0) -> 0 | K18: {=IFERROR(INDEX($H$1:$H$68,SMALL(IF($H$2:$H$68<>"",ROW($H$2:$H$68),4^8),ROW(18:18)))&"","")} | M18: 炼狱语 | O18: 织法宗 | P18: 0 | Q18: 0 | R18: 3 | S18: 4 | T18: 4 | U18: 4 | V18: 5 | W18: 6 | X18: 6 | Y18: 7 | Z18: 8 | AA18: 8 | AB18: 9 | AC18: 10 | AD18: 10 | AE18: 11 | AF18: 11 | AG18: 11 | AH18: 12 | AI18: 13 | AJ18: =职业!$BB$10 -> 0 | AX18: D10 | CI18: 195000 | CJ18: 16 | CL18: 中型 | CM18: 17 | CN18: 6 | CO18: 13 | CP18: 5
A19: 18 | B19: =IF(法术书!X20="","",法术书!X20) | C19: =IFERROR(VLOOKUP(B19,法术大全!$A:$W,5,FALSE),"") | D19: =IFERROR(VLOOKUP(B19,法术大全!$A:$W,4,FALSE),"") | E19: 18 | F19: {=IFERROR(INDEX($B$1:$B$301,SMALL(IF($B$1:$B$301<>"",ROW($B$1:$B$301),4^8),ROW(19:19)))&"","")} | H19: =IF(主要!Y81<>"",主要!Y81,"") | I19: =IF(VLOOKUP(H19,法术大全!$A$3:$E$864,4,0)="√",1,0) -> 0 | J19: =IF(VLOOKUP(H19,法术大全!$A$3:$E$864,5,0)="√",1,0) -> 0 | K19: {=IFERROR(INDEX($H$1:$H$68,SMALL(IF($H$2:$H$68<>"",ROW($H$2:$H$68),4^8),ROW(19:19)))&"","")} | M19: 原初语 | O19: 秘术武者 | P19: 0 | Q19: 0 | R19: 3 | S19: 4 | T19: 4 | U19: 4 | V19: 5 | W19: 6 | X19: 6 | Y19: 7 | Z19: 8 | AA19: 8 | AB19: 9 | AC19: 10 | AD19: 10 | AE19: 11 | AF19: 11 | AG19: 11 | AH19: 12 | AI19: 13 | AJ19: =职业!$BB$11 -> 0 | CI19: 225000 | CJ19: 17 | CL19: 大型 | CM19: 18 | CN19: 6 | CO19: 14 | CP19: 5
A20: 19 | B20: =IF(法术书!X21="","",法术书!X21) | C20: =IFERROR(VLOOKUP(B20,法术大全!$A:$W,5,FALSE),"") | D20: =IFERROR(VLOOKUP(B20,法术大全!$A:$W,4,FALSE),"") | E20: 19 | F20: {=IFERROR(INDEX($B$1:$B$301,SMALL(IF($B$1:$B$301<>"",ROW($B$1:$B$301),4^8),ROW(20:20)))&"","")} | G20: 列1 | H20: =IF(主要!Y66<>"",主要!Y66,"") | I20: =IF(VLOOKUP(H20,法术大全!$A$3:$E$864,4,0)="√",1,0) -> 0 | J20: =IF(VLOOKUP(H20,法术大全!$A$3:$E$864,5,0)="√",1,0) -> 0 | K20: {=IFERROR(INDEX($H$1:$H$68,SMALL(IF($H$2:$H$68<>"",ROW($H$2:$H$68),4^8),ROW(20:20)))&"","")} | M20: 木族语 | CI20: 265000 | CJ20: 18 | CL20: 巨型 | CM20: 19 | CN20: 6 | CO20: 15 | CP20: 5
A21: 20 | B21: =IF(法术书!X22="","",法术书!X22) | C21: =IFERROR(VLOOKUP(B21,法术大全!$A:$W,5,FALSE),"") | D21: =IFERROR(VLOOKUP(B21,法术大全!$A:$W,4,FALSE),"") | E21: 20 | F21: {=IFERROR(INDEX($B$1:$B$301,SMALL(IF($B$1:$B$301<>"",ROW($B$1:$B$301),4^8),ROW(21:21)))&"","")} | H21: =IF(主要!Y67<>"",主要!Y67,"") | I21: =IF(VLOOKUP(H21,法术大全!$A$3:$E$864,4,0)="√",1,0) -> 0 | J21: =IF(VLOOKUP(H21,法术大全!$A$3:$E$864,5,0)="√",1,0) -> 0 | K21: {=IFERROR(INDEX($H$1:$H$68,SMALL(IF($H$2:$H$68<>"",ROW($H$2:$H$68),4^8),ROW(21:21)))&"","")} | M21: 盗贼黑话 | AL21: ———随身钱币——— | CI21: 305000 | CJ21: 19 | CL21: 超巨型 | CM21: 20 | CN21: 6 | CO21: 16 | CP21: 5
A22: 21 | B22: =IF(法术书!X23="","",法术书!X23) | C22: =IFERROR(VLOOKUP(B22,法术大全!$A:$W,5,FALSE),"") | D22: =IFERROR(VLOOKUP(B22,法术大全!$A:$W,4,FALSE),"") | E22: 21 | F22: {=IFERROR(INDEX($B$1:$B$301,SMALL(IF($B$1:$B$301<>"",ROW($B$1:$B$301),4^8),ROW(22:22)))&"","")} | H22: =IF(主要!Y68<>"",主要!Y68,"") | I22: =IF(VLOOKUP(H22,法术大全!$A$3:$E$864,4,0)="√",1,0) -> 0 | J22: =IF(VLOOKUP(H22,法术大全!$A$3:$E$864,5,0)="√",1,0) -> 0 | K22: {=IFERROR(INDEX($H$1:$H$68,SMALL(IF($H$2:$H$68<>"",ROW($H$2:$H$68),4^8),ROW(22:22)))&"","")} | M22: 地底通用语 | O22: 主职业 | P22: =主要!E6 -> 0 | Q22: =IFERROR(VLOOKUP(P22,$O$2:$AI$11,主要!O6+1,0),"") | AL22: CP | AS22: SP | AZ22: EP | BG22: GP | BN22: PP | BU22: 总计 | BX22: =CONCATENATE(SUM(BP22*10+BB22/2+BI22+AU22/10+AN22/100),"GP") -> 0GP | CI22: 355000 | CJ22: 20 | CO22: 17 | CP22: 6
A23: 22 | B23: =IF(法术书!X24="","",法术书!X24) | C23: =IFERROR(VLOOKUP(B23,法术大全!$A:$W,5,FALSE),"") | D23: =IFERROR(VLOOKUP(B23,法术大全!$A:$W,4,FALSE),"") | E23: 22 | F23: {=IFERROR(INDEX($B$1:$B$301,SMALL(IF($B$1:$B$301<>"",ROW($B$1:$B$301),4^8),ROW(23:23)))&"","")} | H23: =IF(主要!Y69<>"",主要!Y69,"") | I23: =IF(VLOOKUP(H23,法术大全!$A$3:$E$864,4,0)="√",1,0) -> 0 | J23: =IF(VLOOKUP(H23,法术大全!$A$3:$E$864,5,0)="√",1,0) -> 0 | K23: {=IFERROR(INDEX($H$1:$H$68,SMALL(IF($H$2:$H$68<>"",ROW($H$2:$H$68),4^8),ROW(23:23)))&"","")} | O23: 兼职1 | P23: =主要!E7 -> 0 | Q23: =IFERROR(VLOOKUP(P23,$O$2:$AI$11,主要!O7+1,0),"") | CI23: =_xlfn.XLOOKUP(VLOOKUP(主要!E9,CI3:CJ22,2,TRUE), CJ3:CJ22, CI3:CI22, 0) -> 0 | CJ23: =_xlfn.XLOOKUP(VLOOKUP(主要!E9,CI3:CJ22,2,TRUE)+1, CJ3:CJ22, CI3:CI22, 355000) -> 300 | CO23: 18 | CP23: 6
A24: 23 | B24: =IF(法术书!X25="","",法术书!X25) | C24: =IFERROR(VLOOKUP(B24,法术大全!$A:$W,5,FALSE),"") | D24: =IFERROR(VLOOKUP(B24,法术大全!$A:$W,4,FALSE),"") | E24: 23 | F24: {=IFERROR(INDEX($B$1:$B$301,SMALL(IF($B$1:$B$301<>"",ROW($B$1:$B$301),4^8),ROW(24:24)))&"","")} | H24: =IF(主要!Y70<>"",主要!Y70,"") | I24: =IF(VLOOKUP(H24,法术大全!$A$3:$E$864,4,0)="√",1,0) -> 0 | J24: =IF(VLOOKUP(H24,法术大全!$A$3:$E$864,5,0)="√",1,0) -> 0 | K24: {=IFERROR(INDEX($H$1:$H$68,SMALL(IF($H$2:$H$68<>"",ROW($H$2:$H$68),4^8),ROW(24:24)))&"","")} | O24: 兼职2 | P24: =主要!E8 -> 0 | Q24: =IFERROR(VLOOKUP(P24,$O$2:$AI$11,主要!O8+1,0),"") | CO24: 19 | CP24: 6
A25: 24 | B25: =IF(法术书!X26="","",法术书!X26) | C25: =IFERROR(VLOOKUP(B25,法术大全!$A:$W,5,FALSE),"") | D25: =IFERROR(VLOOKUP(B25,法术大全!$A:$W,4,FALSE),"") | E25: 24 | F25: {=IFERROR(INDEX($B$1:$B$301,SMALL(IF($B$1:$B$301<>"",ROW($B$1:$B$301),4^8),ROW(25:25)))&"","")} | H25: =IF(主要!Y71<>"",主要!Y71,"") | I25: =IF(VLOOKUP(H25,法术大全!$A$3:$E$864,4,0)="√",1,0) -> 0 | J25: =IF(VLOOKUP(H25,法术大全!$A$3:$E$864,5,0)="√",1,0) -> 0 | K25: {=IFERROR(INDEX($H$1:$H$68,SMALL(IF($H$2:$H$68<>"",ROW($H$2:$H$68),4^8),ROW(25:25)))&"","")} | CO25: 20 | CP25: 6
A26: 25 | B26: =IF(法术书!X27="","",法术书!X27) | C26: =IFERROR(VLOOKUP(B26,法术大全!$A:$W,5,FALSE),"") | D26: =IFERROR(VLOOKUP(B26,法术大全!$A:$W,4,FALSE),"") | E26: 25 | F26: {=IFERROR(INDEX($B$1:$B$301,SMALL(IF($B$1:$B$301<>"",ROW($B$1:$B$301),4^8),ROW(26:26)))&"","")} | H26: =IF(主要!Y72<>"",主要!Y72,"") | I26: =IF(VLOOKUP(H26,法术大全!$A$3:$E$864,4,0)="√",1,0) -> 0 | J26: =IF(VLOOKUP(H26,法术大全!$A$3:$E$864,5,0)="√",1,0) -> 0 | K26: {=IFERROR(INDEX($H$1:$H$68,SMALL(IF($H$2:$H$68<>"",ROW($H$2:$H$68),4^8),ROW(26:26)))&"","")} | O26: 准备法术 | P26: =IFERROR(VLOOKUP(主要!$B$70,$O$2:$AI$19, IF(VLOOKUP(主要!$B$70,$O$2:$AJ$19,22,FALSE)=0,"",VLOOKUP(主要!$B$70,$O$2:$AJ$19,22,FALSE)+1), FALSE),"") | AL26: 背包 | BP26: 重量 | BS26: 重量 | BV26: 重量 | BY26: 重量 | CB26: 重量 | CO26: 21 | CP26: 7
A27: 26 | B27: =IF(法术书!X28="","",法术书!X28) | C27: =IFERROR(VLOOKUP(B27,法术大全!$A:$W,5,FALSE),"") | D27: =IFERROR(VLOOKUP(B27,法术大全!$A:$W,4,FALSE),"") | E27: 26 | F27: {=IFERROR(INDEX($B$1:$B$301,SMALL(IF($B$1:$B$301<>"",ROW($B$1:$B$301),4^8),ROW(27:27)))&"","")} | H27: =IF(主要!Y73<>"",主要!Y73,"") | I27: =IF(VLOOKUP(H27,法术大全!$A$3:$E$864,4,0)="√",1,0) -> 0 | J27: =IF(VLOOKUP(H27,法术大全!$A$3:$E$864,5,0)="√",1,0) -> 0 | K27: {=IFERROR(INDEX($H$1:$H$68,SMALL(IF($H$2:$H$68<>"",ROW($H$2:$H$68),4^8),ROW(27:27)))&"","")} | R27: =IFERROR(VLOOKUP(主要!$B$70,$O$2:$AI$19, IF(VLOOKUP(主要!$B$70,职业!$AY$2:$AZ$20,2,FALSE)=0,"",VLOOKUP(主要!$B$70,职业!$AY$2:$AZ$20,2,FALSE)+1), FALSE),"") | AL27: 装备 | AR27: 稀有度 | AU27: 部位 | AW27: 描述 | BP27: =装备!AX12 | BS27: =IF(主要!AS40="否","",6) | BV27: =装备!AY2 | CO27: 22 | CP27: 7
A28: 27 | B28: =IF(法术书!X29="","",法术书!X29) | C28: =IFERROR(VLOOKUP(B28,法术大全!$A:$W,5,FALSE),"") | D28: =IFERROR(VLOOKUP(B28,法术大全!$A:$W,4,FALSE),"") | E28: 27 | F28: {=IFERROR(INDEX($B$1:$B$301,SMALL(IF($B$1:$B$301<>"",ROW($B$1:$B$301),4^8),ROW(28:28)))&"","")} | G28: 列2 | H28: =IF(主要!AG66<>"",主要!AG66,"") | I28: =IF(VLOOKUP(H28,法术大全!$A$3:$E$864,4,0)="√",1,0) -> 0 | J28: =IF(VLOOKUP(H28,法术大全!$A$3:$E$864,5,0)="√",1,0) -> 0 | K28: {=IFERROR(INDEX($H$1:$H$68,SMALL(IF($H$2:$H$68<>"",ROW($H$2:$H$68),4^8),ROW(28:28)))&"","")} | AQ28: > | BV28: =装备!AY3 | CO28: 23 | CP28: 7
A29: 28 | B29: =IF(法术书!X30="","",法术书!X30) | C29: =IFERROR(VLOOKUP(B29,法术大全!$A:$W,5,FALSE),"") | D29: =IFERROR(VLOOKUP(B29,法术大全!$A:$W,4,FALSE),"") | E29: 28 | F29: {=IFERROR(INDEX($B$1:$B$301,SMALL(IF($B$1:$B$301<>"",ROW($B$1:$B$301),4^8),ROW(29:29)))&"","")} | H29: =IF(主要!AG67<>"",主要!AG67,"") | I29: =IF(VLOOKUP(H29,法术大全!$A$3:$E$864,4,0)="√",1,0) -> 0 | J29: =IF(VLOOKUP(H29,法术大全!$A$3:$E$864,5,0)="√",1,0) -> 0 | K29: {=IFERROR(INDEX($H$1:$H$68,SMALL(IF($H$2:$H$68<>"",ROW($H$2:$H$68),4^8),ROW(29:29)))&"","")} | AQ29: > | BV29: =装备!AY4 | CO29: 24 | CP29: 7
A30: 29 | B30: =IF(法术书!X31="","",法术书!X31) | C30: =IFERROR(VLOOKUP(B30,法术大全!$A:$W,5,FALSE),"") | D30: =IFERROR(VLOOKUP(B30,法术大全!$A:$W,4,FALSE),"") | E30: 29 | F30: {=IFERROR(INDEX($B$1:$B$301,SMALL(IF($B$1:$B$301<>"",ROW($B$1:$B$301),4^8),ROW(30:30)))&"","")} | H30: =IF(主要!AG68<>"",主要!AG68,"") | I30: =IF(VLOOKUP(H30,法术大全!$A$3:$E$864,4,0)="√",1,0) -> 0 | J30: =IF(VLOOKUP(H30,法术大全!$A$3:$E$864,5,0)="√",1,0) -> 0 | K30: {=IFERROR(INDEX($H$1:$H$68,SMALL(IF($H$2:$H$68<>"",ROW($H$2:$H$68),4^8),ROW(30:30)))&"","")} | AQ30: > | BV30: =装备!AY5 | CO30: 25 | CP30: 8
A31: 30 | B31: =IF(法术书!X32="","",法术书!X32) | C31: =IFERROR(VLOOKUP(B31,法术大全!$A:$W,5,FALSE),"") | D31: =IFERROR(VLOOKUP(B31,法术大全!$A:$W,4,FALSE),"") | E31: 30 | F31: {=IFERROR(INDEX($B$1:$B$301,SMALL(IF($B$1:$B$301<>"",ROW($B$1:$B$301),4^8),ROW(31:31)))&"","")} | H31: =IF(主要!AG69<>"",主要!AG69,"") | I31: =IF(VLOOKUP(H31,法术大全!$A$3:$E$864,4,0)="√",1,0) -> 0 | J31: =IF(VLOOKUP(H31,法术大全!$A$3:$E$864,5,0)="√",1,0) -> 0 | K31: {=IFERROR(INDEX($H$1:$H$68,SMALL(IF($H$2:$H$68<>"",ROW($H$2:$H$68),4^8),ROW(31:31)))&"","")} | AQ31: > | BV31: =装备!AY6 | CO31: 26 | CP31: 8
A32: 31 | B32: =IF(法术书!X33="","",法术书!X33) | C32: =IFERROR(VLOOKUP(B32,法术大全!$A:$W,5,FALSE),"") | D32: =IFERROR(VLOOKUP(B32,法术大全!$A:$W,4,FALSE),"") | E32: 31 | F32: {=IFERROR(INDEX($B$1:$B$301,SMALL(IF($B$1:$B$301<>"",ROW($B$1:$B$301),4^8),ROW(32:32)))&"","")} | H32: =IF(主要!AG70<>"",主要!AG70,"") | I32: =IF(VLOOKUP(H32,法术大全!$A$3:$E$864,4,0)="√",1,0) -> 0 | J32: =IF(VLOOKUP(H32,法术大全!$A$3:$E$864,5,0)="√",1,0) -> 0 | K32: {=IFERROR(INDEX($H$1:$H$68,SMALL(IF($H$2:$H$68<>"",ROW($H$2:$H$68),4^8),ROW(32:32)))&"","")} | V32: 计算 | AQ32: > | CO32: 27 | CP32: 8
A33: 32 | B33: =IF(法术书!X34="","",法术书!X34) | C33: =IFERROR(VLOOKUP(B33,法术大全!$A:$W,5,FALSE),"") | D33: =IFERROR(VLOOKUP(B33,法术大全!$A:$W,4,FALSE),"") | E33: 32 | F33: {=IFERROR(INDEX($B$1:$B$301,SMALL(IF($B$1:$B$301<>"",ROW($B$1:$B$301),4^8),ROW(33:33)))&"","")} | H33: =IF(主要!AG71<>"",主要!AG71,"") | I33: =IF(VLOOKUP(H33,法术大全!$A$3:$E$864,4,0)="√",1,0) -> 0 | J33: =IF(VLOOKUP(H33,法术大全!$A$3:$E$864,5,0)="√",1,0) -> 0 | K33: {=IFERROR(INDEX($H$1:$H$68,SMALL(IF($H$2:$H$68<>"",ROW($H$2:$H$68),4^8),ROW(33:33)))&"","")} | W33: D6 | X33: D8 | Y33: D10 | Z33: D12 | AL33: 消耗品 | AR33: 描述 | BC33: 数量 | BP33: 隐匿劣势 | BT33: 无 | CO33: 28 | CP33: 8
A34: 33 | B34: =IF(法术书!X35="","",法术书!X35) | C34: =IFERROR(VLOOKUP(B34,法术大全!$A:$W,5,FALSE),"") | D34: =IFERROR(VLOOKUP(B34,法术大全!$A:$W,4,FALSE),"") | E34: 33 | F34: {=IFERROR(INDEX($B$1:$B$301,SMALL(IF($B$1:$B$301<>"",ROW($B$1:$B$301),4^8),ROW(34:34)))&"","")} | H34: =IF(主要!AG72<>"",主要!AG72,"") | I34: =IF(VLOOKUP(H34,法术大全!$A$3:$E$864,4,0)="√",1,0) -> 0 | J34: =IF(VLOOKUP(H34,法术大全!$A$3:$E$864,5,0)="√",1,0) -> 0 | K34: {=IFERROR(INDEX($H$1:$H$68,SMALL(IF($H$2:$H$68<>"",ROW($H$2:$H$68),4^8),ROW(34:34)))&"","")} | P34: 戏法 | Q34: 变化 | R34: 动作 | S34: 触及 | T34: 立即 | W34: =IF(自定义调整栏!$V$23=0,0,SUM($W$35:INDEX($W$35:$W$54,自定义调整栏!$V$23,1))) -> 0 | X34: =IF(自定义调整栏!$X$23=0,0,SUM($X$35:INDEX($X$35:$X$54,自定义调整栏!$X$23,1))) -> 0 | Y34: =IF(自定义调整栏!$Z$23=0,0,SUM($Y$35:INDEX($Y$35:$Y$54,自定义调整栏!$Z$23,1))) -> 0 | Z34: =IF(自定义调整栏!$AB$23=0,0,SUM($Z$35:INDEX($Z$35:$Z$54,自定义调整栏!$AB$23,1))) -> 0 | AQ34: > | BE34: / | CO34: 29 | CP34: 9
A35: 34 | B35: =IF(法术书!X36="","",法术书!X36) | C35: =IFERROR(VLOOKUP(B35,法术大全!$A:$W,5,FALSE),"") | D35: =IFERROR(VLOOKUP(B35,法术大全!$A:$W,4,FALSE),"") | E35: 34 | F35: {=IFERROR(INDEX($B$1:$B$301,SMALL(IF($B$1:$B$301<>"",ROW($B$1:$B$301),4^8),ROW(35:35)))&"","")} | H35: =IF(主要!AG73<>"",主要!AG73,"") | I35: =IF(VLOOKUP(H35,法术大全!$A$3:$E$864,4,0)="√",1,0) -> 0 | J35: =IF(VLOOKUP(H35,法术大全!$A$3:$E$864,5,0)="√",1,0) -> 0 | K35: {=IFERROR(INDEX($H$1:$H$68,SMALL(IF($H$2:$H$68<>"",ROW($H$2:$H$68),4^8),ROW(35:35)))&"","")} | P35: 1 | Q35: 塑能 | R35: 附赠动作 | S35: 自身 | T35: 1轮 | V35: 1 | W35: =RANDBETWEEN(1,6) -> 1 | X35: =RANDBETWEEN(1,8) -> 3 | Y35: =RANDBETWEEN(1,10) -> 6 | Z35: =RANDBETWEEN(1,12) -> 2 | AQ35: > | BE35: / | CO35: 30 | CP35: 9
A36: 35 | B36: =IF(法术书!X37="","",法术书!X37) | C36: =IFERROR(VLOOKUP(B36,法术大全!$A:$W,5,FALSE),"") | D36: =IFERROR(VLOOKUP(B36,法术大全!$A:$W,4,FALSE),"") | E36: 35 | F36: {=IFERROR(INDEX($B$1:$B$301,SMALL(IF($B$1:$B$301<>"",ROW($B$1:$B$301),4^8),ROW(36:36)))&"","")} | H36: =IF(主要!AG74<>"",主要!AG74,"") | I36: =IF(VLOOKUP(H36,法术大全!$A$3:$E$864,4,0)="√",1,0) -> 0 | J36: =IF(VLOOKUP(H36,法术大全!$A$3:$E$864,5,0)="√",1,0) -> 0 | K36: {=IFERROR(INDEX($H$1:$H$68,SMALL(IF($H$2:$H$68<>"",ROW($H$2:$H$68),4^8),ROW(36:36)))&"","")} | P36: 2 | Q36: 防护 | R36: 1分钟 | S36: 15尺 | T36: 1分钟 | V36: 2 | W36: =RANDBETWEEN(1,6) -> 2 | X36: =RANDBETWEEN(1,8) -> 8 | Y36: =RANDBETWEEN(1,10) -> 8 | Z36: =RANDBETWEEN(1,12) -> 12 | AQ36: > | BE36: /
A37: 36 | B37: =IF(法术书!X38="","",法术书!X38) | C37: =IFERROR(VLOOKUP(B37,法术大全!$A:$W,5,FALSE),"") | D37: =IFERROR(VLOOKUP(B37,法术大全!$A:$W,4,FALSE),"") | E37: 36 | F37: {=IFERROR(INDEX($B$1:$B$301,SMALL(IF($B$1:$B$301<>"",ROW($B$1:$B$301),4^8),ROW(37:37)))&"","")} | H37: =IF(主要!AG75<>"",主要!AG75,"") | I37: =IF(VLOOKUP(H37,法术大全!$A$3:$E$864,4,0)="√",1,0) -> 0 | J37: =IF(VLOOKUP(H37,法术大全!$A$3:$E$864,5,0)="√",1,0) -> 0 | K37: {=IFERROR(INDEX($H$1:$H$68,SMALL(IF($H$2:$H$68<>"",ROW($H$2:$H$68),4^8),ROW(37:37)))&"","")} | P37: 3 | Q37: 死灵 | R37: 动作或仪式 | S37: 30尺 | T37: 10分钟 | V37: 3 | W37: =RANDBETWEEN(1,6) -> 4 | X37: =RANDBETWEEN(1,8) -> 6 | Y37: =RANDBETWEEN(1,10) -> 6 | Z37: =RANDBETWEEN(1,12) -> 3 | AQ37: > | BE37: /
A38: 37 | B38: =IF(法术书!X39="","",法术书!X39) | C38: =IFERROR(VLOOKUP(B38,法术大全!$A:$W,5,FALSE),"") | D38: =IFERROR(VLOOKUP(B38,法术大全!$A:$W,4,FALSE),"") | E38: 37 | F38: {=IFERROR(INDEX($B$1:$B$301,SMALL(IF($B$1:$B$301<>"",ROW($B$1:$B$301),4^8),ROW(38:38)))&"","")} | H38: =IF(主要!AG76<>"",主要!AG76,"") | I38: =IF(VLOOKUP(H38,法术大全!$A$3:$E$864,4,0)="√",1,0) -> 0 | J38: =IF(VLOOKUP(H38,法术大全!$A$3:$E$864,5,0)="√",1,0) -> 0 | K38: {=IFERROR(INDEX($H$1:$H$68,SMALL(IF($H$2:$H$68<>"",ROW($H$2:$H$68),4^8),ROW(38:38)))&"","")} | P38: 4 | Q38: 预言 | R38: 1分钟或仪式 | S38: 60尺 | T38: 1小时 | V38: 4 | W38: =RANDBETWEEN(1,6) -> 4 | X38: =RANDBETWEEN(1,8) -> 3 | Y38: =RANDBETWEEN(1,10) -> 3 | Z38: =RANDBETWEEN(1,12) -> 12 | AQ38: > | BE38: /
A39: 38 | B39: =IF(法术书!X40="","",法术书!X40) | C39: =IFERROR(VLOOKUP(B39,法术大全!$A:$W,5,FALSE),"") | D39: =IFERROR(VLOOKUP(B39,法术大全!$A:$W,4,FALSE),"") | E39: 38 | F39: {=IFERROR(INDEX($B$1:$B$301,SMALL(IF($B$1:$B$301<>"",ROW($B$1:$B$301),4^8),ROW(39:39)))&"","")} | H39: =IF(主要!AG77<>"",主要!AG77,"") | I39: =IF(VLOOKUP(H39,法术大全!$A$3:$E$864,4,0)="√",1,0) -> 0 | J39: =IF(VLOOKUP(H39,法术大全!$A$3:$E$864,5,0)="√",1,0) -> 0 | K39: {=IFERROR(INDEX($H$1:$H$68,SMALL(IF($H$2:$H$68<>"",ROW($H$2:$H$68),4^8),ROW(39:39)))&"","")} | P39: 5 | Q39: 咒法 | R39: 10分钟 | S39: 90尺 | T39: 8小时 | V39: 5 | W39: =RANDBETWEEN(1,6) -> 5 | X39: =RANDBETWEEN(1,8) -> 8 | Y39: =RANDBETWEEN(1,10) -> 5 | Z39: =RANDBETWEEN(1,12) -> 2 | AL39: 消耗品 | AR39: 稀有度 | AU39: 描述 | BF39: 数量
A40: 39 | B40: =IF(法术书!X41="","",法术书!X41) | C40: =IFERROR(VLOOKUP(B40,法术大全!$A:$W,5,FALSE),"") | D40: =IFERROR(VLOOKUP(B40,法术大全!$A:$W,4,FALSE),"") | E40: 39 | F40: {=IFERROR(INDEX($B$1:$B$301,SMALL(IF($B$1:$B$301<>"",ROW($B$1:$B$301),4^8),ROW(40:40)))&"","")} | H40: =IF(主要!AG78<>"",主要!AG78,"") | I40: =IF(VLOOKUP(H40,法术大全!$A$3:$E$864,4,0)="√",1,0) -> 0 | J40: =IF(VLOOKUP(H40,法术大全!$A$3:$E$864,5,0)="√",1,0) -> 0 | K40: {=IFERROR(INDEX($H$1:$H$68,SMALL(IF($H$2:$H$68<>"",ROW($H$2:$H$68),4^8),ROW(40:40)))&"","")} | P40: 6 | Q40: 惑控 | R40: 1小时 | S40: 120尺 | T40: 24小时 | V40: 6 | W40: =RANDBETWEEN(1,6) -> 2 | X40: =RANDBETWEEN(1,8) -> 4 | Y40: =RANDBETWEEN(1,10) -> 2 | Z40: =RANDBETWEEN(1,12) -> 9 | AQ40: > | BH40: /
A41: 40 | B41: =IF(法术书!X42="","",法术书!X42) | C41: =IFERROR(VLOOKUP(B41,法术大全!$A:$W,5,FALSE),"") | D41: =IFERROR(VLOOKUP(B41,法术大全!$A:$W,4,FALSE),"") | E41: 40 | F41: {=IFERROR(INDEX($B$1:$B$301,SMALL(IF($B$1:$B$301<>"",ROW($B$1:$B$301),4^8),ROW(41:41)))&"","")} | H41: =IF(主要!AG79<>"",主要!AG79,"") | I41: =IF(VLOOKUP(H41,法术大全!$A$3:$E$864,4,0)="√",1,0) -> 0 | J41: =IF(VLOOKUP(H41,法术大全!$A$3:$E$864,5,0)="√",1,0) -> 0 | K41: {=IFERROR(INDEX($H$1:$H$68,SMALL(IF($H$2:$H$68<>"",ROW($H$2:$H$68),4^8),ROW(41:41)))&"","")} | P41: 7 | Q41: 幻术 | R41: 8小时 | S41: 150尺 | T41: 专注，至多1轮 | V41: 7 | W41: =RANDBETWEEN(1,6) -> 1 | X41: =RANDBETWEEN(1,8) -> 2 | Y41: =RANDBETWEEN(1,10) -> 7 | Z41: =RANDBETWEEN(1,12) -> 7 | AQ41: > | BH41: /
A42: 41 | B42: =IF(法术书!X43="","",法术书!X43) | C42: =IFERROR(VLOOKUP(B42,法术大全!$A:$W,5,FALSE),"") | D42: =IFERROR(VLOOKUP(B42,法术大全!$A:$W,4,FALSE),"") | E42: 41 | F42: {=IFERROR(INDEX($B$1:$B$301,SMALL(IF($B$1:$B$301<>"",ROW($B$1:$B$301),4^8),ROW(42:42)))&"","")} | H42: =IF(主要!AG80<>"",主要!AG80,"") | I42: =IF(VLOOKUP(H42,法术大全!$A$3:$E$864,4,0)="√",1,0) -> 0 | J42: =IF(VLOOKUP(H42,法术大全!$A$3:$E$864,5,0)="√",1,0) -> 0 | K42: {=IFERROR(INDEX($H$1:$H$68,SMALL(IF($H$2:$H$68<>"",ROW($H$2:$H$68),4^8),ROW(42:42)))&"","")} | P42: 8 | S42: 300尺 | T42: 专注，至多1分钟 | V42: 8 | W42: =RANDBETWEEN(1,6) -> 2 | X42: =RANDBETWEEN(1,8) -> 6 | Y42: =RANDBETWEEN(1,10) -> 5 | Z42: =RANDBETWEEN(1,12) -> 11 | AQ42: > | BH42: /
A43: 42 | B43: =IF(法术书!X44="","",法术书!X44) | C43: =IFERROR(VLOOKUP(B43,法术大全!$A:$W,5,FALSE),"") | D43: =IFERROR(VLOOKUP(B43,法术大全!$A:$W,4,FALSE),"") | E43: 42 | F43: {=IFERROR(INDEX($B$1:$B$301,SMALL(IF($B$1:$B$301<>"",ROW($B$1:$B$301),4^8),ROW(43:43)))&"","")} | H43: =IF(主要!AG81<>"",主要!AG81,"") | I43: =IF(VLOOKUP(H43,法术大全!$A$3:$E$864,4,0)="√",1,0) -> 0 | J43: =IF(VLOOKUP(H43,法术大全!$A$3:$E$864,5,0)="√",1,0) -> 0 | K43: {=IFERROR(INDEX($H$1:$H$68,SMALL(IF($H$2:$H$68<>"",ROW($H$2:$H$68),4^8),ROW(43:43)))&"","")} | P43: 9 | S43: 自身(5尺半径) | T43: 专注，至多10分钟 | V43: 9 | W43: =RANDBETWEEN(1,6) -> 6 | X43: =RANDBETWEEN(1,8) -> 8 | Y43: =RANDBETWEEN(1,10) -> 1 | Z43: =RANDBETWEEN(1,12) -> 1 | AQ43: > | BH43: /
A44: 43 | B44: =IF(法术书!X45="","",法术书!X45) | C44: =IFERROR(VLOOKUP(B44,法术大全!$A:$W,5,FALSE),"") | D44: =IFERROR(VLOOKUP(B44,法术大全!$A:$W,4,FALSE),"") | E44: 43 | F44: {=IFERROR(INDEX($B$1:$B$301,SMALL(IF($B$1:$B$301<>"",ROW($B$1:$B$301),4^8),ROW(44:44)))&"","")} | G44: 列3 | H44: =IF(主要!AO66<>"",主要!AO66,"") | I44: =IF(VLOOKUP(H44,法术大全!$A$3:$E$864,4,0)="√",1,0) -> 0 | J44: =IF(VLOOKUP(H44,法术大全!$A$3:$E$864,5,0)="√",1,0) -> 0 | K44: {=IFERROR(INDEX($H$1:$H$68,SMALL(IF($H$2:$H$68<>"",ROW($H$2:$H$68),4^8),ROW(44:44)))&"","")} | S44: 自身(30尺半径) | T44: 专注，至多1小时 | V44: 10 | W44: =RANDBETWEEN(1,6) -> 4 | X44: =RANDBETWEEN(1,8) -> 4 | Y44: =RANDBETWEEN(1,10) -> 5 | Z44: =RANDBETWEEN(1,12) -> 6
A45: 44 | B45: =IF(法术书!X46="","",法术书!X46) | C45: =IFERROR(VLOOKUP(B45,法术大全!$A:$W,5,FALSE),"") | D45: =IFERROR(VLOOKUP(B45,法术大全!$A:$W,4,FALSE),"") | E45: 44 | F45: {=IFERROR(INDEX($B$1:$B$301,SMALL(IF($B$1:$B$301<>"",ROW($B$1:$B$301),4^8),ROW(45:45)))&"","")} | H45: =IF(主要!AO67<>"",主要!AO67,"") | I45: =IF(VLOOKUP(H45,法术大全!$A$3:$E$864,4,0)="√",1,0) -> 0 | J45: =IF(VLOOKUP(H45,法术大全!$A$3:$E$864,5,0)="√",1,0) -> 0 | K45: {=IFERROR(INDEX($H$1:$H$68,SMALL(IF($H$2:$H$68<>"",ROW($H$2:$H$68),4^8),ROW(45:45)))&"","")} | S45: 自身(15尺立方) | T45: 10日 | V45: 11 | W45: =RANDBETWEEN(1,6) -> 6 | X45: =RANDBETWEEN(1,8) -> 5 | Y45: =RANDBETWEEN(1,10) -> 10 | Z45: =RANDBETWEEN(1,12) -> 1
A46: 45 | B46: =IF(法术书!X47="","",法术书!X47) | C46: =IFERROR(VLOOKUP(B46,法术大全!$A:$W,5,FALSE),"") | D46: =IFERROR(VLOOKUP(B46,法术大全!$A:$W,4,FALSE),"") | E46: 45 | F46: {=IFERROR(INDEX($B$1:$B$301,SMALL(IF($B$1:$B$301<>"",ROW($B$1:$B$301),4^8),ROW(46:46)))&"","")} | H46: =IF(主要!AO68<>"",主要!AO68,"") | I46: =IF(VLOOKUP(H46,法术大全!$A$3:$E$864,4,0)="√",1,0) -> 0 | J46: =IF(VLOOKUP(H46,法术大全!$A$3:$E$864,5,0)="√",1,0) -> 0 | K46: {=IFERROR(INDEX($H$1:$H$68,SMALL(IF($H$2:$H$68<>"",ROW($H$2:$H$68),4^8),ROW(46:46)))&"","")} | S46: 自身(30尺锥状) | T46: 7日 | V46: 12 | W46: =RANDBETWEEN(1,6) -> 5 | X46: =RANDBETWEEN(1,8) -> 5 | Y46: =RANDBETWEEN(1,10) -> 3 | Z46: =RANDBETWEEN(1,12) -> 3
A47: 46 | B47: =IF(法术书!X48="","",法术书!X48) | C47: =IFERROR(VLOOKUP(B47,法术大全!$A:$W,5,FALSE),"") | D47: =IFERROR(VLOOKUP(B47,法术大全!$A:$W,4,FALSE),"") | E47: 46 | F47: {=IFERROR(INDEX($B$1:$B$301,SMALL(IF($B$1:$B$301<>"",ROW($B$1:$B$301),4^8),ROW(47:47)))&"","")} | H47: =IF(主要!AO69<>"",主要!AO69,"") | I47: =IF(VLOOKUP(H47,法术大全!$A$3:$E$864,4,0)="√",1,0) -> 0 | J47: =IF(VLOOKUP(H47,法术大全!$A$3:$E$864,5,0)="√",1,0) -> 0 | K47: {=IFERROR(INDEX($H$1:$H$68,SMALL(IF($H$2:$H$68<>"",ROW($H$2:$H$68),4^8),ROW(47:47)))&"","")} | S47: 自身(30尺线状) | T47: 30日 | V47: 13 | W47: =RANDBETWEEN(1,6) -> 5 | X47: =RANDBETWEEN(1,8) -> 5 | Y47: =RANDBETWEEN(1,10) -> 6 | Z47: =RANDBETWEEN(1,12) -> 10
A48: 47 | B48: =IF(法术书!X49="","",法术书!X49) | C48: =IFERROR(VLOOKUP(B48,法术大全!$A:$W,5,FALSE),"") | D48: =IFERROR(VLOOKUP(B48,法术大全!$A:$W,4,FALSE),"") | E48: 47 | F48: {=IFERROR(INDEX($B$1:$B$301,SMALL(IF($B$1:$B$301<>"",ROW($B$1:$B$301),4^8),ROW(48:48)))&"","")} | H48: =IF(主要!AO70<>"",主要!AO70,"") | I48: =IF(VLOOKUP(H48,法术大全!$A$3:$E$864,4,0)="√",1,0) -> 0 | J48: =IF(VLOOKUP(H48,法术大全!$A$3:$E$864,5,0)="√",1,0) -> 0 | K48: {=IFERROR(INDEX($H$1:$H$68,SMALL(IF($H$2:$H$68<>"",ROW($H$2:$H$68),4^8),ROW(48:48)))&"","")} | S48: 1里 | T48: 特殊 | V48: 14 | W48: =RANDBETWEEN(1,6) -> 2 | X48: =RANDBETWEEN(1,8) -> 5 | Y48: =RANDBETWEEN(1,10) -> 2 | Z48: =RANDBETWEEN(1,12) -> 3
A49: 48 | B49: =IF(法术书!X50="","",法术书!X50) | C49: =IFERROR(VLOOKUP(B49,法术大全!$A:$W,5,FALSE),"") | D49: =IFERROR(VLOOKUP(B49,法术大全!$A:$W,4,FALSE),"") | E49: 48 | F49: {=IFERROR(INDEX($B$1:$B$301,SMALL(IF($B$1:$B$301<>"",ROW($B$1:$B$301),4^8),ROW(49:49)))&"","")} | H49: =IF(主要!AO71<>"",主要!AO71,"") | I49: =IF(VLOOKUP(H49,法术大全!$A$3:$E$864,4,0)="√",1,0) -> 0 | J49: =IF(VLOOKUP(H49,法术大全!$A$3:$E$864,5,0)="√",1,0) -> 0 | K49: {=IFERROR(INDEX($H$1:$H$68,SMALL(IF($H$2:$H$68<>"",ROW($H$2:$H$68),4^8),ROW(49:49)))&"","")} | S49: 视野内 | T49: 直到被解除 | V49: 15 | W49: =RANDBETWEEN(1,6) -> 3 | X49: =RANDBETWEEN(1,8) -> 5 | Y49: =RANDBETWEEN(1,10) -> 3 | Z49: =RANDBETWEEN(1,12) -> 4
A50: 49 | B50: =IF(法术书!X51="","",法术书!X51) | C50: =IFERROR(VLOOKUP(B50,法术大全!$A:$W,5,FALSE),"") | D50: =IFERROR(VLOOKUP(B50,法术大全!$A:$W,4,FALSE),"") | E50: 49 | F50: {=IFERROR(INDEX($B$1:$B$301,SMALL(IF($B$1:$B$301<>"",ROW($B$1:$B$301),4^8),ROW(50:50)))&"","")} | H50: =IF(主要!AO72<>"",主要!AO72,"") | I50: =IF(VLOOKUP(H50,法术大全!$A$3:$E$864,4,0)="√",1,0) -> 0 | J50: =IF(VLOOKUP(H50,法术大全!$A$3:$E$864,5,0)="√",1,0) -> 0 | K50: {=IFERROR(INDEX($H$1:$H$68,SMALL(IF($H$2:$H$68<>"",ROW($H$2:$H$68),4^8),ROW(50:50)))&"","")} | S50: 特殊 | T50: 直至被解除或被触发 | V50: 16 | W50: =RANDBETWEEN(1,6) -> 6 | X50: =RANDBETWEEN(1,8) -> 1 | Y50: =RANDBETWEEN(1,10) -> 4 | Z50: =RANDBETWEEN(1,12) -> 4
A51: 50 | B51: =IF(法术书!X52="","",法术书!X52) | C51: =IFERROR(VLOOKUP(B51,法术大全!$A:$W,5,FALSE),"") | D51: =IFERROR(VLOOKUP(B51,法术大全!$A:$W,4,FALSE),"") | E51: 50 | F51: {=IFERROR(INDEX($B$1:$B$301,SMALL(IF($B$1:$B$301<>"",ROW($B$1:$B$301),4^8),ROW(51:51)))&"","")} | H51: =IF(主要!AO73<>"",主要!AO73,"") | I51: =IF(VLOOKUP(H51,法术大全!$A$3:$E$864,4,0)="√",1,0) -> 0 | J51: =IF(VLOOKUP(H51,法术大全!$A$3:$E$864,5,0)="√",1,0) -> 0 | K51: {=IFERROR(INDEX($H$1:$H$68,SMALL(IF($H$2:$H$68<>"",ROW($H$2:$H$68),4^8),ROW(51:51)))&"","")} | T51: 直至被驱散 | V51: 17 | W51: =RANDBETWEEN(1,6) -> 2 | X51: =RANDBETWEEN(1,8) -> 6 | Y51: =RANDBETWEEN(1,10) -> 4 | Z51: =RANDBETWEEN(1,12) -> 9
A52: 51 | B52: =IF(法术书!AC3="","",法术书!AC3) | C52: =IFERROR(VLOOKUP(B52,法术大全!$A:$W,5,FALSE),"") | D52: =IFERROR(VLOOKUP(B52,法术大全!$A:$W,4,FALSE),"") | E52: 51 | F52: {=IFERROR(INDEX($B$1:$B$301,SMALL(IF($B$1:$B$301<>"",ROW($B$1:$B$301),4^8),ROW(52:52)))&"","")} | H52: =IF(主要!AO74<>"",主要!AO74,"") | I52: =IF(VLOOKUP(H52,法术大全!$A$3:$E$864,4,0)="√",1,0) -> 0 | J52: =IF(VLOOKUP(H52,法术大全!$A$3:$E$864,5,0)="√",1,0) -> 0 | K52: {=IFERROR(INDEX($H$1:$H$68,SMALL(IF($H$2:$H$68<>"",ROW($H$2:$H$68),4^8),ROW(52:52)))&"","")} | V52: 18 | W52: =RANDBETWEEN(1,6) -> 1 | X52: =RANDBETWEEN(1,8) -> 1 | Y52: =RANDBETWEEN(1,10) -> 6 | Z52: =RANDBETWEEN(1,12) -> 2
A53: 52 | B53: =IF(法术书!AC4="","",法术书!AC4) | C53: =IFERROR(VLOOKUP(B53,法术大全!$A:$W,5,FALSE),"") | D53: =IFERROR(VLOOKUP(B53,法术大全!$A:$W,4,FALSE),"") | E53: 52 | F53: {=IFERROR(INDEX($B$1:$B$301,SMALL(IF($B$1:$B$301<>"",ROW($B$1:$B$301),4^8),ROW(53:53)))&"","")} | H53: =IF(主要!AO75<>"",主要!AO75,"") | I53: =IF(VLOOKUP(H53,法术大全!$A$3:$E$864,4,0)="√",1,0) -> 0 | J53: =IF(VLOOKUP(H53,法术大全!$A$3:$E$864,5,0)="√",1,0) -> 0 | K53: {=IFERROR(INDEX($H$1:$H$68,SMALL(IF($H$2:$H$68<>"",ROW($H$2:$H$68),4^8),ROW(53:53)))&"","")} | V53: 19 | W53: =RANDBETWEEN(1,6) -> 3 | X53: =RANDBETWEEN(1,8) -> 3 | Y53: =RANDBETWEEN(1,10) -> 8 | Z53: =RANDBETWEEN(1,12) -> 9
A54: 53 | B54: =IF(法术书!AC5="","",法术书!AC5) | C54: =IFERROR(VLOOKUP(B54,法术大全!$A:$W,5,FALSE),"") | D54: =IFERROR(VLOOKUP(B54,法术大全!$A:$W,4,FALSE),"") | E54: 53 | F54: {=IFERROR(INDEX($B$1:$B$301,SMALL(IF($B$1:$B$301<>"",ROW($B$1:$B$301),4^8),ROW(54:54)))&"","")} | H54: =IF(主要!AO76<>"",主要!AO76,"") | I54: =IF(VLOOKUP(H54,法术大全!$A$3:$E$864,4,0)="√",1,0) -> 0 | J54: =IF(VLOOKUP(H54,法术大全!$A$3:$E$864,5,0)="√",1,0) -> 0 | K54: {=IFERROR(INDEX($H$1:$H$68,SMALL(IF($H$2:$H$68<>"",ROW($H$2:$H$68),4^8),ROW(54:54)))&"","")} | V54: 20 | W54: =RANDBETWEEN(1,6) -> 4 | X54: =RANDBETWEEN(1,8) -> 5 | Y54: =RANDBETWEEN(1,10) -> 2 | Z54: =RANDBETWEEN(1,12) -> 12
A55: 54 | B55: =IF(法术书!AC6="","",法术书!AC6) | C55: =IFERROR(VLOOKUP(B55,法术大全!$A:$W,5,FALSE),"") | D55: =IFERROR(VLOOKUP(B55,法术大全!$A:$W,4,FALSE),"") | E55: 54 | F55: {=IFERROR(INDEX($B$1:$B$301,SMALL(IF($B$1:$B$301<>"",ROW($B$1:$B$301),4^8),ROW(55:55)))&"","")} | H55: =IF(主要!AO77<>"",主要!AO77,"") | I55: =IF(VLOOKUP(H55,法术大全!$A$3:$E$864,4,0)="√",1,0) -> 0 | J55: =IF(VLOOKUP(H55,法术大全!$A$3:$E$864,5,0)="√",1,0) -> 0 | K55: {=IFERROR(INDEX($H$1:$H$68,SMALL(IF($H$2:$H$68<>"",ROW($H$2:$H$68),4^8),ROW(55:55)))&"","")}
A56: 55 | B56: =IF(法术书!AC7="","",法术书!AC7) | C56: =IFERROR(VLOOKUP(B56,法术大全!$A:$W,5,FALSE),"") | D56: =IFERROR(VLOOKUP(B56,法术大全!$A:$W,4,FALSE),"") | E56: 55 | F56: {=IFERROR(INDEX($B$1:$B$301,SMALL(IF($B$1:$B$301<>"",ROW($B$1:$B$301),4^8),ROW(56:56)))&"","")} | H56: =IF(主要!AO78<>"",主要!AO78,"") | I56: =IF(VLOOKUP(H56,法术大全!$A$3:$E$864,4,0)="√",1,0) -> 0 | J56: =IF(VLOOKUP(H56,法术大全!$A$3:$E$864,5,0)="√",1,0) -> 0 | K56: {=IFERROR(INDEX($H$1:$H$68,SMALL(IF($H$2:$H$68<>"",ROW($H$2:$H$68),4^8),ROW(56:56)))&"","")}
A57: 56 | B57: =IF(法术书!AC8="","",法术书!AC8) | C57: =IFERROR(VLOOKUP(B57,法术大全!$A:$W,5,FALSE),"") | D57: =IFERROR(VLOOKUP(B57,法术大全!$A:$W,4,FALSE),"") | E57: 56 | F57: {=IFERROR(INDEX($B$1:$B$301,SMALL(IF($B$1:$B$301<>"",ROW($B$1:$B$301),4^8),ROW(57:57)))&"","")} | H57: =IF(主要!AO79<>"",主要!AO79,"") | I57: =IF(VLOOKUP(H57,法术大全!$A$3:$E$864,4,0)="√",1,0) -> 0 | J57: =IF(VLOOKUP(H57,法术大全!$A$3:$E$864,5,0)="√",1,0) -> 0 | K57: {=IFERROR(INDEX($H$1:$H$68,SMALL(IF($H$2:$H$68<>"",ROW($H$2:$H$68),4^8),ROW(57:57)))&"","")}
A58: 57 | B58: =IF(法术书!AC9="","",法术书!AC9) | C58: =IFERROR(VLOOKUP(B58,法术大全!$A:$W,5,FALSE),"") | D58: =IFERROR(VLOOKUP(B58,法术大全!$A:$W,4,FALSE),"") | E58: 57 | F58: {=IFERROR(INDEX($B$1:$B$301,SMALL(IF($B$1:$B$301<>"",ROW($B$1:$B$301),4^8),ROW(58:58)))&"","")} | H58: =IF(主要!AO80<>"",主要!AO80,"") | I58: =IF(VLOOKUP(H58,法术大全!$A$3:$E$864,4,0)="√",1,0) -> 0 | J58: =IF(VLOOKUP(H58,法术大全!$A$3:$E$864,5,0)="√",1,0) -> 0 | K58: {=IFERROR(INDEX($H$1:$H$68,SMALL(IF($H$2:$H$68<>"",ROW($H$2:$H$68),4^8),ROW(58:58)))&"","")}
A59: 58 | B59: =IF(法术书!AC10="","",法术书!AC10) | C59: =IFERROR(VLOOKUP(B59,法术大全!$A:$W,5,FALSE),"") | D59: =IFERROR(VLOOKUP(B59,法术大全!$A:$W,4,FALSE),"") | E59: 58 | F59: {=IFERROR(INDEX($B$1:$B$301,SMALL(IF($B$1:$B$301<>"",ROW($B$1:$B$301),4^8),ROW(59:59)))&"","")} | H59: =IF(主要!AO81<>"",主要!AO81,"") | I59: =IF(VLOOKUP(H59,法术大全!$A$3:$E$864,4,0)="√",1,0) -> 0 | J59: =IF(VLOOKUP(H59,法术大全!$A$3:$E$864,5,0)="√",1,0) -> 0 | K59: {=IFERROR(INDEX($H$1:$H$68,SMALL(IF($H$2:$H$68<>"",ROW($H$2:$H$68),4^8),ROW(59:59)))&"","")}
A60: 59 | B60: =IF(法术书!AC11="","",法术书!AC11) | C60: =IFERROR(VLOOKUP(B60,法术大全!$A:$W,5,FALSE),"") | D60: =IFERROR(VLOOKUP(B60,法术大全!$A:$W,4,FALSE),"") | E60: 59 | F60: {=IFERROR(INDEX($B$1:$B$301,SMALL(IF($B$1:$B$301<>"",ROW($B$1:$B$301),4^8),ROW(60:60)))&"","")}
A61: 60 | B61: =IF(法术书!AC12="","",法术书!AC12) | C61: =IFERROR(VLOOKUP(B61,法术大全!$A:$W,5,FALSE),"") | D61: =IFERROR(VLOOKUP(B61,法术大全!$A:$W,4,FALSE),"") | E61: 60 | F61: {=IFERROR(INDEX($B$1:$B$301,SMALL(IF($B$1:$B$301<>"",ROW($B$1:$B$301),4^8),ROW(61:61)))&"","")}
A62: 61 | B62: =IF(法术书!AC13="","",法术书!AC13) | C62: =IFERROR(VLOOKUP(B62,法术大全!$A:$W,5,FALSE),"") | D62: =IFERROR(VLOOKUP(B62,法术大全!$A:$W,4,FALSE),"") | E62: 61 | F62: {=IFERROR(INDEX($B$1:$B$301,SMALL(IF($B$1:$B$301<>"",ROW($B$1:$B$301),4^8),ROW(62:62)))&"","")}
A63: 62 | B63: =IF(法术书!AC14="","",法术书!AC14) | C63: =IFERROR(VLOOKUP(B63,法术大全!$A:$W,5,FALSE),"") | D63: =IFERROR(VLOOKUP(B63,法术大全!$A:$W,4,FALSE),"") | E63: 62 | F63: {=IFERROR(INDEX($B$1:$B$301,SMALL(IF($B$1:$B$301<>"",ROW($B$1:$B$301),4^8),ROW(63:63)))&"","")} | BJ63: 职业能力
A64: 63 | B64: =IF(法术书!AC15="","",法术书!AC15) | C64: =IFERROR(VLOOKUP(B64,法术大全!$A:$W,5,FALSE),"") | D64: =IFERROR(VLOOKUP(B64,法术大全!$A:$W,4,FALSE),"") | E64: 63 | F64: {=IFERROR(INDEX($B$1:$B$301,SMALL(IF($B$1:$B$301<>"",ROW($B$1:$B$301),4^8),ROW(64:64)))&"","")}
A65: 64 | B65: =IF(法术书!AC16="","",法术书!AC16) | C65: =IFERROR(VLOOKUP(B65,法术大全!$A:$W,5,FALSE),"") | D65: =IFERROR(VLOOKUP(B65,法术大全!$A:$W,4,FALSE),"") | E65: 64 | F65: {=IFERROR(INDEX($B$1:$B$301,SMALL(IF($B$1:$B$301<>"",ROW($B$1:$B$301),4^8),ROW(65:65)))&"","")}
A66: 65 | B66: =IF(法术书!AC17="","",法术书!AC17) | C66: =IFERROR(VLOOKUP(B66,法术大全!$A:$W,5,FALSE),"") | D66: =IFERROR(VLOOKUP(B66,法术大全!$A:$W,4,FALSE),"") | E66: 65 | F66: {=IFERROR(INDEX($B$1:$B$301,SMALL(IF($B$1:$B$301<>"",ROW($B$1:$B$301),4^8),ROW(66:66)))&"","")}
A67: 66 | B67: =IF(法术书!AC18="","",法术书!AC18) | C67: =IFERROR(VLOOKUP(B67,法术大全!$A:$W,5,FALSE),"") | D67: =IFERROR(VLOOKUP(B67,法术大全!$A:$W,4,FALSE),"") | E67: 66 | F67: {=IFERROR(INDEX($B$1:$B$301,SMALL(IF($B$1:$B$301<>"",ROW($B$1:$B$301),4^8),ROW(67:67)))&"","")}
A68: 67 | B68: =IF(法术书!AC19="","",法术书!AC19) | C68: =IFERROR(VLOOKUP(B68,法术大全!$A:$W,5,FALSE),"") | D68: =IFERROR(VLOOKUP(B68,法术大全!$A:$W,4,FALSE),"") | E68: 67 | F68: {=IFERROR(INDEX($B$1:$B$301,SMALL(IF($B$1:$B$301<>"",ROW($B$1:$B$301),4^8),ROW(68:68)))&"","")} | BJ68: =职业!CV69
A69: 68 | B69: =IF(法术书!AC20="","",法术书!AC20) | C69: =IFERROR(VLOOKUP(B69,法术大全!$A:$W,5,FALSE),"") | D69: =IFERROR(VLOOKUP(B69,法术大全!$A:$W,4,FALSE),"") | E69: 68 | F69: {=IFERROR(INDEX($B$1:$B$301,SMALL(IF($B$1:$B$301<>"",ROW($B$1:$B$301),4^8),ROW(69:69)))&"","")} | BJ69: =职业!CV70
A70: 69 | B70: =IF(法术书!AC21="","",法术书!AC21) | C70: =IFERROR(VLOOKUP(B70,法术大全!$A:$W,5,FALSE),"") | D70: =IFERROR(VLOOKUP(B70,法术大全!$A:$W,4,FALSE),"") | E70: 69 | F70: {=IFERROR(INDEX($B$1:$B$301,SMALL(IF($B$1:$B$301<>"",ROW($B$1:$B$301),4^8),ROW(70:70)))&"","")} | BJ70: =职业!CV71
A71: 70 | B71: =IF(法术书!AC22="","",法术书!AC22) | C71: =IFERROR(VLOOKUP(B71,法术大全!$A:$W,5,FALSE),"") | D71: =IFERROR(VLOOKUP(B71,法术大全!$A:$W,4,FALSE),"") | E71: 70 | F71: {=IFERROR(INDEX($B$1:$B$301,SMALL(IF($B$1:$B$301<>"",ROW($B$1:$B$301),4^8),ROW(71:71)))&"","")} | BJ71: =职业!CV72
A72: 71 | B72: =IF(法术书!AC23="","",法术书!AC23) | C72: =IFERROR(VLOOKUP(B72,法术大全!$A:$W,5,FALSE),"") | D72: =IFERROR(VLOOKUP(B72,法术大全!$A:$W,4,FALSE),"") | E72: 71 | F72: {=IFERROR(INDEX($B$1:$B$301,SMALL(IF($B$1:$B$301<>"",ROW($B$1:$B$301),4^8),ROW(72:72)))&"","")} | BJ72: =职业!CV73
A73: 72 | B73: =IF(法术书!AC24="","",法术书!AC24) | C73: =IFERROR(VLOOKUP(B73,法术大全!$A:$W,5,FALSE),"") | D73: =IFERROR(VLOOKUP(B73,法术大全!$A:$W,4,FALSE),"") | E73: 72 | F73: {=IFERROR(INDEX($B$1:$B$301,SMALL(IF($B$1:$B$301<>"",ROW($B$1:$B$301),4^8),ROW(73:73)))&"","")} | BJ73: =职业!CV74
A74: 73 | B74: =IF(法术书!AC25="","",法术书!AC25) | C74: =IFERROR(VLOOKUP(B74,法术大全!$A:$W,5,FALSE),"") | D74: =IFERROR(VLOOKUP(B74,法术大全!$A:$W,4,FALSE),"") | E74: 73 | F74: {=IFERROR(INDEX($B$1:$B$301,SMALL(IF($B$1:$B$301<>"",ROW($B$1:$B$301),4^8),ROW(74:74)))&"","")} | BJ74: =职业!CV75
A75: 74 | B75: =IF(法术书!AC26="","",法术书!AC26) | C75: =IFERROR(VLOOKUP(B75,法术大全!$A:$W,5,FALSE),"") | D75: =IFERROR(VLOOKUP(B75,法术大全!$A:$W,4,FALSE),"") | E75: 74 | F75: {=IFERROR(INDEX($B$1:$B$301,SMALL(IF($B$1:$B$301<>"",ROW($B$1:$B$301),4^8),ROW(75:75)))&"","")} | BJ75: =职业!CV76
A76: 75 | B76: =IF(法术书!AC27="","",法术书!AC27) | C76: =IFERROR(VLOOKUP(B76,法术大全!$A:$W,5,FALSE),"") | D76: =IFERROR(VLOOKUP(B76,法术大全!$A:$W,4,FALSE),"") | E76: 75 | F76: {=IFERROR(INDEX($B$1:$B$301,SMALL(IF($B$1:$B$301<>"",ROW($B$1:$B$301),4^8),ROW(76:76)))&"","")} | BJ76: =职业!CV77
A77: 76 | B77: =IF(法术书!AC28="","",法术书!AC28) | C77: =IFERROR(VLOOKUP(B77,法术大全!$A:$W,5,FALSE),"") | D77: =IFERROR(VLOOKUP(B77,法术大全!$A:$W,4,FALSE),"") | E77: 76 | F77: {=IFERROR(INDEX($B$1:$B$301,SMALL(IF($B$1:$B$301<>"",ROW($B$1:$B$301),4^8),ROW(77:77)))&"","")} | BJ77: =职业!CV78
A78: 77 | B78: =IF(法术书!AC29="","",法术书!AC29) | C78: =IFERROR(VLOOKUP(B78,法术大全!$A:$W,5,FALSE),"") | D78: =IFERROR(VLOOKUP(B78,法术大全!$A:$W,4,FALSE),"") | E78: 77 | F78: {=IFERROR(INDEX($B$1:$B$301,SMALL(IF($B$1:$B$301<>"",ROW($B$1:$B$301),4^8),ROW(78:78)))&"","")} | BJ78: =职业!CV79
A79: 78 | B79: =IF(法术书!AC30="","",法术书!AC30) | C79: =IFERROR(VLOOKUP(B79,法术大全!$A:$W,5,FALSE),"") | D79: =IFERROR(VLOOKUP(B79,法术大全!$A:$W,4,FALSE),"") | E79: 78 | F79: {=IFERROR(INDEX($B$1:$B$301,SMALL(IF($B$1:$B$301<>"",ROW($B$1:$B$301),4^8),ROW(79:79)))&"","")} | BJ79: =职业!CV80
A80: 79 | B80: =IF(法术书!AC31="","",法术书!AC31) | C80: =IFERROR(VLOOKUP(B80,法术大全!$A:$W,5,FALSE),"") | D80: =IFERROR(VLOOKUP(B80,法术大全!$A:$W,4,FALSE),"") | E80: 79 | F80: {=IFERROR(INDEX($B$1:$B$301,SMALL(IF($B$1:$B$301<>"",ROW($B$1:$B$301),4^8),ROW(80:80)))&"","")} | BJ80: =职业!CV81
A81: 80 | B81: =IF(法术书!AC32="","",法术书!AC32) | C81: =IFERROR(VLOOKUP(B81,法术大全!$A:$W,5,FALSE),"") | D81: =IFERROR(VLOOKUP(B81,法术大全!$A:$W,4,FALSE),"") | E81: 80 | F81: {=IFERROR(INDEX($B$1:$B$301,SMALL(IF($B$1:$B$301<>"",ROW($B$1:$B$301),4^8),ROW(81:81)))&"","")}
A82: 81 | B82: =IF(法术书!AC33="","",法术书!AC33) | C82: =IFERROR(VLOOKUP(B82,法术大全!$A:$W,5,FALSE),"") | D82: =IFERROR(VLOOKUP(B82,法术大全!$A:$W,4,FALSE),"") | E82: 81 | F82: {=IFERROR(INDEX($B$1:$B$301,SMALL(IF($B$1:$B$301<>"",ROW($B$1:$B$301),4^8),ROW(82:82)))&"","")}
A83: 82 | B83: =IF(法术书!AC34="","",法术书!AC34) | C83: =IFERROR(VLOOKUP(B83,法术大全!$A:$W,5,FALSE),"") | D83: =IFERROR(VLOOKUP(B83,法术大全!$A:$W,4,FALSE),"") | E83: 82 | F83: {=IFERROR(INDEX($B$1:$B$301,SMALL(IF($B$1:$B$301<>"",ROW($B$1:$B$301),4^8),ROW(83:83)))&"","")}
A84: 83 | B84: =IF(法术书!AC35="","",法术书!AC35) | C84: =IFERROR(VLOOKUP(B84,法术大全!$A:$W,5,FALSE),"") | D84: =IFERROR(VLOOKUP(B84,法术大全!$A:$W,4,FALSE),"") | E84: 83 | F84: {=IFERROR(INDEX($B$1:$B$301,SMALL(IF($B$1:$B$301<>"",ROW($B$1:$B$301),4^8),ROW(84:84)))&"","")}
A85: 84 | B85: =IF(法术书!AC36="","",法术书!AC36) | C85: =IFERROR(VLOOKUP(B85,法术大全!$A:$W,5,FALSE),"") | D85: =IFERROR(VLOOKUP(B85,法术大全!$A:$W,4,FALSE),"") | E85: 84 | F85: {=IFERROR(INDEX($B$1:$B$301,SMALL(IF($B$1:$B$301<>"",ROW($B$1:$B$301),4^8),ROW(85:85)))&"","")}
A86: 85 | B86: =IF(法术书!AC37="","",法术书!AC37) | C86: =IFERROR(VLOOKUP(B86,法术大全!$A:$W,5,FALSE),"") | D86: =IFERROR(VLOOKUP(B86,法术大全!$A:$W,4,FALSE),"") | E86: 85 | F86: {=IFERROR(INDEX($B$1:$B$301,SMALL(IF($B$1:$B$301<>"",ROW($B$1:$B$301),4^8),ROW(86:86)))&"","")}
A87: 86 | B87: =IF(法术书!AC38="","",法术书!AC38) | C87: =IFERROR(VLOOKUP(B87,法术大全!$A:$W,5,FALSE),"") | D87: =IFERROR(VLOOKUP(B87,法术大全!$A:$W,4,FALSE),"") | E87: 86 | F87: {=IFERROR(INDEX($B$1:$B$301,SMALL(IF($B$1:$B$301<>"",ROW($B$1:$B$301),4^8),ROW(87:87)))&"","")}
A88: 87 | B88: =IF(法术书!AC39="","",法术书!AC39) | C88: =IFERROR(VLOOKUP(B88,法术大全!$A:$W,5,FALSE),"") | D88: =IFERROR(VLOOKUP(B88,法术大全!$A:$W,4,FALSE),"") | E88: 87 | F88: {=IFERROR(INDEX($B$1:$B$301,SMALL(IF($B$1:$B$301<>"",ROW($B$1:$B$301),4^8),ROW(88:88)))&"","")}
A89: 88 | B89: =IF(法术书!AC40="","",法术书!AC40) | C89: =IFERROR(VLOOKUP(B89,法术大全!$A:$W,5,FALSE),"") | D89: =IFERROR(VLOOKUP(B89,法术大全!$A:$W,4,FALSE),"") | E89: 88 | F89: {=IFERROR(INDEX($B$1:$B$301,SMALL(IF($B$1:$B$301<>"",ROW($B$1:$B$301),4^8),ROW(89:89)))&"","")}
A90: 89 | B90: =IF(法术书!AC41="","",法术书!AC41) | C90: =IFERROR(VLOOKUP(B90,法术大全!$A:$W,5,FALSE),"") | D90: =IFERROR(VLOOKUP(B90,法术大全!$A:$W,4,FALSE),"") | E90: 89 | F90: {=IFERROR(INDEX($B$1:$B$301,SMALL(IF($B$1:$B$301<>"",ROW($B$1:$B$301),4^8),ROW(90:90)))&"","")}
A91: 90 | B91: =IF(法术书!AC42="","",法术书!AC42) | C91: =IFERROR(VLOOKUP(B91,法术大全!$A:$W,5,FALSE),"") | D91: =IFERROR(VLOOKUP(B91,法术大全!$A:$W,4,FALSE),"") | E91: 90 | F91: {=IFERROR(INDEX($B$1:$B$301,SMALL(IF($B$1:$B$301<>"",ROW($B$1:$B$301),4^8),ROW(91:91)))&"","")}
A92: 91 | B92: =IF(法术书!AC43="","",法术书!AC43) | C92: =IFERROR(VLOOKUP(B92,法术大全!$A:$W,5,FALSE),"") | D92: =IFERROR(VLOOKUP(B92,法术大全!$A:$W,4,FALSE),"") | E92: 91 | F92: {=IFERROR(INDEX($B$1:$B$301,SMALL(IF($B$1:$B$301<>"",ROW($B$1:$B$301),4^8),ROW(92:92)))&"","")}
A93: 92 | B93: =IF(法术书!AC44="","",法术书!AC44) | C93: =IFERROR(VLOOKUP(B93,法术大全!$A:$W,5,FALSE),"") | D93: =IFERROR(VLOOKUP(B93,法术大全!$A:$W,4,FALSE),"") | E93: 92 | F93: {=IFERROR(INDEX($B$1:$B$301,SMALL(IF($B$1:$B$301<>"",ROW($B$1:$B$301),4^8),ROW(93:93)))&"","")}
A94: 93 | B94: =IF(法术书!AC45="","",法术书!AC45) | C94: =IFERROR(VLOOKUP(B94,法术大全!$A:$W,5,FALSE),"") | D94: =IFERROR(VLOOKUP(B94,法术大全!$A:$W,4,FALSE),"") | E94: 93 | F94: {=IFERROR(INDEX($B$1:$B$301,SMALL(IF($B$1:$B$301<>"",ROW($B$1:$B$301),4^8),ROW(94:94)))&"","")}
A95: 94 | B95: =IF(法术书!AC46="","",法术书!AC46) | C95: =IFERROR(VLOOKUP(B95,法术大全!$A:$W,5,FALSE),"") | D95: =IFERROR(VLOOKUP(B95,法术大全!$A:$W,4,FALSE),"") | E95: 94 | F95: {=IFERROR(INDEX($B$1:$B$301,SMALL(IF($B$1:$B$301<>"",ROW($B$1:$B$301),4^8),ROW(95:95)))&"","")}
A96: 95 | B96: =IF(法术书!AC47="","",法术书!AC47) | C96: =IFERROR(VLOOKUP(B96,法术大全!$A:$W,5,FALSE),"") | D96: =IFERROR(VLOOKUP(B96,法术大全!$A:$W,4,FALSE),"") | E96: 95 | F96: {=IFERROR(INDEX($B$1:$B$301,SMALL(IF($B$1:$B$301<>"",ROW($B$1:$B$301),4^8),ROW(96:96)))&"","")}
A97: 96 | B97: =IF(法术书!AC48="","",法术书!AC48) | C97: =IFERROR(VLOOKUP(B97,法术大全!$A:$W,5,FALSE),"") | D97: =IFERROR(VLOOKUP(B97,法术大全!$A:$W,4,FALSE),"") | E97: 96 | F97: {=IFERROR(INDEX($B$1:$B$301,SMALL(IF($B$1:$B$301<>"",ROW($B$1:$B$301),4^8),ROW(97:97)))&"","")}
A98: 97 | B98: =IF(法术书!AC49="","",法术书!AC49) | C98: =IFERROR(VLOOKUP(B98,法术大全!$A:$W,5,FALSE),"") | D98: =IFERROR(VLOOKUP(B98,法术大全!$A:$W,4,FALSE),"") | E98: 97 | F98: {=IFERROR(INDEX($B$1:$B$301,SMALL(IF($B$1:$B$301<>"",ROW($B$1:$B$301),4^8),ROW(98:98)))&"","")}
A99: 98 | B99: =IF(法术书!AC50="","",法术书!AC50) | C99: =IFERROR(VLOOKUP(B99,法术大全!$A:$W,5,FALSE),"") | D99: =IFERROR(VLOOKUP(B99,法术大全!$A:$W,4,FALSE),"") | E99: 98 | F99: {=IFERROR(INDEX($B$1:$B$301,SMALL(IF($B$1:$B$301<>"",ROW($B$1:$B$301),4^8),ROW(99:99)))&"","")}
A100: 99 | B100: =IF(法术书!AC51="","",法术书!AC51) | C100: =IFERROR(VLOOKUP(B100,法术大全!$A:$W,5,FALSE),"") | D100: =IFERROR(VLOOKUP(B100,法术大全!$A:$W,4,FALSE),"") | E100: 99 | F100: {=IFERROR(INDEX($B$1:$B$301,SMALL(IF($B$1:$B$301<>"",ROW($B$1:$B$301),4^8),ROW(100:100)))&"","")}
...

Sheet 职业
B1: PHB | C1: XGE | D1: TCE | E1: BGG | F1: FTD | G1: VGR | H1: EGtW | K1: UA | L1: TCSR | M1: VSS | N1: HW | Q1: FR:HoF | R1: GH | S1: DoDk | U1: BET | W1: CM | X1: TGS2 | Y1: OTTG | Z1: CBT | AB1: 主职业 | AC1: =IFERROR(IF(VLOOKUP(AB2,$B$3:$Z$22,2,FALSE)=0,"",VLOOKUP(AB2,$B$3:$Z$22,2,FALSE)),"") | AD1: 筛选 | AE1: 兼职1 | AF1: =IFERROR(IF(VLOOKUP(AE2,$B$3:$Z$22,2,FALSE)=0,"",VLOOKUP(AE2,$B$3:$Z$22,2,FALSE)),"") | AG1: 筛选 | AH1: 兼职2 | AI1: =IFERROR(IF(VLOOKUP(AH2,$B$3:$Z$22,2,FALSE)=0,"",VLOOKUP(AH2,$B$3:$Z$22,2,FALSE)),"") | AJ1: 筛选 | AK1: 职业特性 | AL1: =IFERROR(IF(VLOOKUP(AK2,$B$3:$Z$22,2,FALSE)=0,"",VLOOKUP(AK2,$B$3:$Z$22,2,FALSE)),"") | AM1: 筛选 | AO1: 生命值成长 | AQ1: 期望值 | AS1: 生命骰 | AT1: 期望值 | AU1: 1环 | AV1: =IF(AR12+AT17+AX18+AV17=0,"",AR12+AT17+AX18+AV17) | AY1: 职业 | AZ1: 等级 | BA1: 本职 | BB1: 子职 | BC1: 等级 | BE1: 等级 | BF1: 1环 | BG1: 2环 | BH1: 3环 | BI1: 4环 | BJ1: 5环 | BK1: 6环 | BL1: 7环 | BM1: 8环 | BN1: 9环 | BO1: 法术值 | BP1: 等级 | BQ1: 1环 | BR1: 2环 | BS1: 3环 | BT1: 4环 | BU1: 5环 | BV1: 等级 | BW1: 1环 | BX1: 2环 | BY1: 3环 | BZ1: 4环 | CA1: 等级 | CB1: 1环 | CC1: 2环 | CD1: 3环 | CE1: 4环 | CF1: 5环 | CI1: 等级 | CJ1: 名称 | CK1: 描述 | CL1: 最小数据 | CM1: 最大数据 | CO1: 等级 | CP1: 名称 | CQ1: 描述 | CR1: 最小数据行 | CS1: 最大数据行 | CT1: 待选特性 | CV1: 等级 | CW1: 特性名 | CX1: 特性描述
B2: 1 | C2: 2 | D2: 3 | E2: 4 | F2: 5 | G2: 6 | H2: 7 | I2: 8 | J2: 9 | K2: 10 | L2: 11 | M2: 12 | N2: 13 | O2: 14 | P2: 15 | Q2: 16 | R2: 17 | S2: 18 | T2: 19 | U2: 20 | V2: 21 | W2: 22 | X2: 23 | Y2: 24 | Z2: 25 | AB2: =主要!E6 -> 0 | AC2: =IFERROR(IF(VLOOKUP(AB2,$B$3:$Z$22,3,FALSE)=0,"",VLOOKUP(AB2,$B$3:$Z$22,3,FALSE)),"") | AD2: {=IFERROR(INDEX($AC$1:$AC$24,SMALL(IF($AC$1:$AC$24<>"",ROW($AC$1:$AC$24),4^8),ROW(AC1)))&"","")} | AE2: =主要!E7 -> 0 | AF2: =IFERROR(IF(VLOOKUP(AE2,$B$3:$Z$22,3,FALSE)=0,"",VLOOKUP(AE2,$B$3:$Z$22,3,FALSE)),"") | AG2: {=IFERROR(INDEX($AF$1:$AF$24,SMALL(IF($AF$1:$AF$24<>"",ROW($AF$1:$AF$24),4^8),ROW(1:1)))&"","")} | AH2: =主要!E8 -> 0 | AI2: =IFERROR(IF(VLOOKUP(AH2,$B$3:$Z$22,3,FALSE)=0,"",VLOOKUP(AH2,$B$3:$Z$22,3,FALSE)),"") | AJ2: {=IFERROR(INDEX($AI$1:$AI$24,SMALL(IF($AI$1:$AI$24<>"",ROW($AI$1:$AI$24),4^8),ROW(1:1)))&"","")} | AK2: =主要!AW9 -> 0 | AL2: =IFERROR(IF(VLOOKUP(AK2,$B$3:$Z$22,3,FALSE)=0,"",VLOOKUP(AK2,$B$3:$Z$22,3,FALSE)),"") | AM2: {=IFERROR(INDEX($AL$1:$AL$24,SMALL(IF($AL$1:$AL$24<>"",ROW($AL$1:$AL$24),4^8),ROW(1:1)))&"","")} | AO2: 法师 | AP2: D6 | AQ2: D6 | AR2: 4 | AS2: =IFERROR(VLOOKUP(主要!E6,$AO$2:$AP$21,2,FALSE),"") | AT2: =IFERROR(VLOOKUP(AS2,$AQ$2:$AR$5,2,FALSE),0) -> 0 | AU2: 2环 | AV2: =IF(AR13+AT18+AX19+AV18=0,"",AR13+AT18+AX19+AV18) | AY2: 野蛮人 | AZ2: =IFERROR(VLOOKUP(AY2,$BA$2:$BC$4,3,0),0) -> 0 | BA2: =IF(主要!E6="",0,主要!E6) -> 0 | BB2: =IF(主要!I6="",0,主要!I6) -> 0 | BC2: =IF(主要!O6="",0,主要!O6) -> 1 | BE2: 0 | BP2: 0 | BV2: 0 | CA2: 0 | CH2: 野蛮人 | CI2: 1 | CJ2: 2 | CK2: 3 | CL2: 1 | CM2: {=_xlfn.IFS($AZ$2=20,26,$AZ$2>=19,25,$AZ$2>=18,24,$AZ$2>=17,23,$AZ$2>=15,22,$AZ$2>=11,20,$AZ$2>=9,19,$AZ$2>=7,18,$AZ$2>=5,16,$AZ$2>=4,14,$AZ$2>=3,13,$AZ$2=2,11,$AZ$2=1,9,1,0)} -> 0 | CN2: =IF(主要!AW9<>"",主要!AW9,"") | CO2: =IFERROR(VLOOKUP($CN$2,$CH$2:$CM$22,2,FALSE),"") | CP2: =IFERROR(VLOOKUP($CN$2,$CH$2:$CM$22,3,FALSE),"") | CQ2: =IFERROR(VLOOKUP($CN$2,$CH$2:$CM$22,4,FALSE),"") | CR2: =IFERROR(VLOOKUP($CN$2,$CH$2:$CM$22,5,FALSE),"") | CS2: =IFERROR(VLOOKUP($CN$2,$CH$2:$CM$22,6,FALSE),"") | CT2: =IFERROR(IF(OR(CO6="",COUNTIF($CW$2:$CW$81,CO6)),"",CO6),"") | CU2: {=INDEX(CT:CT,SMALL(IF($CT$2:$CT$101<>"",ROW($CT$2:$CT$101),142),ROW(CT1)))&""} | CV2: =IFERROR(VLOOKUP(CW2,$CO$6:$CQ$105,3,FALSE),"") | CW2: =IF(主要!AX11="","",主要!AX11) -> 豁免熟练 | CX2: =IFERROR(VLOOKUP(CW2,$CO$6:$CQ$105,2,FALSE),"")
A3: 1 | B3: 野蛮人 | C3: 狂战士道途 | D3: 兽心道途 | E3: 世界树道途 | F3: 狂热者道途 | G3: =IF(自定义调整栏!$E$3="O","先祖守卫道途","") -> 先祖守卫道途 | H3: =IF(自定义调整栏!$E$3="O","风暴先驱道途","") -> 风暴先驱道途 | I3: =IF(自定义调整栏!$E$4="O","狂野魔法道途","") -> 狂野魔法道途 | J3: =IF(自定义调整栏!$E$4="O","野兽道途","") -> 野兽道途 | K3: =IF(自定义调整栏!$E$7="O","巨人道途","") -> 巨人道途 | L3: =IF(自定义调整栏!$E$26="O","巨像道途","") | M3: =IF(自定义调整栏!$E$34="O","肌肉法师道途","") | R3: =IF(自定义调整栏!$E$27="O","腐鸦道途","") | S3: =IF(自定义调整栏!$E$28="O","古神道途","") | T3: =IF(自定义调整栏!$E$28="O","污霭狂怒者道途","") | U3: =IF(自定义调整栏!$E$30="O","噬影徒","") | W3: =IF(自定义调整栏!$E$35="O","实验道途","") | X3: =IF(自定义调整栏!$E$32="O","炼狱道途","") | Y3: =IF(自定义调整栏!$E$33="O","腹酿道途","") | Z3: =IF(自定义调整栏!$E$36="O","蔑法道途","") | AA3: {=IFERROR(INDEX($B$1:$B$22,SMALL(IF($B$1:$B$22<>"",ROW($B$1:$B$22),4^8),ROW(3:3)))&"","")} -> 野蛮人 | AC3: =IFERROR(IF(VLOOKUP(AB2,$B$3:$Z$22,4,FALSE)=0,"",VLOOKUP(AB2,$B$3:$Z$22,4,FALSE)),"") | AD3: {=IFERROR(INDEX($AC$1:$AC$24,SMALL(IF($AC$1:$AC$24<>"",ROW($AC$1:$AC$24),4^8),ROW(AC2)))&"","")} | AF3: =IFERROR(IF(VLOOKUP(AE2,$B$3:$Z$22,4,FALSE)=0,"",VLOOKUP(AE2,$B$3:$Z$22,4,FALSE)),"") | AG3: {=IFERROR(INDEX($AF$1:$AF$24,SMALL(IF($AF$1:$AF$24<>"",ROW($AF$1:$AF$24),4^8),ROW(2:2)))&"","")} | AI3: =IFERROR(IF(VLOOKUP(AH2,$B$3:$Z$22,4,FALSE)=0,"",VLOOKUP(AH2,$B$3:$Z$22,4,FALSE)),"") | AJ3: {=IFERROR(INDEX($AI$1:$AI$24,SMALL(IF($AI$1:$AI$24<>"",ROW($AI$1:$AI$24),4^8),ROW(2:2)))&"","")} | AL3: =IFERROR(IF(VLOOKUP(AK2,$B$3:$Z$22,4,FALSE)=0,"",VLOOKUP(AK2,$B$3:$Z$22,4,FALSE)),"") | AM3: {=IFERROR(INDEX($AL$1:$AL$24,SMALL(IF($AL$1:$AL$24<>"",ROW($AL$1:$AL$24),4^8),ROW(2:2)))&"","")} | AO3: 术士 | AP3: D6 | AQ3: D8 | AR3: 5 | AS3: =IFERROR(VLOOKUP(主要!E7,$AO$2:$AP$21,2,FALSE),"") | AT3: =IFERROR(VLOOKUP(AS3,$AQ$2:$AR$5,2,FALSE),0) -> 0 | AU3: 3环 | AV3: =IF(AR14+AT19+AX20+AV19=0,"",AR14+AT19+AX20+AV19) | AY3: 吟游诗人 | AZ3: =IFERROR(VLOOKUP(AY3,$BA$2:$BC$4,3,0),0) -> 0 | BA3: =IF(主要!E7="",0,主要!E7) -> 0 | BB3: =IF(主要!I7="",0,主要!I7) -> 0 | BC3: =IF(主要!O7="",0,主要!O7) -> 0 | BE3: 1 | BF3: 2 | BO3: 4 | BP3: 1 | BQ3: 1 | BV3: 1 | CA3: 1 | CB3: 1 | CH3: 吟游诗人 | CI3: 4 | CJ3: 5 | CK3: 6 | CL3: 1 | CM3: {=_xlfn.IFS($AZ$3>=20,24,$AZ$3>=19,23,$AZ$3>=18,22,$AZ$3>=10,21,$AZ$3>=7,20,$AZ$3>=5,19,$AZ$3>=4,18,$AZ$3>=3,17,$AZ$3=2,16,$AZ$3=1,14,1,0)} -> 0 | CN3: =IF(主要!BD9<>"",主要!BD9,"") | CP3: 0v0? | CQ3: 0v0? | CR3: =IFERROR(VLOOKUP($CN$3,$CH$30:$CJ$285,2,FALSE),"") | CS3: =IFERROR(VLOOKUP($CN$3,$CH$30:$CJ$285,3,FALSE),"") | CT3: =IFERROR(IF(OR(CO7="",COUNTIF($CW$2:$CW$81,CO7)),"",CO7),"") | CU3: {=INDEX(CT:CT,SMALL(IF($CT$2:$CT$101<>"",ROW($CT$2:$CT$101),142),ROW(CT2)))&""} | CV3: =IFERROR(VLOOKUP(CW3,$CO$6:$CQ$105,3,FALSE),"") | CW3: =IF(主要!AX12="","",主要!AX12) -> 技能熟练 | CX3: =IFERROR(VLOOKUP(CW3,$CO$6:$CQ$105,2,FALSE),"")
A4: 2 | B4: 吟游诗人 | C4: 舞蹈学院 | D4: 魅心学院 | E4: 逸闻学院 | F4: 勇气学院 | G4: =IF(自定义调整栏!$E$3="O","剑舞学院","") -> 剑舞学院 | H4: =IF(自定义调整栏!$E$3="O","低语学院","") -> 低语学院 | I4: =IF(自定义调整栏!$E$4="O","创造学院","") -> 创造学院 | J4: =IF(自定义调整栏!$E$4="O","雄辩学院","") -> 雄辩学院 | K4: =IF(自定义调整栏!$E$19="O","精魂学院","") -> 精魂学院 | L4: =IF(自定义调整栏!$E$26="O","悲剧学院","") | M4: =IF(自定义调整栏!$E$29="O","旅路学院","") | Q4: =IF(自定义调整栏!$E$10="O","皓月学院","") -> 皓月学院 | R4: =IF(自定义调整栏!$E$27="O","安魂学院","") | S4: =IF(自定义调整栏!$E$28="O","末谕学院","") | U4: =IF(自定义调整栏!$E$30="O","暗影学院","") | W4: =IF(自定义调整栏!$E$35="O","灵哨学院","") | X4: =IF(自定义调整栏!$E$32="O","交易学院","") | Y4: =IF(自定义调整栏!$E$33="O","面具学院","") | Z4: =IF(自定义调整栏!$E$36="O","戏剧学院","") | AA4: {=IFERROR(INDEX($B$1:$B$22,SMALL(IF($B$1:$B$22<>"",ROW($B$1:$B$22),4^8),ROW(4:4)))&"","")} -> 吟游诗人 | AC4: =IFERROR(IF(VLOOKUP(AB2,$B$3:$Z$22,5,FALSE)=0,"",VLOOKUP(AB2,$B$3:$Z$22,5,FALSE)),"") | AD4: {=IFERROR(INDEX($AC$1:$AC$24,SMALL(IF($AC$1:$AC$24<>"",ROW($AC$1:$AC$24),4^8),ROW(AC3)))&"","")} | AF4: =IFERROR(IF(VLOOKUP(AE2,$B$3:$Z$22,5,FALSE)=0,"",VLOOKUP(AE2,$B$3:$Z$22,5,FALSE)),"") | AG4: {=IFERROR(INDEX($AF$1:$AF$24,SMALL(IF($AF$1:$AF$24<>"",ROW($AF$1:$AF$24),4^8),ROW(3:3)))&"","")} | AI4: =IFERROR(IF(VLOOKUP(AH2,$B$3:$Z$22,5,FALSE)=0,"",VLOOKUP(AH2,$B$3:$Z$22,5,FALSE)),"") | AJ4: {=IFERROR(INDEX($AI$1:$AI$24,SMALL(IF($AI$1:$AI$24<>"",ROW($AI$1:$AI$24),4^8),ROW(3:3)))&"","")} | AL4: =IFERROR(IF(VLOOKUP(AK2,$B$3:$Z$22,5,FALSE)=0,"",VLOOKUP(AK2,$B$3:$Z$22,5,FALSE)),"") | AM4: {=IFERROR(INDEX($AL$1:$AL$24,SMALL(IF($AL$1:$AL$24<>"",ROW($AL$1:$AL$24),4^8),ROW(3:3)))&"","")} | AO4: 灵能使 | AP4: D6 | AQ4: D10 | AR4: 6 | AS4: =IFERROR(VLOOKUP(主要!E8,$AO$2:$AP$21,2,FALSE),"") | AT4: =IFERROR(VLOOKUP(AS4,$AQ$2:$AR$5,2,FALSE),0) -> 0 | AU4: 4环 | AV4: =IF(AR15+AT20+AX21+AV20=0,"",AR15+AT20+AX21+AV20) | AY4: 牧师 | AZ4: =IFERROR(VLOOKUP(AY4,$BA$2:$BC$4,3,0),0) -> 0 | BA4: =IF(主要!E8="",0,主要!E8) -> 0 | BB4: =IF(主要!I8="",0,主要!I8) -> 0 | BC4: =IF(主要!O8="",0,主要!O8) -> 0 | BE4: 2 | BF4: 3 | BO4: 6 | BP4: 2 | BQ4: 2 | BV4: 2 | CA4: 2 | CB4: 2 | CH4: 牧师 | CI4: 7 | CJ4: 8 | CK4: 9 | CL4: 1 | CM4: {=_xlfn.IFS($AZ$4>=20,25,$AZ$4>=19,24,$AZ$4>=14,23,$AZ$4>=10,22,$AZ$4>=7,21,$AZ$4>=5,20,$AZ$4>=4,19,$AZ$4>=3,18,$AZ$4=2,17,$AZ$4=1,14,1,0)} -> 0 | CT4: =IFERROR(IF(OR(CO8="",COUNTIF($CW$2:$CW$81,CO8)),"",CO8),"") | CU4: {=INDEX(CT:CT,SMALL(IF($CT$2:$CT$101<>"",ROW($CT$2:$CT$101),142),ROW(CT3)))&""} | CV4: =IFERROR(VLOOKUP(CW4,$CO$6:$CQ$105,3,FALSE),"") | CW4: =IF(主要!AX13="","",主要!AX13) -> 武器熟练 | CX4: =IFERROR(VLOOKUP(CW4,$CO$6:$CQ$105,2,FALSE),"")
A5: 3 | B5: 牧师 | C5: 生命领域 | D5: 光明领域 | E5: 诡术领域 | F5: 战争领域 | G5: =IF(自定义调整栏!$E$3="O","锻造领域","") -> 锻造领域 | H5: =IF(自定义调整栏!$E$3="O","坟墓领域","") -> 坟墓领域 | I5: =IF(自定义调整栏!$E$4="O","秩序领域","") -> 秩序领域 | J5: =IF(自定义调整栏!$E$4="O","和平领域","") -> 和平领域 | K5: =IF(自定义调整栏!$E$4="O","暮光领域","") -> 暮光领域 | L5: =IF(自定义调整栏!$E$26="O","月亮领域","") | M5: =IF(自定义调整栏!$E$26="O","鲜血领域","") | N5: =IF(自定义调整栏!$E$29="O","团队领域","") | O5: =IF(自定义调整栏!$E$29="O","黑夜领域","") | Q5: =IF(自定义调整栏!$E$10="O","知识领域","") -> 知识领域 | R5: =IF(自定义调整栏!$E$27="O","审判领域","") | S5: =IF(自定义调整栏!$E$28="O","暗影领域-德城","") | T5: =IF(自定义调整栏!$E$30="O","监管领域","") | U5: =IF(自定义调整栏!$E$30="O","暗影领域","") | W5: =IF(自定义调整栏!$E$35="O","丰收领域","") | X5: =IF(自定义调整栏!$E$32="O","宴饮领域","") | Z5: =IF(自定义调整栏!$E$36="O","天启领域","") | AA5: {=IFERROR(INDEX($B$1:$B$22,SMALL(IF($B$1:$B$22<>"",ROW($B$1:$B$22),4^8),ROW(5:5)))&"","")} -> 牧师 | AC5: =IFERROR(IF(VLOOKUP(AB2,$B$3:$Z$22,6,FALSE)=0,"",VLOOKUP(AB2,$B$3:$Z$22,6,FALSE)),"") | AD5: {=IFERROR(INDEX($AC$1:$AC$24,SMALL(IF($AC$1:$AC$24<>"",ROW($AC$1:$AC$24),4^8),ROW(AC4)))&"","")} | AF5: =IFERROR(IF(VLOOKUP(AE2,$B$3:$Z$22,6,FALSE)=0,"",VLOOKUP(AE2,$B$3:$Z$22,6,FALSE)),"") | AG5: {=IFERROR(INDEX($AF$1:$AF$24,SMALL(IF($AF$1:$AF$24<>"",ROW($AF$1:$AF$24),4^8),ROW(4:4)))&"","")} | AI5: =IFERROR(IF(VLOOKUP(AH2,$B$3:$Z$22,6,FALSE)=0,"",VLOOKUP(AH2,$B$3:$Z$22,6,FALSE)),"") | AJ5: {=IFERROR(INDEX($AI$1:$AI$24,SMALL(IF($AI$1:$AI$24<>"",ROW($AI$1:$AI$24),4^8),ROW(4:4)))&"","")} | AL5: =IFERROR(IF(VLOOKUP(AK2,$B$3:$Z$22,6,FALSE)=0,"",VLOOKUP(AK2,$B$3:$Z$22,6,FALSE)),"") | AM5: {=IFERROR(INDEX($AL$1:$AL$24,SMALL(IF($AL$1:$AL$24<>"",ROW($AL$1:$AL$24),4^8),ROW(4:4)))&"","")} | AO5: 吟游诗人 | AP5: D8 | AQ5: D12 | AR5: 7 | AU5: 5环 | AV5: =IF(AR16+AT21+AV21=0,"",AR16+AT21+AV21) | AY5: 德鲁伊 | AZ5: =IFERROR(VLOOKUP(AY5,$BA$2:$BC$4,3,0),0) -> 0 | BE5: 3 | BF5: 4 | BG5: 2 | BO5: 14 | BP5: 3 | BR5: 2 | BV5: 3 | BW5: 1 | CA5: 3 | CC5: 2 | CH5: 德鲁伊 | CI5: 10 | CJ5: 11 | CK5: 12 | CL5: 1 | CM5: {=_xlfn.IFS($AZ$5>=20,29,$AZ$5>=19,28,$AZ$5>=18,27,$AZ$5>=15,26,$AZ$5>=7,25,$AZ$5>=5,24,$AZ$5>=4,23,$AZ$5>=3,22,$AZ$5=2,21,$AZ$5=1,15,1,0)} -> 0 | CN5: 0 | CO5: 名称 | CP5: 描述 | CR5: 增值 | CT5: =IFERROR(IF(OR(CO9="",COUNTIF($CW$2:$CW$81,CO9)),"",CO9),"") | CU5: {=INDEX(CT:CT,SMALL(IF($CT$2:$CT$101<>"",ROW($CT$2:$CT$101),142),ROW(CT4)))&""} | CV5: =IFERROR(VLOOKUP(CW5,$CO$6:$CQ$105,3,FALSE),"") | CW5: =IF(主要!AX14="","",主要!AX14) -> 工具熟练 | CX5: =IFERROR(VLOOKUP(CW5,$CO$6:$CQ$105,2,FALSE),"")
A6: 4 | B6: 德鲁伊 | C6: 大地结社 | D6: 月亮结社 | E6: 海洋结社 | F6: 星辰结社 | G6: =IF(自定义调整栏!$E$3="O","梦境结社","") -> 梦境结社 | H6: =IF(自定义调整栏!$E$3="O","牧人结社","") -> 牧人结社 | I6: =IF(自定义调整栏!$E$4="O","孢子结社","") -> 孢子结社 | J6: =IF(自定义调整栏!$E$4="O","野火结社","") -> 野火结社 | K6: =IF(自定义调整栏!$E$26="O","枯朽结社","") | L6: =IF(自定义调整栏!$E$29="O","守望结社","") | O6: =IF(自定义调整栏!$E$39="O","恩护结社","") | S6: =IF(自定义调整栏!$E$28="O","秽染结社","") | U6: =IF(自定义调整栏!$E$30="O","暗影结社","") | V6: =IF(自定义调整栏!$E$35="O","旧途结社","") | W6: =IF(自定义调整栏!$E$35="O","柳艺结社","") | X6: =IF(自定义调整栏!$E$32="O","巨龙结社","") | Y6: =IF(自定义调整栏!$E$33="O","落英结社","") | Z6: =IF(自定义调整栏!$E$36="O","共生结社","") | AA6: {=IFERROR(INDEX($B$1:$B$22,SMALL(IF($B$1:$B$22<>"",ROW($B$1:$B$22),4^8),ROW(6:6)))&"","")} -> 德鲁伊 | AC6: =IFERROR(IF(VLOOKUP(AB2,$B$3:$Z$22,7,FALSE)=0,"",VLOOKUP(AB2,$B$3:$Z$22,7,FALSE)),"") | AD6: {=IFERROR(INDEX($AC$1:$AC$24,SMALL(IF($AC$1:$AC$24<>"",ROW($AC$1:$AC$24),4^8),ROW(AC5)))&"","")} | AF6: =IFERROR(IF(VLOOKUP(AE2,$B$3:$Z$22,7,FALSE)=0,"",VLOOKUP(AE2,$B$3:$Z$22,7,FALSE)),"") | AG6: {=IFERROR(INDEX($AF$1:$AF$24,SMALL(IF($AF$1:$AF$24<>"",ROW($AF$1:$AF$24),4^8),ROW(5:5)))&"","")} | AI6: =IFERROR(IF(VLOOKUP(AH2,$B$3:$Z$22,7,FALSE)=0,"",VLOOKUP(AH2,$B$3:$Z$22,7,FALSE)),"") | AJ6: {=IFERROR(INDEX($AI$1:$AI$24,SMALL(IF($AI$1:$AI$24<>"",ROW($AI$1:$AI$24),4^8),ROW(5:5)))&"","")} | AL6: =IFERROR(IF(VLOOKUP(AK2,$B$3:$Z$22,7,FALSE)=0,"",VLOOKUP(AK2,$B$3:$Z$22,7,FALSE)),"") | AM6: {=IFERROR(INDEX($AL$1:$AL$24,SMALL(IF($AL$1:$AL$24<>"",ROW($AL$1:$AL$24),4^8),ROW(5:5)))&"","")} | AO6: 牧师 | AP6: D8 | AQ6: 首级 | AS6: 总等级 | AT6: =主要!O6+主要!O7+主要!O8 -> 1 | AU6: 6环 | AV6: =IF(AR17+0=0,"",AR17) | AY6: 战士 | AZ6: =IFERROR(VLOOKUP(AY6,$BA$2:$BC$4,3,0),0) -> 0 | BA6: 奥法骑士 | BB6: =IF($BB$2="奥法骑士",$BC$2,IF($BB$3="奥法骑士",$BC$3,IF($BB$4="奥法骑士",$BC$4,0))) -> 0 | BC6: =IF($AT$9=0,IF($AT$10=0,IF(SUM(BB7:BB11)=0,ROUNDUP(BB6/3,0),ROUNDDOWN(BB6/3,0)),ROUNDDOWN(BB6/3,0)),ROUNDDOWN(BB6/3,0)) -> 0 | BE6: 4 | BF6: 4 | BG6: 3 | BO6: 17 | BP6: 4 | BR6: 2 | BV6: 4 | BW6: 1 | CA6: 4 | CC6: 2 | CH6: 战士 | CI6: 13 | CJ6: 14 | CK6: 15 | CL6: 1 | CM6: {=_xlfn.IFS($AZ$6=20,21,$AZ$6>=19,20,$AZ$6>=13,19,$AZ$6>=11,18,$AZ$6>=9,17,$AZ$6>=5,15,$AZ$6>=4,13,$AZ$6>=3,12,$AZ$6>=2,11,$AZ$6=1,9,1,0)} -> 0 | CN6: =IFERROR(IF(CN5+1>CS2,IF(CN5+1>CS2,IF(CR3+CR5>CS3,"",CR3+CR5)),CN5+1),"") -> 1 | CO6: {=IFERROR(INDEX($B$34:$BO$262,CN6,$CP$2),"")} | CP6: {=IFERROR(INDEX($B$34:$BO$262,CN6,$CQ$2),"")} | CQ6: {=IF(IFERROR(INDEX($B$34:$BO$262,CN6,$CO$2),"")=0,"",IFERROR(INDEX($B$34:$BO$262,CN6,$CO$2),""))} | CR6: =IFERROR(IF(CN5+1>CS2,CR5+1,0),"") -> 0 | CT6: =IFERROR(IF(OR(CO10="",COUNTIF($CW$2:$CW$81,CO10)),"",CO10),"") | CU6: {=INDEX(CT:CT,SMALL(IF($CT$2:$CT$101<>"",ROW($CT$2:$CT$101),142),ROW(CT5)))&""} | CV6: =IFERROR(VLOOKUP(CW6,$CO$6:$CQ$105,3,FALSE),"") | CW6: =IF(主要!AX15="","",主要!AX15) -> 护甲受训 | CX6: =IFERROR(VLOOKUP(CW6,$CO$6:$CQ$105,2,FALSE),"")
A7: 5 | B7: 战士 | C7: 战斗大师 | D7: 勇士 | E7: 奥法骑士 | F7: 灵能武士 | G7: =IF(自定义调整栏!$E$3="O","魔射手","") -> 魔射手 | H7: =IF(自定义调整栏!$E$3="O","骑兵","") -> 骑兵 | I7: =IF(自定义调整栏!$E$3="O","武士","") -> 武士 | J7: =IF(自定义调整栏!$E$4="O","符文骑士","") -> 符文骑士 | K7: =IF(自定义调整栏!$E$23="O","回音骑士","") -> 回音骑士 | L7: =IF(自定义调整栏!$E$34="O","地城探险家","") | M7: =IF(自定义调整栏!$E$29="O","法外狂徒","") | O7: =IF(自定义调整栏!$E$39="O","角斗士","") | Q7: =IF(自定义调整栏!$E$10="O","旗将","") -> 旗将 | R7: =IF(自定义调整栏!$E$27="O","破锋者","") | S7: =IF(自定义调整栏!$E$28="O","指挥官","") | W7: =IF(自定义调整栏!$E$35="O","陵墓守卫","") | X7: =IF(自定义调整栏!$E$32="O","钢隼","") | Y7: =IF(自定义调整栏!$E$33="O","附灵","") | Z7: =IF(自定义调整栏!$E$36="O","英雄","") | AA7: {=IFERROR(INDEX($B$1:$B$22,SMALL(IF($B$1:$B$22<>"",ROW($B$1:$B$22),4^8),ROW(7:7)))&"","")} -> 战士 | AC7: =IFERROR(IF(VLOOKUP(AB2,$B$3:$Z$22,8,FALSE)=0,"",VLOOKUP(AB2,$B$3:$Z$22,8,FALSE)),"") | AD7: {=IFERROR(INDEX($AC$1:$AC$24,SMALL(IF($AC$1:$AC$24<>"",ROW($AC$1:$AC$24),4^8),ROW(AC6)))&"","")} | AF7: =IFERROR(IF(VLOOKUP(AE2,$B$3:$Z$22,8,FALSE)=0,"",VLOOKUP(AE2,$B$3:$Z$22,8,FALSE)),"") | AG7: {=IFERROR(INDEX($AF$1:$AF$24,SMALL(IF($AF$1:$AF$24<>"",ROW($AF$1:$AF$24),4^8),ROW(6:6)))&"","")} | AI7: =IFERROR(IF(VLOOKUP(AH2,$B$3:$Z$22,8,FALSE)=0,"",VLOOKUP(AH2,$B$3:$Z$22,8,FALSE)),"") | AJ7: {=IFERROR(INDEX($AI$1:$AI$24,SMALL(IF($AI$1:$AI$24<>"",ROW($AI$1:$AI$24),4^8),ROW(6:6)))&"","")} | AL7: =IFERROR(IF(VLOOKUP(AK2,$B$3:$Z$22,8,FALSE)=0,"",VLOOKUP(AK2,$B$3:$Z$22,8,FALSE)),"") | AM7: {=IFERROR(INDEX($AL$1:$AL$24,SMALL(IF($AL$1:$AL$24<>"",ROW($AL$1:$AL$24),4^8),ROW(6:6)))&"","")} | AO7: 德鲁伊 | AP7: D8 | AQ7: D6 | AR7: 2 | AS7: 首级 | AT7: =IFERROR(VLOOKUP(AS2,AQ7:AR10,2,FALSE),0) -> 0 | AU7: 7环 | AV7: =IF(AR18+0=0,"",AR18) | AY7: 武僧 | AZ7: =IFERROR(VLOOKUP(AY7,$BA$2:$BC$4,3,0),0) -> 0 | BA7: 诡术师 | BB7: =IF($BB$2="诡术师",$BC$2,IF($BB$3="诡术师",$BC$3,IF($BB$4="诡术师",$BC$4,0))) -> 0 | BC7: =IF($AT$9=0,IF($AT$10=0,IF(SUM(BB6,BB8:BB11)=0,ROUNDUP(BB7/3,0),ROUNDDOWN(BB7/3,0)),ROUNDDOWN(BB7/3,0)),ROUNDDOWN(BB7/3,0)) -> 0 | BE7: 5 | BF7: 4 | BG7: 3 | BH7: 2 | BO7: 27 | BP7: 5 | BS7: 2 | BV7: 5 | BW7: 1 | CA7: 5 | CD7: 3 | CH7: 武僧 | CI7: 16 | CJ7: 17 | CK7: 18 | CL7: 1 | CM7: {=_xlfn.IFS($AZ$7=20,28,$AZ$7=19,27,$AZ$7=18,26,$AZ$7>=15,25,$AZ$7>=14,24,$AZ$7>=13,23,$AZ$7>=10,22,$AZ$7>=9,20,$AZ$7>=7,19,$AZ$7>=6,18,$AZ$7>=5,17,$AZ$7>=4,15,$AZ$7>=3,13,$AZ$7=2,11,$AZ$7=1,8,1,0)} -> 0 | CN7: =IFERROR(IF(CN6+1>CS2,IF(CN6+1>CS2,IF(CR3+CR6>CS3,"",CR3+CR6)),CN6+1),"") -> 2 | CO7: {=IFERROR(INDEX($B$34:$BO$262,CN7,$CP$2),"")} | CP7: {=IFERROR(INDEX($B$34:$BO$262,CN7,$CQ$2),"")} | CQ7: {=IF(IFERROR(INDEX($B$34:$BO$262,CN7,$CO$2),"")=0,"",IFERROR(INDEX($B$34:$BO$262,CN7,$CO$2),""))} | CR7: =IFERROR(IF(CN6+1>CS2,CR6+1,0),"") -> 0 | CT7: =IFERROR(IF(OR(CO11="",COUNTIF($CW$2:$CW$81,CO11)),"",CO11),"") | CU7: {=INDEX(CT:CT,SMALL(IF($CT$2:$CT$101<>"",ROW($CT$2:$CT$101),142),ROW(CT6)))&""} | CV7: =IFERROR(VLOOKUP(CW7,$CO$6:$CQ$105,3,FALSE),"") | CW7: =IF(主要!AX16="","",主要!AX16) -> 起始装备 | CX7: =IFERROR(VLOOKUP(CW7,$CO$6:$CQ$105,2,FALSE),"")
A8: 6 | B8: 武僧 | C8: 命流武者 | D8: 暗影武者 | E8: 四象武者 | F8: 散打武者 | G8: =IF(自定义调整栏!$E$3="O","醉拳宗","") -> 醉拳宗 | H8: =IF(自定义调整栏!$E$3="O","剑圣宗","") -> 剑圣宗 | I8: =IF(自定义调整栏!$E$3="O","日魂宗","") -> 日魂宗 | J8: =IF(自定义调整栏!$E$4="O","星我宗","") -> 星我宗 | K8: =IF(自定义调整栏!$E$6="O","神龙宗","") -> 神龙宗 | L8: =IF(自定义调整栏!$E$26="O","钴魂宗","") | M8: =IF(自定义调整栏!$E$34="O","街霸武者","") | O8: =IF(自定义调整栏!$E$40="O","秘术武者","") | S8: =IF(自定义调整栏!$E$28="O","盘蛇宗","") | T8: =IF(自定义调整栏!$E$28="O","织法宗","") | U8: =IF(自定义调整栏!$E$30="O","先知宗","") | W8: =IF(自定义调整栏!$E$35="O","疫瘴武者","") | X8: =IF(自定义调整栏!$E$32="O","虚灵宗","") | Y8: =IF(自定义调整栏!$E$33="O","绵龙牧者","") | Z8: =IF(自定义调整栏!$E$36="O","天衡武者","") | AA8: {=IFERROR(INDEX($B$1:$B$22,SMALL(IF($B$1:$B$22<>"",ROW($B$1:$B$22),4^8),ROW(8:8)))&"","")} -> 武僧 | AC8: =IFERROR(IF(VLOOKUP(AB2,$B$3:$Z$22,9,FALSE)=0,"",VLOOKUP(AB2,$B$3:$Z$22,9,FALSE)),"") | AD8: {=IFERROR(INDEX($AC$1:$AC$24,SMALL(IF($AC$1:$AC$24<>"",ROW($AC$1:$AC$24),4^8),ROW(AC7)))&"","")} | AF8: =IFERROR(IF(VLOOKUP(AE2,$B$3:$Z$22,9,FALSE)=0,"",VLOOKUP(AE2,$B$3:$Z$22,9,FALSE)),"") | AG8: {=IFERROR(INDEX($AF$1:$AF$24,SMALL(IF($AF$1:$AF$24<>"",ROW($AF$1:$AF$24),4^8),ROW(7:7)))&"","")} | AI8: =IFERROR(IF(VLOOKUP(AH2,$B$3:$Z$22,9,FALSE)=0,"",VLOOKUP(AH2,$B$3:$Z$22,9,FALSE)),"") | AJ8: {=IFERROR(INDEX($AI$1:$AI$24,SMALL(IF($AI$1:$AI$24<>"",ROW($AI$1:$AI$24),4^8),ROW(7:7)))&"","")} | AL8: =IFERROR(IF(VLOOKUP(AK2,$B$3:$Z$22,9,FALSE)=0,"",VLOOKUP(AK2,$B$3:$Z$22,9,FALSE)),"") | AM8: {=IFERROR(INDEX($AL$1:$AL$24,SMALL(IF($AL$1:$AL$24<>"",ROW($AL$1:$AL$24),4^8),ROW(7:7)))&"","")} | AO8: 武僧 | AP8: D8 | AQ8: D8 | AR8: 3 | AU8: 8环 | AV8: =IF(AR19+0=0,"",AR19) | AY8: 圣武士 | AZ8: =IFERROR(VLOOKUP(AY8,$BA$2:$BC$4,3,0),0) -> 0 | BA8: 筑灭师 | BB8: =IF($BB$3="筑灭师",$BC$3,IF($BB$4="筑灭师",$BC$4,IF($BB$5="筑灭师",$BC$5,0))) -> 0 | BC8: =IF($AT$9=0,IF($AT$10=0,IF(SUM(BB6:BB7,BB9:BB11)=0,ROUNDUP(BB8/3,0),ROUNDDOWN(BB8/3,0)),ROUNDDOWN(BB8/3,0)),ROUNDDOWN(BB8/3,0)) -> 0 | BE8: 6 | BF8: 4 | BG8: 3 | BH8: 3 | BO8: 32 | BP8: 6 | BS8: 2 | BV8: 6 | BW8: 2 | CA8: 6 | CD8: 3 | CH8: 圣武士 | CI8: 19 | CJ8: 20 | CK8: 21 | CL8: 1 | CM8: {=_xlfn.IFS($AZ$8>=19,29,$AZ$8>=18,28,$AZ$8>=14,27,$AZ$8>=11,26,$AZ$8>=10,25,$AZ$8>=9,24,$AZ$8>=6,23,$AZ$8>=5,22,$AZ$8>=4,20,$AZ$8>=3,19,$AZ$8=2,16,$AZ$8=1,14,1,0)} -> 0 | CN8: =IFERROR(IF(CN7+1>CS2,IF(CN7+1>CS2,IF(CR3+CR7>CS3,"",CR3+CR7)),CN7+1),"") -> 3 | CO8: {=IFERROR(INDEX($B$34:$BO$262,CN8,$CP$2),"")} | CP8: {=IFERROR(INDEX($B$34:$BO$262,CN8,$CQ$2),"")} | CQ8: {=IF(IFERROR(INDEX($B$34:$BO$262,CN8,$CO$2),"")=0,"",IFERROR(INDEX($B$34:$BO$262,CN8,$CO$2),""))} | CR8: =IFERROR(IF(CN7+1>CS2,CR7+1,0),"") -> 0 | CT8: =IFERROR(IF(OR(CO12="",COUNTIF($CW$2:$CW$81,CO12)),"",CO12),"") | CU8: {=INDEX(CT:CT,SMALL(IF($CT$2:$CT$101<>"",ROW($CT$2:$CT$101),142),ROW(CT7)))&""} | CV8: =IFERROR(VLOOKUP(CW8,$CO$6:$CQ$105,3,FALSE),"") | CW8: =IF(主要!AX17="","",主要!AX17) | CX8: =IFERROR(VLOOKUP(CW8,$CO$6:$CQ$105,2,FALSE),"")
A9: 7 | B9: 圣武士 | C9: 奉献之誓 | D9: 荣耀之誓 | E9: 古贤之誓 | F9: 复仇之誓 | G9: =IF(自定义调整栏!$E$3="O","征服之誓","") -> 征服之誓 | H9: =IF(自定义调整栏!$E$3="O","救赎之誓","") -> 救赎之誓 | I9: =IF(自定义调整栏!$E$4="O","守望之誓","") -> 守望之誓 | J9: =IF(自定义调整栏!$E$26="O","远洋之誓","") | K9: =IF(自定义调整栏!$E$34="O","狂欢之誓","") | L9: 王冠之誓 | O9: =IF(自定义调整栏!$E$40="O","护法之誓","") | Q9: =IF(自定义调整栏!$E$10="O","巨灵贵族之誓","") -> 巨灵贵族之誓 | R9: =IF(自定义调整栏!$E$27="O","狂热之誓","") | S9: =IF(自定义调整栏!$E$28="O","巫咒之誓","") | W9: =IF(自定义调整栏!$E$35="O","惩戒之誓","") | X9: =IF(自定义调整栏!$E$32="O","饮咒之誓","") | Y9: =IF(自定义调整栏!$E$33="O","川流之誓","") | Z9: =IF(自定义调整栏!$E$36="O","守护之誓","") | AA9: {=IFERROR(INDEX($B$1:$B$22,SMALL(IF($B$1:$B$22<>"",ROW($B$1:$B$22),4^8),ROW(9:9)))&"","")} -> 圣武士 | AC9: =IFERROR(IF(VLOOKUP(AB2,$B$3:$Z$22,10,FALSE)=0,"",VLOOKUP(AB2,$B$3:$Z$22,10,FALSE)),"") | AD9: {=IFERROR(INDEX($AC$1:$AC$24,SMALL(IF($AC$1:$AC$24<>"",ROW($AC$1:$AC$24),4^8),ROW(AC8)))&"","")} | AF9: =IFERROR(IF(VLOOKUP(AE2,$B$3:$Z$22,10,FALSE)=0,"",VLOOKUP(AE2,$B$3:$Z$22,10,FALSE)),"") | AG9: {=IFERROR(INDEX($AF$1:$AF$24,SMALL(IF($AF$1:$AF$24<>"",ROW($AF$1:$AF$24),4^8),ROW(8:8)))&"","")} | AI9: =IFERROR(IF(VLOOKUP(AH2,$B$3:$Z$22,10,FALSE)=0,"",VLOOKUP(AH2,$B$3:$Z$22,10,FALSE)),"") | AJ9: {=IFERROR(INDEX($AI$1:$AI$24,SMALL(IF($AI$1:$AI$24<>"",ROW($AI$1:$AI$24),4^8),ROW(8:8)))&"","")} | AL9: =IFERROR(IF(VLOOKUP(AK2,$B$3:$Z$22,10,FALSE)=0,"",VLOOKUP(AK2,$B$3:$Z$22,10,FALSE)),"") | AM9: {=IFERROR(INDEX($AL$1:$AL$24,SMALL(IF($AL$1:$AL$24<>"",ROW($AL$1:$AL$24),4^8),ROW(8:8)))&"","")} | AO9: 游荡者 | AP9: D8 | AQ9: D10 | AR9: 4 | AS9: 全施法者 | AT9: =$AZ$3+$AZ$4+$AZ$5+$AZ$11+$AZ$13+$AZ$15 -> 0 | AU9: 9环 | AV9: =IF(AR20+0=0,"",AR20) | AY9: 游侠 | AZ9: =IFERROR(VLOOKUP(AY9,$BA$2:$BC$4,3,0),0) -> 0 | BA9: 魔弹客 | BB9: =IF($BB$2="魔弹客",$BC$2,IF($BB$3="魔弹客",$BC$3,IF($BB$4="魔弹客",$BC$4,0))) -> 0 | BC9: =IF($AT$9=0,IF($AT$10=0,IF(SUM(BB6:BB8,BB10:BB11)=0,ROUNDUP(BB9/3,0),ROUNDDOWN(BB9/3,0)),ROUNDDOWN(BB9/3,0)),ROUNDDOWN(BB9/3,0)) -> 0 | BE9: 7 | BF9: 4 | BG9: 3 | BH9: 3 | BI9: 1 | BO9: 38 | BP9: 7 | BT9: 2 | BV9: 7 | BX9: 2 | CA9: 7 | CE9: 3 | CH9: 游侠 | CI9: 22 | CJ9: 23 | CK9: 24 | CL9: 1 | CM9: {=_xlfn.IFS($AZ$9=20,28,$AZ$9>=19,27,$AZ$9>=18,26,$AZ$9>=17,25,$AZ$9>=14,24,$AZ$9>=13,23,$AZ$9>=10,22,$AZ$9>=9,21,$AZ$9>=6,20,$AZ$9>=5,19,$AZ$9>=4,18,$AZ$9>=3,17,$AZ$9=2,16,$AZ$9=1,14,1,0)} -> 0 | CN9: =IFERROR(IF(CN8+1>CS2,IF(CN8+1>CS2,IF(CR3+CR8>CS3,"",CR3+CR8)),CN8+1),"") -> 4 | CO9: {=IFERROR(INDEX($B$34:$BO$262,CN9,$CP$2),"")} | CP9: {=IFERROR(INDEX($B$34:$BO$262,CN9,$CQ$2),"")} | CQ9: {=IF(IFERROR(INDEX($B$34:$BO$262,CN9,$CO$2),"")=0,"",IFERROR(INDEX($B$34:$BO$262,CN9,$CO$2),""))} | CR9: =IFERROR(IF(CN8+1>CS2,CR8+1,0),"") -> 0 | CT9: =IFERROR(IF(OR(CO13="",COUNTIF($CW$2:$CW$81,CO13)),"",CO13),"") | CU9: {=INDEX(CT:CT,SMALL(IF($CT$2:$CT$101<>"",ROW($CT$2:$CT$101),142),ROW(CT8)))&""} | CV9: =IFERROR(VLOOKUP(CW9,$CO$6:$CQ$105,3,FALSE),"") | CW9: =IF(主要!AX18="","",主要!AX18) | CX9: =IFERROR(VLOOKUP(CW9,$CO$6:$CQ$105,2,FALSE),"")
A10: 8 | B10: 游侠 | C10: 驯兽师 | D10: 妖精漫游者 | E10: 幽域追踪者 | F10: 猎人 | G10: =IF(自定义调整栏!$E$3="O","边界行者","") -> 边界行者 | H10: =IF(自定义调整栏!$E$3="O","怪物杀手","") -> 怪物杀手 | I10: =IF(自定义调整栏!$E$4="O","集群牧者","") -> 集群牧者 | J10: =IF(自定义调整栏!$E$6="O","龙兽守卫","") -> 龙兽守卫 | Q10: =IF(自定义调整栏!$E$10="O","凛冬行者","") -> 凛冬行者 | S10: =IF(自定义调整栏!$E$28="O","城市游侠","") | W10: =IF(自定义调整栏!$E$35="O","噩兆先驱","") | X10: =IF(自定义调整栏!$E$32="O","天鹏旅人","") | Y10: =IF(自定义调整栏!$E$33="O","侵蚀行者","") | Z10: =IF(自定义调整栏!$E$36="O","荒径守护者","") | AA10: {=IFERROR(INDEX($B$1:$B$22,SMALL(IF($B$1:$B$22<>"",ROW($B$1:$B$22),4^8),ROW(10:10)))&"","")} -> 游侠 | AC10: =IFERROR(IF(VLOOKUP(AB2,$B$3:$Z$22,11,FALSE)=0,"",VLOOKUP(AB2,$B$3:$Z$22,11,FALSE)),"") | AD10: {=IFERROR(INDEX($AC$1:$AC$24,SMALL(IF($AC$1:$AC$24<>"",ROW($AC$1:$AC$24),4^8),ROW(AC9)))&"","")} | AF10: =IFERROR(IF(VLOOKUP(AE2,$B$3:$Z$22,11,FALSE)=0,"",VLOOKUP(AE2,$B$3:$Z$22,11,FALSE)),"") | AG10: {=IFERROR(INDEX($AF$1:$AF$24,SMALL(IF($AF$1:$AF$24<>"",ROW($AF$1:$AF$24),4^8),ROW(9:9)))&"","")} | AI10: =IFERROR(IF(VLOOKUP(AH2,$B$3:$Z$22,11,FALSE)=0,"",VLOOKUP(AH2,$B$3:$Z$22,11,FALSE)),"") | AJ10: {=IFERROR(INDEX($AI$1:$AI$24,SMALL(IF($AI$1:$AI$24<>"",ROW($AI$1:$AI$24),4^8),ROW(9:9)))&"","")} | AL10: =IFERROR(IF(VLOOKUP(AK2,$B$3:$Z$22,11,FALSE)=0,"",VLOOKUP(AK2,$B$3:$Z$22,11,FALSE)),"") | AM10: {=IFERROR(INDEX($AL$1:$AL$24,SMALL(IF($AL$1:$AL$24<>"",ROW($AL$1:$AL$24),4^8),ROW(9:9)))&"","")} | AO10: 魔契师 | AP10: D8 | AQ10: D12 | AR10: 5 | AS10: 半施法者 | AT10: =ROUNDUP(($AZ$8+$AZ$9+$AZ$14)/2,0) -> 0 | AY10: 游荡者 | AZ10: =IFERROR(VLOOKUP(AY10,$BA$2:$BC$4,3,0),0) -> 0 | BA10: 织法宗 | BB10: =IF($BB$2="织法宗",$BC$2,IF($BB$3="织法宗",$BC$3,IF($BB$4="织法宗",$BC$4,0))) -> 0 | BC10: =IF($AT$9=0,IF($AT$10=0,IF(SUM(BB6:BB9,BB11)=0,ROUNDUP(BB10/3,0),ROUNDDOWN(BB10/3,0)),ROUNDDOWN(BB10/3,0)),ROUNDDOWN(BB10/3,0)) -> 0 | BE10: 8 | BF10: 4 | BG10: 3 | BH10: 3 | BI10: 2 | BO10: 44 | BP10: 8 | BT10: 2 | BV10: 8 | BX10: 2 | CA10: 8 | CE10: 3 | CH10: 游荡者 | CI10: 25 | CJ10: 26 | CK10: 27 | CL10: 1 | CM10: {=_xlfn.IFS($AZ$10=20,24,$AZ$10>=19,23,$AZ$10>=18,22,$AZ$10>=15,21,$AZ$10>=14,20,$AZ$10>=11,19,$AZ$10>=7,18,$AZ$10>=5,16,$AZ$10>=4,14,$AZ$10>=3,13,$AZ$10=2,11,$AZ$10=1,10,1,0)} -> 0 | CN10: =IFERROR(IF(CN9+1>CS2,IF(CN9+1>CS2,IF(CR3+CR9>CS3,"",CR3+CR9)),CN9+1),"") -> 5 | CO10: {=IFERROR(INDEX($B$34:$BO$262,CN10,$CP$2),"")} | CP10: {=IFERROR(INDEX($B$34:$BO$262,CN10,$CQ$2),"")} | CQ10: {=IF(IFERROR(INDEX($B$34:$BO$262,CN10,$CO$2),"")=0,"",IFERROR(INDEX($B$34:$BO$262,CN10,$CO$2),""))} | CR10: =IFERROR(IF(CN9+1>CS2,CR9+1,0),"") -> 0 | CT10: =IFERROR(IF(OR(CO14="",COUNTIF($CW$2:$CW$81,CO14)),"",CO14),"") | CU10: {=INDEX(CT:CT,SMALL(IF($CT$2:$CT$101<>"",ROW($CT$2:$CT$101),142),ROW(CT9)))&""} | CV10: =IFERROR(VLOOKUP(CW10,$CO$6:$CQ$105,3,FALSE),"") | CW10: =IF(主要!AX19="","",主要!AX19) | CX10: =IFERROR(VLOOKUP(CW10,$CO$6:$CQ$105,2,FALSE),"")
A11: 9 | B11: 游荡者 | C11: 诡术师 | D11: 刺客 | E11: 魂刃 | F11: 盗贼 | G11: =IF(自定义调整栏!$E$3="O","调查员","") -> 调查员 | H11: =IF(自定义调整栏!$E$3="O","策士","") -> 策士 | I11: =IF(自定义调整栏!$E$3="O","斥候","") -> 斥候 | J11: =IF(自定义调整栏!$E$3="O","游荡剑客","") -> 游荡剑客 | K11: =IF(自定义调整栏!$E$4="O","鬼魅","") -> 鬼魅 | L11: =IF(自定义调整栏!$E$34="O","蛛网追猎者","") | O11: =IF(自定义调整栏!$E$40="O","窃法者","") | Q11: =IF(自定义调整栏!$E$10="O","三神门徒","") -> 三神门徒 | R11: =IF(自定义调整栏!$E$27="O","厄运使者","") | S11: =IF(自定义调整栏!$E$28="O","走私者","") | U11: =IF(自定义调整栏!$E$30="O","缚影使","") | W11: =IF(自定义调整栏!$E$35="O","罪人","") | X11: =IF(自定义调整栏!$E$32="O","残戮行医","") | Y11: =IF(自定义调整栏!$E$33="O","蜡艺师","") | Z11: =IF(自定义调整栏!$E$36="O","暗影潜行者","") | AA11: {=IFERROR(INDEX($B$1:$B$22,SMALL(IF($B$1:$B$22<>"",ROW($B$1:$B$22),4^8),ROW(11:11)))&"","")} -> 游荡者 | AC11: =IFERROR(IF(VLOOKUP(AB2,$B$3:$Z$22,12,FALSE)=0,"",VLOOKUP(AB2,$B$3:$Z$22,12,FALSE)),"") | AD11: {=IFERROR(INDEX($AC$1:$AC$24,SMALL(IF($AC$1:$AC$24<>"",ROW($AC$1:$AC$24),4^8),ROW(AC10)))&"","")} | AF11: =IFERROR(IF(VLOOKUP(AE2,$B$3:$Z$22,12,FALSE)=0,"",VLOOKUP(AE2,$B$3:$Z$22,12,FALSE)),"") | AG11: {=IFERROR(INDEX($AF$1:$AF$24,SMALL(IF($AF$1:$AF$24<>"",ROW($AF$1:$AF$24),4^8),ROW(10:10)))&"","")} | AI11: =IFERROR(IF(VLOOKUP(AH2,$B$3:$Z$22,12,FALSE)=0,"",VLOOKUP(AH2,$B$3:$Z$22,12,FALSE)),"") | AJ11: {=IFERROR(INDEX($AI$1:$AI$24,SMALL(IF($AI$1:$AI$24<>"",ROW($AI$1:$AI$24),4^8),ROW(10:10)))&"","")} | AL11: =IFERROR(IF(VLOOKUP(AK2,$B$3:$Z$22,12,FALSE)=0,"",VLOOKUP(AK2,$B$3:$Z$22,12,FALSE)),"") | AM11: {=IFERROR(INDEX($AL$1:$AL$24,SMALL(IF($AL$1:$AL$24<>"",ROW($AL$1:$AL$24),4^8),ROW(10:10)))&"","")} | AO11: 奇械师 | AP11: D8 | AQ11: 施法者等级 | AR11: =AT9+AT10+AT11 -> 0 | AS11: 1/3施法 | AT11: =SUM(BC6:BC11) -> 0 | AY11: 术士 | AZ11: =IFERROR(VLOOKUP(AY11,$BA$2:$BC$4,3,0),0) -> 0 | BA11: 秘术武者 | BB11: =IF($BB$2="秘术武者",$BC$2,IF($BB$3="秘术武者",$BC$3,IF($BB$4="秘术武者",$BC$4,0))) -> 0 | BC11: =IF($AT$9=0,IF($AT$10=0,IF(SUM(BB6:BB10)=0,ROUNDUP(BB11/3,0),ROUNDDOWN(BB11/3,0)),ROUNDDOWN(BB11/3,0)),ROUNDDOWN(BB11/3,0)) -> 0 | BE11: 9 | BF11: 4 | BG11: 3 | BH11: 3 | BI11: 3 | BJ11: 1 | BO11: 57 | BP11: 9 | BU11: 2 | BV11: 9 | BX11: 2 | CA11: 9 | CF11: 4 | CH11: 术士 | CI11: 28 | CJ11: 29 | CK11: 30 | CL11: 1 | CM11: {=_xlfn.IFS($AZ$11=20,32,$AZ$11>=19,31,$AZ$11>=7,30,$AZ$11>=5,29,$AZ$11>=4,28,$AZ$11>=3,27,$AZ$11=2,26,$AZ$11=1,14,1,0)} -> 0 | CN11: =IFERROR(IF(CN10+1>CS2,IF(CN10+1>CS2,IF(CR3+CR10>CS3,"",CR3+CR10)),CN10+1),"") -> 6 | CO11: {=IFERROR(INDEX($B$34:$BO$262,CN11,$CP$2),"")} | CP11: {=IFERROR(INDEX($B$34:$BO$262,CN11,$CQ$2),"")} | CQ11: {=IF(IFERROR(INDEX($B$34:$BO$262,CN11,$CO$2),"")=0,"",IFERROR(INDEX($B$34:$BO$262,CN11,$CO$2),""))} | CR11: =IFERROR(IF(CN10+1>CS2,CR10+1,0),"") -> 0 | CT11: =IFERROR(IF(OR(CO15="",COUNTIF($CW$2:$CW$81,CO15)),"",CO15),"") | CU11: {=INDEX(CT:CT,SMALL(IF($CT$2:$CT$101<>"",ROW($CT$2:$CT$101),142),ROW(CT10)))&""} | CV11: =IFERROR(VLOOKUP(CW11,$CO$6:$CQ$105,3,FALSE),"") | CW11: =IF(主要!AX20="","",主要!AX20) | CX11: =IFERROR(VLOOKUP(CW11,$CO$6:$CQ$105,2,FALSE),"")
A12: 10 | B12: 术士 | C12: 畸变术法 | D12: 时械术法 | E12: 龙族术法 | F12: 狂野术法 | G12: =IF(自定义调整栏!$E$3="O","神圣之魂","") -> 神圣之魂 | H12: =IF(自定义调整栏!$E$3="O","幽影魔法","") -> 幽影魔法 | I12: =IF(自定义调整栏!$E$3="O","风暴术法","") -> 风暴术法 | J12: =IF(自定义调整栏!$E$26="O","符文之子","") | O12: =IF(自定义调整栏!$E$39="O","亵渎术法","") | Q12: =IF(自定义调整栏!$E$10="O","咒火术法","") -> 咒火术法 | S12: =IF(自定义调整栏!$E$28="O","妄质之魂","") | U12: =IF(自定义调整栏!$E$30="O","织光者","") | W12: =IF(自定义调整栏!$E$35="O","猩红术法","") | X12: =IF(自定义调整栏!$E$32="O","荒漠之魂","") | Y12: =IF(自定义调整栏!$E$33="O","鬼之血脉","") | Z12: =IF(自定义调整栏!$E$36="O","饥欲之暗","") | AA12: {=IFERROR(INDEX($B$1:$B$22,SMALL(IF($B$1:$B$22<>"",ROW($B$1:$B$22),4^8),ROW(12:12)))&"","")} -> 术士 | AC12: =IFERROR(IF(VLOOKUP(AB2,$B$3:$Z$22,13,FALSE)=0,"",VLOOKUP(AB2,$B$3:$Z$22,13,FALSE)),"") | AD12: {=IFERROR(INDEX($AC$1:$AC$24,SMALL(IF($AC$1:$AC$24<>"",ROW($AC$1:$AC$24),4^8),ROW(AC11)))&"","")} | AF12: =IFERROR(IF(VLOOKUP(AE2,$B$3:$Z$22,13,FALSE)=0,"",VLOOKUP(AE2,$B$3:$Z$22,13,FALSE)),"") | AG12: {=IFERROR(INDEX($AF$1:$AF$24,SMALL(IF($AF$1:$AF$24<>"",ROW($AF$1:$AF$24),4^8),ROW(11:11)))&"","")} | AI12: =IFERROR(IF(VLOOKUP(AH2,$B$3:$Z$22,13,FALSE)=0,"",VLOOKUP(AH2,$B$3:$Z$22,13,FALSE)),"") | AJ12: {=IFERROR(INDEX($AI$1:$AI$24,SMALL(IF($AI$1:$AI$24<>"",ROW($AI$1:$AI$24),4^8),ROW(11:11)))&"","")} | AL12: =IFERROR(IF(VLOOKUP(AK2,$B$3:$Z$22,13,FALSE)=0,"",VLOOKUP(AK2,$B$3:$Z$22,13,FALSE)),"") | AM12: {=IFERROR(INDEX($AL$1:$AL$24,SMALL(IF($AL$1:$AL$24<>"",ROW($AL$1:$AL$24),4^8),ROW(11:11)))&"","")} | AO12: 药剂师 | AP12: D8 | AQ12: 1环 | AR12: =IFERROR(VLOOKUP($AR$11,$BE$2:$BO$22,2,FALSE),0) -> 0 | AY12: 魔契师 | AZ12: =IFERROR(VLOOKUP(AY12,$BA$2:$BC$4,3,0),0) -> 0 | BE12: 10 | BF12: 4 | BG12: 3 | BH12: 3 | BI12: 3 | BJ12: 2 | BO12: 64 | BP12: 10 | BU12: 2 | BV12: 10 | BX12: 2 | CA12: 10 | CF12: 4 | CH12: 魔契师 | CI12: 31 | CJ12: 32 | CK12: 33 | CL12: 1 | CM12: {=_xlfn.IFS($AZ$12=20,73,$AZ$12>=19,72,$AZ$12>=15,71,$AZ$12>=12,69,$AZ$12>=11,67,$AZ$12>=9,66,$AZ$12>=7,61,$AZ$12>=5,55,$AZ$12>=4,42,$AZ$12>=3,41,$AZ$12=2,40,$AZ$12=1,25,1,0)} -> 0 | CN12: =IFERROR(IF(CN11+1>CS2,IF(CN11+1>CS2,IF(CR3+CR11>CS3,"",CR3+CR11)),CN11+1),"") -> 7 | CO12: {=IFERROR(INDEX($B$34:$BO$262,CN12,$CP$2),"")} | CP12: {=IFERROR(INDEX($B$34:$BO$262,CN12,$CQ$2),"")} | CQ12: {=IF(IFERROR(INDEX($B$34:$BO$262,CN12,$CO$2),"")=0,"",IFERROR(INDEX($B$34:$BO$262,CN12,$CO$2),""))} | CR12: =IFERROR(IF(CN11+1>CS2,CR11+1,0),"") -> 0 | CT12: =IFERROR(IF(OR(CO16="",COUNTIF($CW$2:$CW$81,CO16)),"",CO16),"") | CU12: {=INDEX(CT:CT,SMALL(IF($CT$2:$CT$101<>"",ROW($CT$2:$CT$101),142),ROW(CT11)))&""} | CV12: =IFERROR(VLOOKUP(CW12,$CO$6:$CQ$105,3,FALSE),"") | CW12: =IF(主要!AX21="","",主要!AX21) | CX12: =IFERROR(VLOOKUP(CW12,$CO$6:$CQ$105,2,FALSE),"")
A13: 11 | B13: 魔契师 | C13: 至高妖精宗主 | D13: 天界宗主 | E13: 邪魔宗主 | F13: 旧日支配者宗主 | G13: =IF(自定义调整栏!$E$3="O","咒剑","") -> 咒剑 | H13: =IF(自定义调整栏!$E$4="O","巨灵宗主","") -> 巨灵宗主 | I13: =IF(自定义调整栏!$E$4="O","深海意志","") -> 深海意志 | J13: =IF(自定义调整栏!$E$19="O","死灵宗主","") -> 死灵宗主 | K13: =IF(自定义调整栏!$E$34="O","未来的你宗主","") | L13: =IF(自定义调整栏!$E$29="O","猎食者","") | N13: =IF(自定义调整栏!$E$40="O","契灵宗主","") | O13: =IF(自定义调整栏!$E$39="O","巫王宗主","") | S13: =IF(自定义调整栏!$E$28="O","域外天魔","") | T13: =IF(自定义调整栏!$E$28="O","畸变血肉","") | U13: =IF(自定义调整栏!$E$30="O","悲伤之母","") | V13: =IF(自定义调整栏!$E$35="O","愚神宗主","") | W13: =IF(自定义调整栏!$E$35="O","角之王宗主","") | X13: =IF(自定义调整栏!$E$32="O","众首","") | Y13: =IF(自定义调整栏!$E$33="O","灯笼","") | Z13: =IF(自定义调整栏!$E$36="O","崇高猫猫庭","") | AA13: {=IFERROR(INDEX($B$1:$B$22,SMALL(IF($B$1:$B$22<>"",ROW($B$1:$B$22),4^8),ROW(13:13)))&"","")} -> 魔契师 | AC13: =IFERROR(IF(VLOOKUP(AB2,$B$3:$Z$22,14,FALSE)=0,"",VLOOKUP(AB2,$B$3:$Z$22,14,FALSE)),"") | AD13: {=IFERROR(INDEX($AC$1:$AC$24,SMALL(IF($AC$1:$AC$24<>"",ROW($AC$1:$AC$24),4^8),ROW(AC12)))&"","")} | AF13: =IFERROR(IF(VLOOKUP(AE2,$B$3:$Z$22,14,FALSE)=0,"",VLOOKUP(AE2,$B$3:$Z$22,14,FALSE)),"") | AG13: {=IFERROR(INDEX($AF$1:$AF$24,SMALL(IF($AF$1:$AF$24<>"",ROW($AF$1:$AF$24),4^8),ROW(12:12)))&"","")} | AI13: =IFERROR(IF(VLOOKUP(AH2,$B$3:$Z$22,14,FALSE)=0,"",VLOOKUP(AH2,$B$3:$Z$22,14,FALSE)),"") | AJ13: {=IFERROR(INDEX($AI$1:$AI$24,SMALL(IF($AI$1:$AI$24<>"",ROW($AI$1:$AI$24),4^8),ROW(12:12)))&"","")} | AL13: =IFERROR(IF(VLOOKUP(AK2,$B$3:$Z$22,14,FALSE)=0,"",VLOOKUP(AK2,$B$3:$Z$22,14,FALSE)),"") | AM13: {=IFERROR(INDEX($AL$1:$AL$24,SMALL(IF($AL$1:$AL$24<>"",ROW($AL$1:$AL$24),4^8),ROW(12:12)))&"","")} | AO13: 铳士 | AP13: D8 | AQ13: 2环 | AR13: =IFERROR(VLOOKUP($AR$11,$BE$2:$BO$22,3,FALSE),0) -> 0 | AY13: 法师 | AZ13: =IFERROR(VLOOKUP(AY13,$BA$2:$BC$4,3,0),0) -> 0 | BE13: 11 | BF13: 4 | BG13: 3 | BH13: 3 | BI13: 3 | BJ13: 2 | BK13: 1 | BO13: 73 | BP13: 11 | BU13: 3 | BV13: 11 | BX13: 2 | CA13: 11 | CF13: 4 | CH13: 法师 | CI13: 34 | CJ13: 35 | CK13: 36 | CL13: 1 | CM13: {=_xlfn.IFS($AZ$13=20,26,$AZ$13>=19,25,$AZ$13>=18,24,$AZ$13>=5,23,$AZ$13>=4,22,$AZ$13>=3,21,$AZ$13=2,20,$AZ$13=1,19,1,0)} -> 0 | CN13: =IFERROR(IF(CN12+1>CS2,IF(CN12+1>CS2,IF(CR3+CR12>CS3,"",CR3+CR12)),CN12+1),"") -> 8 | CO13: {=IFERROR(INDEX($B$34:$BO$262,CN13,$CP$2),"")} | CP13: {=IFERROR(INDEX($B$34:$BO$262,CN13,$CQ$2),"")} | CQ13: {=IF(IFERROR(INDEX($B$34:$BO$262,CN13,$CO$2),"")=0,"",IFERROR(INDEX($B$34:$BO$262,CN13,$CO$2),""))} | CR13: =IFERROR(IF(CN12+1>CS2,CR12+1,0),"") -> 0 | CT13: =IFERROR(IF(OR(CO17="",COUNTIF($CW$2:$CW$81,CO17)),"",CO17),"") | CU13: {=INDEX(CT:CT,SMALL(IF($CT$2:$CT$101<>"",ROW($CT$2:$CT$101),142),ROW(CT12)))&""} | CV13: =IFERROR(VLOOKUP(CW13,$CO$6:$CQ$105,3,FALSE),"") | CW13: =IF(主要!AX22="","",主要!AX22) | CX13: =IFERROR(VLOOKUP(CW13,$CO$6:$CQ$105,2,FALSE),"")
A14: 12 | B14: 法师 | C14: 防护师 | D14: 预言师 | E14: 塑能师 | F14: 幻术师 | G14: =IF(自定义调整栏!$E$3="O","战争魔法","") -> 战争魔法 | H14: =IF(自定义调整栏!$E$4="O","书士会","") -> 书士会 | I14: =IF(自定义调整栏!$E$23="O","时间魔法","") -> 时间魔法 | J14: =IF(自定义调整栏!$E$23="O","重力魔法","") -> 重力魔法 | K14: =IF(自定义调整栏!$E$26="O","血魔法","") | L14: =IF(自定义调整栏!$E$29="O","地脉魔法","") | Q14: =IF(自定义调整栏!$E$10="O","剑咏者","") -> 剑咏者 | S14: =IF(自定义调整栏!$E$28="O","叛道法师魔","") | U14: =IF(自定义调整栏!$E$30="O","暗影","") | V14: =IF(自定义调整栏!$E$35="O","神秘学者","") | W14: =IF(自定义调整栏!$E$35="O","贤者","") | X14: =IF(自定义调整栏!$E$32="O","远古魔杖学","") | Y14: =IF(自定义调整栏!$E$33="O","折纸魔法师","") | Z14: =IF(自定义调整栏!$E$36="O","司书","") | AA14: {=IFERROR(INDEX($B$1:$B$22,SMALL(IF($B$1:$B$22<>"",ROW($B$1:$B$22),4^8),ROW(14:14)))&"","")} -> 法师 | AC14: =IFERROR(IF(VLOOKUP(AB2,$B$3:$Z$22,15,FALSE)=0,"",VLOOKUP(AB2,$B$3:$Z$22,15,FALSE)),"") | AD14: {=IFERROR(INDEX($AC$1:$AC$24,SMALL(IF($AC$1:$AC$24<>"",ROW($AC$1:$AC$24),4^8),ROW(AC13)))&"","")} | AF14: =IFERROR(IF(VLOOKUP(AE2,$B$3:$Z$22,15,FALSE)=0,"",VLOOKUP(AE2,$B$3:$Z$22,15,FALSE)),"") | AG14: {=IFERROR(INDEX($AF$1:$AF$24,SMALL(IF($AF$1:$AF$24<>"",ROW($AF$1:$AF$24),4^8),ROW(13:13)))&"","")} | AI14: =IFERROR(IF(VLOOKUP(AH2,$B$3:$Z$22,15,FALSE)=0,"",VLOOKUP(AH2,$B$3:$Z$22,15,FALSE)),"") | AJ14: {=IFERROR(INDEX($AI$1:$AI$24,SMALL(IF($AI$1:$AI$24<>"",ROW($AI$1:$AI$24),4^8),ROW(13:13)))&"","")} | AL14: =IFERROR(IF(VLOOKUP(AK2,$B$3:$Z$22,15,FALSE)=0,"",VLOOKUP(AK2,$B$3:$Z$22,15,FALSE)),"") | AM14: {=IFERROR(INDEX($AL$1:$AL$24,SMALL(IF($AL$1:$AL$24<>"",ROW($AL$1:$AL$24),4^8),ROW(13:13)))&"","")} | AO14: 战士 | AP14: D10 | AQ14: 3环 | AR14: =IFERROR(VLOOKUP($AR$11,$BE$2:$BO$22,4,FALSE),0) -> 0 | AY14: 奇械师 | AZ14: =IFERROR(VLOOKUP(AY14,$BA$2:$BC$4,3,0),0) -> 0 | BE14: 12 | BF14: 4 | BG14: 3 | BH14: 3 | BI14: 3 | BJ14: 2 | BK14: 1 | BO14: 73 | BP14: 12 | BU14: 3 | BV14: 12 | BX14: 2 | CA14: 12 | CF14: 4 | CH14: 奇械师 | CI14: 37 | CJ14: 38 | CK14: 39 | CL14: 1 | CM14: {=_xlfn.IFS($AZ$14=20,29,$AZ$14>=19,28,$AZ$14>=18,27,$AZ$14>=14,26,$AZ$14>=11,24,$AZ$14>=10,23,$AZ$14>=7,21,$AZ$14>=6,20,$AZ$14>=4,18,$AZ$14>=3,17,$AZ$14=2,16,$AZ$14=1,15,1,0)} -> 0 | CN14: =IFERROR(IF(CN13+1>CS2,IF(CN13+1>CS2,IF(CR3+CR13>CS3,"",CR3+CR13)),CN13+1),"") -> 9 | CO14: {=IFERROR(INDEX($B$34:$BO$262,CN14,$CP$2),"")} | CP14: {=IFERROR(INDEX($B$34:$BO$262,CN14,$CQ$2),"")} | CQ14: {=IF(IFERROR(INDEX($B$34:$BO$262,CN14,$CO$2),"")=0,"",IFERROR(INDEX($B$34:$BO$262,CN14,$CO$2),""))} | CR14: =IFERROR(IF(CN13+1>CS2,CR13+1,0),"") -> 0 | CT14: =IFERROR(IF(OR(CO18="",COUNTIF($CW$2:$CW$81,CO18)),"",CO18),"") | CU14: {=INDEX(CT:CT,SMALL(IF($CT$2:$CT$101<>"",ROW($CT$2:$CT$101),142),ROW(CT13)))&""} | CV14: =IFERROR(VLOOKUP(CW14,$CO$6:$CQ$105,3,FALSE),"") | CW14: =IF(主要!AX23="","",主要!AX23) | CX14: =IFERROR(VLOOKUP(CW14,$CO$6:$CQ$105,2,FALSE),"")
A15: 13 | B15: =IF(自定义调整栏!$E$13="O","奇械师","") -> 奇械师 | C15: 炼金师 | D15: 装甲师 | E15: 魔炮师 | F15: 战地匠师 | G15: 制图师 | AA15: {=IFERROR(INDEX($B$1:$B$22,SMALL(IF($B$1:$B$22<>"",ROW($B$1:$B$22),4^8),ROW(15:15)))&"","")} -> 奇械师 | AC15: =IFERROR(IF(VLOOKUP(AB2,$B$3:$Z$22,16,FALSE)=0,"",VLOOKUP(AB2,$B$3:$Z$22,16,FALSE)),"") | AD15: {=IFERROR(INDEX($AC$1:$AC$24,SMALL(IF($AC$1:$AC$24<>"",ROW($AC$1:$AC$24),4^8),ROW(AC14)))&"","")} | AF15: =IFERROR(IF(VLOOKUP(AE2,$B$3:$Z$22,16,FALSE)=0,"",VLOOKUP(AE2,$B$3:$Z$22,16,FALSE)),"") | AG15: {=IFERROR(INDEX($AF$1:$AF$24,SMALL(IF($AF$1:$AF$24<>"",ROW($AF$1:$AF$24),4^8),ROW(14:14)))&"","")} | AI15: =IFERROR(IF(VLOOKUP(AH2,$B$3:$Z$22,16,FALSE)=0,"",VLOOKUP(AH2,$B$3:$Z$22,16,FALSE)),"") | AJ15: {=IFERROR(INDEX($AI$1:$AI$24,SMALL(IF($AI$1:$AI$24<>"",ROW($AI$1:$AI$24),4^8),ROW(14:14)))&"","")} | AL15: =IFERROR(IF(VLOOKUP(AK2,$B$3:$Z$22,16,FALSE)=0,"",VLOOKUP(AK2,$B$3:$Z$22,16,FALSE)),"") | AM15: {=IFERROR(INDEX($AL$1:$AL$24,SMALL(IF($AL$1:$AL$24<>"",ROW($AL$1:$AL$24),4^8),ROW(14:14)))&"","")} | AO15: 圣武士 | AP15: D10 | AQ15: 4环 | AR15: =IFERROR(VLOOKUP($AR$11,$BE$2:$BO$22,5,FALSE),0) -> 0 | AY15: 灵能使 | AZ15: =IFERROR(VLOOKUP(AY15,$BA$2:$BC$4,3,0),0) -> 0 | BE15: 13 | BF15: 4 | BG15: 3 | BH15: 3 | BI15: 3 | BJ15: 2 | BK15: 1 | BL15: 1 | BO15: 83 | BP15: 13 | BU15: 3 | BV15: 13 | BY15: 2 | CA15: 13 | CF15: 5 | CH15: 灵能使 | CI15: 40 | CJ15: 41 | CK15: 42 | CL15: 1 | CM15: {=_xlfn.IFS($AZ$15>=20,34,$AZ$15>=19,33,$AZ$15>=18,32,$AZ$15>=7,31,$AZ$15>=5,30,$AZ$15>=4,29,$AZ$15>=3,28,$AZ$15=2,27,$AZ$15=1,15,1,0)} -> 0 | CN15: =IFERROR(IF(CN14+1>CS2,IF(CN14+1>CS2,IF(CR3+CR14>CS3,"",CR3+CR14)),CN14+1),"") -> 10 | CO15: {=IFERROR(INDEX($B$34:$BO$262,CN15,$CP$2),"")} | CP15: {=IFERROR(INDEX($B$34:$BO$262,CN15,$CQ$2),"")} | CQ15: {=IF(IFERROR(INDEX($B$34:$BO$262,CN15,$CO$2),"")=0,"",IFERROR(INDEX($B$34:$BO$262,CN15,$CO$2),""))} | CR15: =IFERROR(IF(CN14+1>CS2,CR14+1,0),"") -> 0 | CT15: =IFERROR(IF(OR(CO19="",COUNTIF($CW$2:$CW$81,CO19)),"",CO19),"") | CU15: {=INDEX(CT:CT,SMALL(IF($CT$2:$CT$101<>"",ROW($CT$2:$CT$101),142),ROW(CT14)))&""} | CV15: =IFERROR(VLOOKUP(CW15,$CO$6:$CQ$105,3,FALSE),"") | CW15: =IF(主要!AX24="","",主要!AX24) | CX15: =IFERROR(VLOOKUP(CW15,$CO$6:$CQ$105,2,FALSE),"")
A16: 14 | B16: =IF(自定义调整栏!$E$41="O","灵能使","") | C16: 蜕变使 | D16: 裂空使 | E16: 念动使 | F16: 传心使 | AA16: {=IFERROR(INDEX($B$1:$B$22,SMALL(IF($B$1:$B$22<>"",ROW($B$1:$B$22),4^8),ROW(16:16)))&"","")} | AC16: =IFERROR(IF(VLOOKUP(AB2,$B$3:$Z$22,17,FALSE)=0,"",VLOOKUP(AB2,$B$3:$Z$22,17,FALSE)),"") | AD16: {=IFERROR(INDEX($AC$1:$AC$24,SMALL(IF($AC$1:$AC$24<>"",ROW($AC$1:$AC$24),4^8),ROW(AC15)))&"","")} | AF16: =IFERROR(IF(VLOOKUP(AE2,$B$3:$Z$22,17,FALSE)=0,"",VLOOKUP(AE2,$B$3:$Z$22,17,FALSE)),"") | AG16: {=IFERROR(INDEX($AF$1:$AF$24,SMALL(IF($AF$1:$AF$24<>"",ROW($AF$1:$AF$24),4^8),ROW(15:15)))&"","")} | AI16: =IFERROR(IF(VLOOKUP(AH2,$B$3:$Z$22,17,FALSE)=0,"",VLOOKUP(AH2,$B$3:$Z$22,17,FALSE)),"") | AJ16: {=IFERROR(INDEX($AI$1:$AI$24,SMALL(IF($AI$1:$AI$24<>"",ROW($AI$1:$AI$24),4^8),ROW(15:15)))&"","")} | AL16: =IFERROR(IF(VLOOKUP(AK2,$B$3:$Z$22,17,FALSE)=0,"",VLOOKUP(AK2,$B$3:$Z$22,17,FALSE)),"") | AM16: {=IFERROR(INDEX($AL$1:$AL$24,SMALL(IF($AL$1:$AL$24<>"",ROW($AL$1:$AL$24),4^8),ROW(15:15)))&"","")} | AO16: 游侠 | AP16: D10 | AQ16: 5环 | AR16: =IFERROR(VLOOKUP($AR$11,$BE$2:$BO$22,6,FALSE),0) -> 0 | AS16: 魔契师 | AU16: 药剂师 | AY16: 血猎手 | AZ16: =IFERROR(VLOOKUP(AY16,$BA$2:$BC$4,3,0),0) -> 0 | BE16: 14 | BF16: 4 | BG16: 3 | BH16: 3 | BI16: 3 | BJ16: 2 | BK16: 1 | BL16: 1 | BO16: 83 | BP16: 14 | BU16: 3 | BV16: 14 | BY16: 2 | CA16: 14 | CF16: 5 | CH16: 血猎手 | CI16: 43 | CJ16: 44 | CK16: 45 | CL16: 1 | CM16: {=_xlfn.IFS($AZ$16>=20,38,$AZ$16>=19,37,$AZ$16>=18,36,$AZ$16>=15,34,$AZ$16>=14,32,$AZ$16>=13,28,$AZ$16>=10,27,$AZ$16>=9,26,$AZ$16>=6,25,$AZ$16>=5,24,$AZ$16>=4,23,$AZ$16>=3,22,$AZ$16=2,21,$AZ$16=1,17,1,0)} -> 0 | CN16: =IFERROR(IF(CN15+1>CS2,IF(CN15+1>CS2,IF(CR3+CR15>CS3,"",CR3+CR15)),CN15+1),"") -> 11 | CO16: {=IFERROR(INDEX($B$34:$BO$262,CN16,$CP$2),"")} | CP16: {=IFERROR(INDEX($B$34:$BO$262,CN16,$CQ$2),"")} | CQ16: {=IF(IFERROR(INDEX($B$34:$BO$262,CN16,$CO$2),"")=0,"",IFERROR(INDEX($B$34:$BO$262,CN16,$CO$2),""))} | CR16: =IFERROR(IF(CN15+1>CS2,CR15+1,0),"") -> 0 | CT16: =IFERROR(IF(OR(CO20="",COUNTIF($CW$2:$CW$81,CO20)),"",CO20),"") | CU16: {=INDEX(CT:CT,SMALL(IF($CT$2:$CT$101<>"",ROW($CT$2:$CT$101),142),ROW(CT15)))&""} | CV16: =IFERROR(VLOOKUP(CW16,$CO$6:$CQ$105,3,FALSE),"") | CW16: =IF(主要!AX25="","",主要!AX25) | CX16: =IFERROR(VLOOKUP(CW16,$CO$6:$CQ$105,2,FALSE),"")
A17: 15 | B17: =IF(自定义调整栏!$E$25="O","血猎手","") | C17: 弑灵圣约 | D17: 化狼圣约 | E17: 突变圣约 | F17: 渎魂圣约 | AA17: {=IFERROR(INDEX($B$1:$B$22,SMALL(IF($B$1:$B$22<>"",ROW($B$1:$B$22),4^8),ROW(17:17)))&"","")} | AC17: =IFERROR(IF(VLOOKUP(AB2,$B$3:$Z$22,18,FALSE)=0,"",VLOOKUP(AB2,$B$3:$Z$22,18,FALSE)),"") | AD17: {=IFERROR(INDEX($AC$1:$AC$24,SMALL(IF($AC$1:$AC$24<>"",ROW($AC$1:$AC$24),4^8),ROW(AC16)))&"","")} | AF17: =IFERROR(IF(VLOOKUP(AE2,$B$3:$Z$22,18,FALSE)=0,"",VLOOKUP(AE2,$B$3:$Z$22,18,FALSE)),"") | AG17: {=IFERROR(INDEX($AF$1:$AF$24,SMALL(IF($AF$1:$AF$24<>"",ROW($AF$1:$AF$24),4^8),ROW(16:16)))&"","")} | AI17: =IFERROR(IF(VLOOKUP(AH2,$B$3:$Z$22,18,FALSE)=0,"",VLOOKUP(AH2,$B$3:$Z$22,18,FALSE)),"") | AJ17: {=IFERROR(INDEX($AI$1:$AI$24,SMALL(IF($AI$1:$AI$24<>"",ROW($AI$1:$AI$24),4^8),ROW(16:16)))&"","")} | AL17: =IFERROR(IF(VLOOKUP(AK2,$B$3:$Z$22,18,FALSE)=0,"",VLOOKUP(AK2,$B$3:$Z$22,18,FALSE)),"") | AM17: {=IFERROR(INDEX($AL$1:$AL$24,SMALL(IF($AL$1:$AL$24<>"",ROW($AL$1:$AL$24),4^8),ROW(16:16)))&"","")} | AO17: 血猎手 | AP17: D10 | AQ17: 6环 | AR17: =IFERROR(VLOOKUP($AR$11,$BE$2:$BO$22,7,FALSE),0) -> 0 | AS17: 1环 | AT17: =IFERROR(VLOOKUP($AZ$12,$BP$2:$BU$22,2,FALSE),0) -> 0 | AU17: 1环 | AV17: =IFERROR(VLOOKUP($AZ$17,$CA$2:$CF$22,2,FALSE),0) -> 0 | AW17: 渎魂圣约 | AX17: =IF($BB$2="渎魂圣约",$BC$2,IF($BB$3="渎魂圣约",$BC$3,IF($BB$4="渎魂圣约",$BC$4,0))) -> 0 | AY17: 药剂师 | AZ17: =IFERROR(VLOOKUP(AY17,$BA$2:$BC$4,3,0),0) -> 0 | BE17: 15 | BF17: 4 | BG17: 3 | BH17: 3 | BI17: 3 | BJ17: 2 | BK17: 1 | BL17: 1 | BM17: 1 | BO17: 94 | BP17: 15 | BU17: 3 | BV17: 15 | BY17: 2 | CA17: 15 | CF17: 5 | CH17: 药剂师 | CI17: 46 | CJ17: 47 | CK17: 48 | CL17: 1 | CM17: {=_xlfn.IFS($AZ$17=20,59,$AZ$17>=19,58,$AZ$17>=14,57,$AZ$17>=11,53,$AZ$17>=10,52,$AZ$17>=6,46,$AZ$17>=4,35,$AZ$17=3,34,$AZ$17=2,33,$AZ$17=1,13,1,0)} -> 0 | CN17: =IFERROR(IF(CN16+1>CS2,IF(CN16+1>CS2,IF(CR3+CR16>CS3,"",CR3+CR16)),CN16+1),"") -> 12 | CO17: {=IFERROR(INDEX($B$34:$BO$262,CN17,$CP$2),"")} | CP17: {=IFERROR(INDEX($B$34:$BO$262,CN17,$CQ$2),"")} | CQ17: {=IF(IFERROR(INDEX($B$34:$BO$262,CN17,$CO$2),"")=0,"",IFERROR(INDEX($B$34:$BO$262,CN17,$CO$2),""))} | CR17: =IFERROR(IF(CN16+1>CS2,CR16+1,0),"") -> 0 | CT17: =IFERROR(IF(OR(CO21="",COUNTIF($CW$2:$CW$81,CO21)),"",CO21),"") | CU17: {=INDEX(CT:CT,SMALL(IF($CT$2:$CT$101<>"",ROW($CT$2:$CT$101),142),ROW(CT16)))&""} | CV17: =IFERROR(VLOOKUP(CW17,$CO$6:$CQ$105,3,FALSE),"") | CW17: =IF(主要!AX26="","",主要!AX26) | CX17: =IFERROR(VLOOKUP(CW17,$CO$6:$CQ$105,2,FALSE),"")
A18: 16 | B18: =IF(自定义调整栏!$E$28="O","药剂师","") | C18: 精神师 | D18: 化学家 | E18: 驱邪师 | F18: 突变者 | G18: 病原师 | H18: 掘坟人 | AA18: {=IFERROR(INDEX($B$1:$B$22,SMALL(IF($B$1:$B$22<>"",ROW($B$1:$B$22),4^8),ROW(18:18)))&"","")} | AC18: =IFERROR(IF(VLOOKUP(AB2,$B$3:$Z$22,19,FALSE)=0,"",VLOOKUP(AB2,$B$3:$Z$22,19,FALSE)),"") | AD18: {=IFERROR(INDEX($AC$1:$AC$24,SMALL(IF($AC$1:$AC$24<>"",ROW($AC$1:$AC$24),4^8),ROW(AC17)))&"","")} | AF18: =IFERROR(IF(VLOOKUP(AE2,$B$3:$Z$22,19,FALSE)=0,"",VLOOKUP(AE2,$B$3:$Z$22,19,FALSE)),"") | AG18: {=IFERROR(INDEX($AF$1:$AF$24,SMALL(IF($AF$1:$AF$24<>"",ROW($AF$1:$AF$24),4^8),ROW(17:17)))&"","")} | AI18: =IFERROR(IF(VLOOKUP(AH2,$B$3:$Z$22,19,FALSE)=0,"",VLOOKUP(AH2,$B$3:$Z$22,19,FALSE)),"") | AJ18: {=IFERROR(INDEX($AI$1:$AI$24,SMALL(IF($AI$1:$AI$24<>"",ROW($AI$1:$AI$24),4^8),ROW(17:17)))&"","")} | AL18: =IFERROR(IF(VLOOKUP(AK2,$B$3:$Z$22,19,FALSE)=0,"",VLOOKUP(AK2,$B$3:$Z$22,19,FALSE)),"") | AM18: {=IFERROR(INDEX($AL$1:$AL$24,SMALL(IF($AL$1:$AL$24<>"",ROW($AL$1:$AL$24),4^8),ROW(17:17)))&"","")} | AO18: 邪狱使 | AP18: D10 | AQ18: 7环 | AR18: =IFERROR(VLOOKUP($AR$11,$BE$2:$BO$22,8,FALSE),0) -> 0 | AS18: 2环 | AT18: =IFERROR(VLOOKUP($AZ$12,$BP$2:$BU$22,3,FALSE),0) -> 0 | AU18: 2环 | AV18: =IFERROR(VLOOKUP($AZ$17,$CA$2:$CF$22,3,FALSE),0) -> 0 | AW18: 1环 | AX18: =IFERROR(VLOOKUP($AX$17,$BV$2:$BZ$22,2,FALSE),0) -> 0 | AY18: 铳士 | AZ18: =IFERROR(VLOOKUP(AY18,$BA$2:$BC$4,3,0),0) -> 0 | BE18: 16 | BF18: 4 | BG18: 3 | BH18: 3 | BI18: 3 | BJ18: 2 | BK18: 1 | BL18: 1 | BM18: 1 | BO18: 94 | BP18: 16 | BU18: 3 | BV18: 16 | BY18: 2 | CA18: 16 | CF18: 5 | CH18: 铳士 | CI18: 49 | CJ18: 50 | CK18: 51 | CL18: 1 | CM18: {=_xlfn.IFS($AZ$18=20,28,$AZ$18>=19,27,$AZ$18>=18,26,$AZ$18>=15,25,$AZ$18>=13,24,$AZ$18>=11,23,$AZ$18>=7,22,$AZ$18>=5,21,$AZ$18>=4,19,$AZ$18=3,18,$AZ$18=2,17,$AZ$18=1,9,1,0)} -> 0 | CN18: =IFERROR(IF(CN17+1>CS2,IF(CN17+1>CS2,IF(CR3+CR17>CS3,"",CR3+CR17)),CN17+1),"") -> 13 | CO18: {=IFERROR(INDEX($B$34:$BO$262,CN18,$CP$2),"")} | CP18: {=IFERROR(INDEX($B$34:$BO$262,CN18,$CQ$2),"")} | CQ18: {=IF(IFERROR(INDEX($B$34:$BO$262,CN18,$CO$2),"")=0,"",IFERROR(INDEX($B$34:$BO$262,CN18,$CO$2),""))} | CR18: =IFERROR(IF(CN17+1>CS2,CR17+1,0),"") -> 0 | CT18: =IFERROR(IF(OR(CO22="",COUNTIF($CW$2:$CW$81,CO22)),"",CO22),"") | CU18: {=INDEX(CT:CT,SMALL(IF($CT$2:$CT$101<>"",ROW($CT$2:$CT$101),142),ROW(CT17)))&""} | CV18: =IFERROR(VLOOKUP(CW18,$CO$6:$CQ$105,3,FALSE),"") | CW18: =IF(主要!AX27="","",主要!AX27) | CX18: =IFERROR(VLOOKUP(CW18,$CO$6:$CQ$105,2,FALSE),"")
A19: 17 | B19: =IF(自定义调整栏!$E$34="O","铳士","") | C19: 死瞳客 | D19: 豪赌客 | E19: 密间客 | F19: 魔弹客 | G19: 花枪客 | H19: 白帽客 | AA19: {=IFERROR(INDEX($B$1:$B$22,SMALL(IF($B$1:$B$22<>"",ROW($B$1:$B$22),4^8),ROW(19:19)))&"","")} | AC19: =IFERROR(IF(VLOOKUP(AB2,$B$3:$Z$22,20,FALSE)=0,"",VLOOKUP(AB2,$B$3:$Z$22,20,FALSE)),"") | AD19: {=IFERROR(INDEX($AC$1:$AC$24,SMALL(IF($AC$1:$AC$24<>"",ROW($AC$1:$AC$24),4^8),ROW(AC18)))&"","")} | AF19: =IFERROR(IF(VLOOKUP(AE2,$B$3:$Z$22,20,FALSE)=0,"",VLOOKUP(AE2,$B$3:$Z$22,20,FALSE)),"") | AG19: {=IFERROR(INDEX($AF$1:$AF$24,SMALL(IF($AF$1:$AF$24<>"",ROW($AF$1:$AF$24),4^8),ROW(18:18)))&"","")} | AI19: =IFERROR(IF(VLOOKUP(AH2,$B$3:$Z$22,20,FALSE)=0,"",VLOOKUP(AH2,$B$3:$Z$22,20,FALSE)),"") | AJ19: {=IFERROR(INDEX($AI$1:$AI$24,SMALL(IF($AI$1:$AI$24<>"",ROW($AI$1:$AI$24),4^8),ROW(18:18)))&"","")} | AL19: =IFERROR(IF(VLOOKUP(AK2,$B$3:$Z$22,20,FALSE)=0,"",VLOOKUP(AK2,$B$3:$Z$22,20,FALSE)),"") | AM19: {=IFERROR(INDEX($AL$1:$AL$24,SMALL(IF($AL$1:$AL$24<>"",ROW($AL$1:$AL$24),4^8),ROW(18:18)))&"","")} | AO19: 拳斗士 | AP19: D10 | AQ19: 8环 | AR19: =IFERROR(VLOOKUP($AR$11,$BE$2:$BO$22,9,FALSE),0) -> 0 | AS19: 3环 | AT19: =IFERROR(VLOOKUP($AZ$12,$BP$2:$BU$22,4,FALSE),0) -> 0 | AU19: 3环 | AV19: =IFERROR(VLOOKUP($AZ$17,$CA$2:$CF$22,4,FALSE),0) -> 0 | AW19: 2环 | AX19: =IFERROR(VLOOKUP($AX$17,$BV$2:$BZ$22,3,FALSE),0) -> 0 | AY19: 邪狱使 | AZ19: =IFERROR(VLOOKUP(AY19,$BA$2:$BC$4,3,0),0) -> 0 | BE19: 17 | BF19: 4 | BG19: 3 | BH19: 3 | BI19: 3 | BJ19: 2 | BK19: 1 | BL19: 1 | BM19: 1 | BN19: 1 | BO19: 107 | BP19: 17 | BU19: 4 | BV19: 17 | BY19: 2 | CA19: 17 | CF19: 6 | CH19: 邪狱使 | CI19: 52 | CJ19: 53 | CK19: 54 | CL19: 1 | CM19: {=_xlfn.IFS($AZ$19>=20,41,$AZ$19>=19,40,$AZ$19>=14,39,$AZ$19>=13,38,$AZ$19>=11,30,$AZ$19>=10,29,$AZ$19>=7,28,$AZ$19>=6,22,$AZ$19>=5,21,$AZ$19>=4,20,$AZ$19>=3,19,$AZ$19>=2,17,$AZ$19>=1,10,1,0)} -> 0 | CN19: =IFERROR(IF(CN18+1>CS2,IF(CN18+1>CS2,IF(CR3+CR18>CS3,"",CR3+CR18)),CN18+1),"") -> 14 | CO19: {=IFERROR(INDEX($B$34:$BO$262,CN19,$CP$2),"")} | CP19: {=IFERROR(INDEX($B$34:$BO$262,CN19,$CQ$2),"")} | CQ19: {=IF(IFERROR(INDEX($B$34:$BO$262,CN19,$CO$2),"")=0,"",IFERROR(INDEX($B$34:$BO$262,CN19,$CO$2),""))} | CR19: =IFERROR(IF(CN18+1>CS2,CR18+1,0),"") -> 0 | CT19: =IFERROR(IF(OR(CO23="",COUNTIF($CW$2:$CW$81,CO23)),"",CO23),"") | CU19: {=INDEX(CT:CT,SMALL(IF($CT$2:$CT$101<>"",ROW($CT$2:$CT$101),142),ROW(CT18)))&""} | CV19: =IFERROR(VLOOKUP(CW19,$CO$6:$CQ$105,3,FALSE),"") | CW19: =IF(主要!AX28="","",主要!AX28) | CX19: =IFERROR(VLOOKUP(CW19,$CO$6:$CQ$105,2,FALSE),"")
A20: 18 | B20: =IF(自定义调整栏!$E$31="O","邪狱使","") | C20: 筑灭师 | D20: 狱言家 | E20: 恐惧屠戮者 | F20: 猩红骑士 | G20: 影宗 | AA20: {=IFERROR(INDEX($B$1:$B$22,SMALL(IF($B$1:$B$22<>"",ROW($B$1:$B$22),4^8),ROW(20:20)))&"","")} | AC20: =IFERROR(IF(VLOOKUP(AB2,$B$3:$Z$22,21,FALSE)=0,"",VLOOKUP(AB2,$B$3:$Z$22,21,FALSE)),"") | AD20: {=IFERROR(INDEX($AC$1:$AC$24,SMALL(IF($AC$1:$AC$24<>"",ROW($AC$1:$AC$24),4^8),ROW(AC19)))&"","")} | AF20: =IFERROR(IF(VLOOKUP(AE2,$B$3:$Z$22,21,FALSE)=0,"",VLOOKUP(AE2,$B$3:$Z$22,21,FALSE)),"") | AG20: {=IFERROR(INDEX($AF$1:$AF$24,SMALL(IF($AF$1:$AF$24<>"",ROW($AF$1:$AF$24),4^8),ROW(19:19)))&"","")} | AI20: =IFERROR(IF(VLOOKUP(AH2,$B$3:$Z$22,21,FALSE)=0,"",VLOOKUP(AH2,$B$3:$Z$22,21,FALSE)),"") | AJ20: {=IFERROR(INDEX($AI$1:$AI$24,SMALL(IF($AI$1:$AI$24<>"",ROW($AI$1:$AI$24),4^8),ROW(19:19)))&"","")} | AL20: =IFERROR(IF(VLOOKUP(AK2,$B$3:$Z$22,21,FALSE)=0,"",VLOOKUP(AK2,$B$3:$Z$22,21,FALSE)),"") | AM20: {=IFERROR(INDEX($AL$1:$AL$24,SMALL(IF($AL$1:$AL$24<>"",ROW($AL$1:$AL$24),4^8),ROW(19:19)))&"","")} | AQ20: 9环 | AR20: =IFERROR(VLOOKUP($AR$11,$BE$2:$BO$22,10,FALSE),0) -> 0 | AS20: 4环 | AT20: =IFERROR(VLOOKUP($AZ$12,$BP$2:$BU$22,5,FALSE),0) -> 0 | AU20: 4环 | AV20: =IFERROR(VLOOKUP($AZ$17,$CA$2:$CF$22,5,FALSE),0) -> 0 | AW20: 3环 | AX20: =IFERROR(VLOOKUP($AX$17,$BV$2:$BZ$22,4,FALSE),0) -> 0 | AY20: 拳斗士 | AZ20: =IFERROR(VLOOKUP(AY20,$BA$2:$BC$4,3,0),0) -> 0 | BE20: 18 | BF20: 4 | BG20: 3 | BH20: 3 | BI20: 3 | BJ20: 3 | BK20: 1 | BL20: 1 | BM20: 1 | BN20: 1 | BO20: 114 | BP20: 18 | BU20: 4 | BV20: 18 | BY20: 2 | CA20: 18 | CF20: 6 | CH20: 拳斗士 | CI20: 55 | CJ20: 56 | CK20: 57 | CL20: 1 | CM20: {=_xlfn.IFS($AZ$20>=20,28,$AZ$20>=19,27,$AZ$20>=18,26,$AZ$20>=15,25,$AZ$20>=14,24,$AZ$20>=13,23,$AZ$20>=10,22,$AZ$20>=9,20,$AZ$20>=7,19,$AZ$20>=6,18,$AZ$20>=5,17,$AZ$20>=4,15,$AZ$20>=3,13,$AZ$20>=2,11,$AZ$20>=1,8,1,0)} -> 0 | CN20: =IFERROR(IF(CN19+1>CS2,IF(CN19+1>CS2,IF(CR3+CR19>CS3,"",CR3+CR19)),CN19+1),"") -> 15 | CO20: {=IFERROR(INDEX($B$34:$BO$262,CN20,$CP$2),"")} | CP20: {=IFERROR(INDEX($B$34:$BO$262,CN20,$CQ$2),"")} | CQ20: {=IF(IFERROR(INDEX($B$34:$BO$262,CN20,$CO$2),"")=0,"",IFERROR(INDEX($B$34:$BO$262,CN20,$CO$2),""))} | CR20: =IFERROR(IF(CN19+1>CS2,CR19+1,0),"") -> 0 | CT20: =IFERROR(IF(OR(CO24="",COUNTIF($CW$2:$CW$81,CO24)),"",CO24),"") | CU20: {=INDEX(CT:CT,SMALL(IF($CT$2:$CT$101<>"",ROW($CT$2:$CT$101),142),ROW(CT19)))&""} | CV20: =IFERROR(VLOOKUP(CW20,$CO$6:$CQ$105,3,FALSE),"") | CW20: =IF(主要!AX29="","",主要!AX29) | CX20: =IFERROR(VLOOKUP(CW20,$CO$6:$CQ$105,2,FALSE),"")
A21: 19 | B21: =IF(自定义调整栏!$E$38="O","拳斗士","") | C21: 犬师拳狩 | D21: 惧恶之手 | E21: 怒雷恶氓 | F21: 街角圣徒 | G21: 方圆擂尊 | H21: 甜蜜科学 | AA21: {=IFERROR(INDEX($B$1:$B$22,SMALL(IF($B$1:$B$22<>"",ROW($B$1:$B$22),4^8),ROW(21:21)))&"","")} | AC21: =IFERROR(IF(VLOOKUP(AB2,$B$3:$Z$22,22,FALSE)=0,"",VLOOKUP(AB2,$B$3:$Z$22,22,FALSE)),"") | AD21: {=IFERROR(INDEX($AC$1:$AC$24,SMALL(IF($AC$1:$AC$24<>"",ROW($AC$1:$AC$24),4^8),ROW(AC20)))&"","")} | AF21: =IFERROR(IF(VLOOKUP(AE2,$B$3:$Z$22,22,FALSE)=0,"",VLOOKUP(AE2,$B$3:$Z$22,22,FALSE)),"") | AG21: {=IFERROR(INDEX($AF$1:$AF$24,SMALL(IF($AF$1:$AF$24<>"",ROW($AF$1:$AF$24),4^8),ROW(20:20)))&"","")} | AI21: =IFERROR(IF(VLOOKUP(AH2,$B$3:$Z$22,22,FALSE)=0,"",VLOOKUP(AH2,$B$3:$Z$22,22,FALSE)),"") | AJ21: {=IFERROR(INDEX($AI$1:$AI$24,SMALL(IF($AI$1:$AI$24<>"",ROW($AI$1:$AI$24),4^8),ROW(20:20)))&"","")} | AL21: =IFERROR(IF(VLOOKUP(AK2,$B$3:$Z$22,22,FALSE)=0,"",VLOOKUP(AK2,$B$3:$Z$22,22,FALSE)),"") | AM21: {=IFERROR(INDEX($AL$1:$AL$24,SMALL(IF($AL$1:$AL$24<>"",ROW($AL$1:$AL$24),4^8),ROW(20:20)))&"","")} | AO21: 野蛮人 | AP21: D12 | AQ21: 法术值 | AR21: =IFERROR(VLOOKUP($AR$11,$BE$2:$BO$22,11,FALSE),0) -> 0 | AS21: 5环 | AT21: =IFERROR(VLOOKUP($AZ$12,$BP$2:$BU$22,6,FALSE),0) -> 0 | AU21: 5环 | AV21: =IFERROR(VLOOKUP($AZ$17,$CA$2:$CF$22,6,FALSE),0) -> 0 | AW21: 4环 | AX21: =IFERROR(VLOOKUP($AX$17,$BV$2:$BZ$22,5,FALSE),0) -> 0 | AZ21: =IFERROR(VLOOKUP(AY21,$BA$2:$BC$4,3,0),0) -> 1 | BE21: 19 | BF21: 4 | BG21: 3 | BH21: 3 | BI21: 3 | BJ21: 3 | BK21: 2 | BL21: 1 | BM21: 1 | BN21: 1 | BO21: 123 | BP21: 19 | BU21: 4 | BV21: 19 | BZ21: 2 | CA21: 19 | CF21: 6 | CN21: =IFERROR(IF(CN20+1>CS2,IF(CN20+1>CS2,IF(CR3+CR20>CS3,"",CR3+CR20)),CN20+1),"") -> 16 | CO21: {=IFERROR(INDEX($B$34:$BO$262,CN21,$CP$2),"")} | CP21: {=IFERROR(INDEX($B$34:$BO$262,CN21,$CQ$2),"")} | CQ21: {=IF(IFERROR(INDEX($B$34:$BO$262,CN21,$CO$2),"")=0,"",IFERROR(INDEX($B$34:$BO$262,CN21,$CO$2),""))} | CR21: =IFERROR(IF(CN20+1>CS2,CR20+1,0),"") -> 0 | CT21: =IFERROR(IF(OR(CO25="",COUNTIF($CW$2:$CW$81,CO25)),"",CO25),"") | CU21: {=INDEX(CT:CT,SMALL(IF($CT$2:$CT$101<>"",ROW($CT$2:$CT$101),142),ROW(CT20)))&""} | CV21: =IFERROR(VLOOKUP(CW21,$CO$6:$CQ$105,3,FALSE),"") | CW21: =IF(主要!AX30="","",主要!AX30) | CX21: =IFERROR(VLOOKUP(CW21,$CO$6:$CQ$105,2,FALSE),"")
A22: 20 | B22: ="" | AA22: {=IFERROR(INDEX($B$1:$B$22,SMALL(IF($B$1:$B$22<>"",ROW($B$1:$B$22),4^8),ROW(22:22)))&"","")} | AC22: =IFERROR(IF(VLOOKUP(AB2,$B$3:$Z$22,23,FALSE)=0,"",VLOOKUP(AB2,$B$3:$Z$22,23,FALSE)),"") | AD22: {=IFERROR(INDEX($AC$1:$AC$24,SMALL(IF($AC$1:$AC$24<>"",ROW($AC$1:$AC$24),4^8),ROW(AC21)))&"","")} | AF22: =IFERROR(IF(VLOOKUP(AE2,$B$3:$Z$22,23,FALSE)=0,"",VLOOKUP(AE2,$B$3:$Z$22,23,FALSE)),"") | AG22: {=IFERROR(INDEX($AF$1:$AF$24,SMALL(IF($AF$1:$AF$24<>"",ROW($AF$1:$AF$24),4^8),ROW(21:21)))&"","")} | AI22: =IFERROR(IF(VLOOKUP(AH2,$B$3:$Z$22,23,FALSE)=0,"",VLOOKUP(AH2,$B$3:$Z$22,23,FALSE)),"") | AJ22: {=IFERROR(INDEX($AI$1:$AI$24,SMALL(IF($AI$1:$AI$24<>"",ROW($AI$1:$AI$24),4^8),ROW(21:21)))&"","")} | AL22: =IFERROR(IF(VLOOKUP(AK2,$B$3:$Z$22,23,FALSE)=0,"",VLOOKUP(AK2,$B$3:$Z$22,23,FALSE)),"") | AM22: {=IFERROR(INDEX($AL$1:$AL$24,SMALL(IF($AL$1:$AL$24<>"",ROW($AL$1:$AL$24),4^8),ROW(21:21)))&"","")} | BE22: 20 | BF22: 4 | BG22: 3 | BH22: 3 | BI22: 3 | BJ22: 3 | BK22: 2 | BL22: 2 | BM22: 1 | BN22: 1 | BO22: 133 | BP22: 20 | BQ22: ="" | BR22: ="" | BS22: ="" | BT22: ="" | BU22: 4 | BV22: 20 | BW22: ="" | BX22: ="" | BY22: ="" | BZ22: 2 | CA22: 20 | CB22: ="" | CC22: ="" | CD22: ="" | CE22: ="" | CF22: 6 | CN22: =IFERROR(IF(CN21+1>CS2,IF(CN21+1>CS2,IF(CR3+CR21>CS3,"",CR3+CR21)),CN21+1),"") -> 17 | CO22: {=IFERROR(INDEX($B$34:$BO$262,CN22,$CP$2),"")} | CP22: {=IFERROR(INDEX($B$34:$BO$262,CN22,$CQ$2),"")} | CQ22: {=IF(IFERROR(INDEX($B$34:$BO$262,CN22,$CO$2),"")=0,"",IFERROR(INDEX($B$34:$BO$262,CN22,$CO$2),""))} | CR22: =IFERROR(IF(CN21+1>CS2,CR21+1,0),"") -> 0 | CT22: =IFERROR(IF(OR(CO26="",COUNTIF($CW$2:$CW$81,CO26)),"",CO26),"") | CU22: {=INDEX(CT:CT,SMALL(IF($CT$2:$CT$101<>"",ROW($CT$2:$CT$101),142),ROW(CT21)))&""} | CV22: =IFERROR(VLOOKUP(CW22,$CO$6:$CQ$105,3,FALSE),"") | CW22: =IF(主要!AX31="","",主要!AX31) | CX22: =IFERROR(VLOOKUP(CW22,$CO$6:$CQ$105,2,FALSE),"")
AC23: =IFERROR(IF(VLOOKUP(AB2,$B$3:$Z$22,24,FALSE)=0,"",VLOOKUP(AB2,$B$3:$Z$22,24,FALSE)),"") | AD23: {=IFERROR(INDEX($AC$1:$AC$24,SMALL(IF($AC$1:$AC$24<>"",ROW($AC$1:$AC$24),4^8),ROW(AC22)))&"","")} | AF23: =IFERROR(IF(VLOOKUP(AE2,$B$3:$Z$22,24,FALSE)=0,"",VLOOKUP(AE2,$B$3:$Z$22,24,FALSE)),"") | AG23: {=IFERROR(INDEX($AF$1:$AF$24,SMALL(IF($AF$1:$AF$24<>"",ROW($AF$1:$AF$24),4^8),ROW(22:22)))&"","")} | AI23: =IFERROR(IF(VLOOKUP(AH2,$B$3:$Z$22,24,FALSE)=0,"",VLOOKUP(AH2,$B$3:$Z$22,24,FALSE)),"") | AJ23: {=IFERROR(INDEX($AI$1:$AI$24,SMALL(IF($AI$1:$AI$24<>"",ROW($AI$1:$AI$24),4^8),ROW(22:22)))&"","")} | AL23: =IFERROR(IF(VLOOKUP(AK2,$B$3:$Z$22,24,FALSE)=0,"",VLOOKUP(AK2,$B$3:$Z$22,24,FALSE)),"") | AM23: {=IFERROR(INDEX($AL$1:$AL$24,SMALL(IF($AL$1:$AL$24<>"",ROW($AL$1:$AL$24),4^8),ROW(22:22)))&"","")} | BQ23: 魔契师 | BW23: 渎魂圣约 | CB23: 药剂师 | CN23: =IFERROR(IF(CN22+1>CS2,IF(CN22+1>CS2,IF(CR3+CR22>CS3,"",CR3+CR22)),CN22+1),"") -> 18 | CO23: {=IFERROR(INDEX($B$34:$BO$262,CN23,$CP$2),"")} | CP23: {=IFERROR(INDEX($B$34:$BO$262,CN23,$CQ$2),"")} | CQ23: {=IF(IFERROR(INDEX($B$34:$BO$262,CN23,$CO$2),"")=0,"",IFERROR(INDEX($B$34:$BO$262,CN23,$CO$2),""))} | CR23: =IFERROR(IF(CN22+1>CS2,CR22+1,0),"") -> 0 | CT23: =IFERROR(IF(OR(CO27="",COUNTIF($CW$2:$CW$81,CO27)),"",CO27),"") | CU23: {=INDEX(CT:CT,SMALL(IF($CT$2:$CT$101<>"",ROW($CT$2:$CT$101),142),ROW(CT22)))&""} | CV23: =IFERROR(VLOOKUP(CW23,$CO$6:$CQ$105,3,FALSE),"") | CW23: =IF(主要!AX32="","",主要!AX32) | CX23: =IFERROR(VLOOKUP(CW23,$CO$6:$CQ$105,2,FALSE),"")
AC24: =IFERROR(IF(VLOOKUP(AB2,$B$3:$Z$22,25,FALSE)=0,"",VLOOKUP(AB2,$B$3:$Z$22,25,FALSE)),"") | AD24: {=IFERROR(INDEX($AC$1:$AC$24,SMALL(IF($AC$1:$AC$24<>"",ROW($AC$1:$AC$24),4^8),ROW(AC23)))&"","")} | AF24: =IFERROR(IF(VLOOKUP(AE2,$B$3:$Z$22,25,FALSE)=0,"",VLOOKUP(AE2,$B$3:$Z$22,25,FALSE)),"") | AG24: {=IFERROR(INDEX($AF$1:$AF$24,SMALL(IF($AF$1:$AF$24<>"",ROW($AF$1:$AF$24),4^8),ROW(23:23)))&"","")} | AI24: =IFERROR(IF(VLOOKUP(AH2,$B$3:$Z$22,25,FALSE)=0,"",VLOOKUP(AH2,$B$3:$Z$22,25,FALSE)),"") | AJ24: {=IFERROR(INDEX($AI$1:$AI$24,SMALL(IF($AI$1:$AI$24<>"",ROW($AI$1:$AI$24),4^8),ROW(23:23)))&"","")} | AL24: =IFERROR(IF(VLOOKUP(AK2,$B$3:$Z$22,25,FALSE)=0,"",VLOOKUP(AK2,$B$3:$Z$22,25,FALSE)),"") | AM24: {=IFERROR(INDEX($AL$1:$AL$24,SMALL(IF($AL$1:$AL$24<>"",ROW($AL$1:$AL$24),4^8),ROW(23:23)))&"","")} | CN24: =IFERROR(IF(CN23+1>CS2,IF(CN23+1>CS2,IF(CR3+CR23>CS3,"",CR3+CR23)),CN23+1),"") -> 19 | CO24: {=IFERROR(INDEX($B$34:$BO$262,CN24,$CP$2),"")} | CP24: {=IFERROR(INDEX($B$34:$BO$262,CN24,$CQ$2),"")} | CQ24: {=IF(IFERROR(INDEX($B$34:$BO$262,CN24,$CO$2),"")=0,"",IFERROR(INDEX($B$34:$BO$262,CN24,$CO$2),""))} | CR24: =IFERROR(IF(CN23+1>CS2,CR23+1,0),"") -> 0 | CT24: =IFERROR(IF(OR(CO28="",COUNTIF($CW$2:$CW$81,CO28)),"",CO28),"") | CU24: {=INDEX(CT:CT,SMALL(IF($CT$2:$CT$101<>"",ROW($CT$2:$CT$101),142),ROW(CT23)))&""} | CV24: =IFERROR(VLOOKUP(CW24,$CO$6:$CQ$105,3,FALSE),"") | CW24: =IF(主要!AX33="","",主要!AX33) | CX24: =IFERROR(VLOOKUP(CW24,$CO$6:$CQ$105,2,FALSE),"")
CN25: =IFERROR(IF(CN24+1>CS2,IF(CN24+1>CS2,IF(CR3+CR24>CS3,"",CR3+CR24)),CN24+1),"") -> 20 | CO25: {=IFERROR(INDEX($B$34:$BO$262,CN25,$CP$2),"")} | CP25: {=IFERROR(INDEX($B$34:$BO$262,CN25,$CQ$2),"")} | CQ25: {=IF(IFERROR(INDEX($B$34:$BO$262,CN25,$CO$2),"")=0,"",IFERROR(INDEX($B$34:$BO$262,CN25,$CO$2),""))} | CR25: =IFERROR(IF(CN24+1>CS2,CR24+1,0),"") -> 0 | CT25: =IFERROR(IF(OR(CO29="",COUNTIF($CW$2:$CW$81,CO29)),"",CO29),"") | CU25: {=INDEX(CT:CT,SMALL(IF($CT$2:$CT$101<>"",ROW($CT$2:$CT$101),142),ROW(CT24)))&""} | CV25: =IFERROR(VLOOKUP(CW25,$CO$6:$CQ$105,3,FALSE),"") | CW25: =IF(主要!AX34="","",主要!AX34) | CX25: =IFERROR(VLOOKUP(CW25,$CO$6:$CQ$105,2,FALSE),"")
CN26: =IFERROR(IF(CN25+1>CS2,IF(CN25+1>CS2,IF(CR3+CR25>CS3,"",CR3+CR25)),CN25+1),"") -> 21 | CO26: {=IFERROR(INDEX($B$34:$BO$262,CN26,$CP$2),"")} | CP26: {=IFERROR(INDEX($B$34:$BO$262,CN26,$CQ$2),"")} | CQ26: {=IF(IFERROR(INDEX($B$34:$BO$262,CN26,$CO$2),"")=0,"",IFERROR(INDEX($B$34:$BO$262,CN26,$CO$2),""))} | CR26: =IFERROR(IF(CN25+1>CS2,CR25+1,0),"") -> 0 | CT26: =IFERROR(IF(OR(CO30="",COUNTIF($CW$2:$CW$81,CO30)),"",CO30),"") | CU26: {=INDEX(CT:CT,SMALL(IF($CT$2:$CT$101<>"",ROW($CT$2:$CT$101),142),ROW(CT25)))&""} | CV26: =IFERROR(VLOOKUP(CW26,$CO$6:$CQ$105,3,FALSE),"") | CW26: =IF(主要!AX35="","",主要!AX35) | CX26: =IFERROR(VLOOKUP(CW26,$CO$6:$CQ$105,2,FALSE),"")
CN27: =IFERROR(IF(CN26+1>CS2,IF(CN26+1>CS2,IF(CR3+CR26>CS3,"",CR3+CR26)),CN26+1),"") -> 22 | CO27: {=IFERROR(INDEX($B$34:$BO$262,CN27,$CP$2),"")} | CP27: {=IFERROR(INDEX($B$34:$BO$262,CN27,$CQ$2),"")} | CQ27: {=IF(IFERROR(INDEX($B$34:$BO$262,CN27,$CO$2),"")=0,"",IFERROR(INDEX($B$34:$BO$262,CN27,$CO$2),""))} | CR27: =IFERROR(IF(CN26+1>CS2,CR26+1,0),"") -> 0 | CT27: =IFERROR(IF(OR(CO31="",COUNTIF($CW$2:$CW$81,CO31)),"",CO31),"") | CU27: {=INDEX(CT:CT,SMALL(IF($CT$2:$CT$101<>"",ROW($CT$2:$CT$101),142),ROW(CT26)))&""} | CV27: =IFERROR(VLOOKUP(CW27,$CO$6:$CQ$105,3,FALSE),"") | CW27: =IF(主要!AX36="","",主要!AX36) | CX27: =IFERROR(VLOOKUP(CW27,$CO$6:$CQ$105,2,FALSE),"")
CN28: =IFERROR(IF(CN27+1>CS2,IF(CN27+1>CS2,IF(CR3+CR27>CS3,"",CR3+CR27)),CN27+1),"") -> 23 | CO28: {=IFERROR(INDEX($B$34:$BO$262,CN28,$CP$2),"")} | CP28: {=IFERROR(INDEX($B$34:$BO$262,CN28,$CQ$2),"")} | CQ28: {=IF(IFERROR(INDEX($B$34:$BO$262,CN28,$CO$2),"")=0,"",IFERROR(INDEX($B$34:$BO$262,CN28,$CO$2),""))} | CR28: =IFERROR(IF(CN27+1>CS2,CR27+1,0),"") -> 0 | CT28: =IFERROR(IF(OR(CO32="",COUNTIF($CW$2:$CW$81,CO32)),"",CO32),"") | CU28: {=INDEX(CT:CT,SMALL(IF($CT$2:$CT$101<>"",ROW($CT$2:$CT$101),142),ROW(CT27)))&""} | CV28: =IFERROR(VLOOKUP(CW28,$CO$6:$CQ$105,3,FALSE),"") | CW28: =IF(主要!AX37="","",主要!AX37) | CX28: =IFERROR(VLOOKUP(CW28,$CO$6:$CQ$105,2,FALSE),"")
CN29: =IFERROR(IF(CN28+1>CS2,IF(CN28+1>CS2,IF(CR3+CR28>CS3,"",CR3+CR28)),CN28+1),"") -> 24 | CO29: {=IFERROR(INDEX($B$34:$BO$262,CN29,$CP$2),"")} | CP29: {=IFERROR(INDEX($B$34:$BO$262,CN29,$CQ$2),"")} | CQ29: {=IF(IFERROR(INDEX($B$34:$BO$262,CN29,$CO$2),"")=0,"",IFERROR(INDEX($B$34:$BO$262,CN29,$CO$2),""))} | CR29: =IFERROR(IF(CN28+1>CS2,CR28+1,0),"") -> 0 | CT29: =IFERROR(IF(OR(CO33="",COUNTIF($CW$2:$CW$81,CO33)),"",CO33),"") | CU29: {=INDEX(CT:CT,SMALL(IF($CT$2:$CT$101<>"",ROW($CT$2:$CT$101),142),ROW(CT28)))&""} | CV29: =IFERROR(VLOOKUP(CW29,$CO$6:$CQ$105,3,FALSE),"") | CW29: =IF(主要!AX38="","",主要!AX38) | CX29: =IFERROR(VLOOKUP(CW29,$CO$6:$CQ$105,2,FALSE),"")
CH30: 狂战士道途 | CI30: 27 | CJ30: {=_xlfn.IFS($AZ$2>=14,30,$AZ$2>=10,29,$AZ$2>=6,28,$AZ$2>=3,27,1,0)} -> 0 | CN30: =IFERROR(IF(CN29+1>CS2,IF(CN29+1>CS2,IF(CR3+CR29>CS3,"",CR3+CR29)),CN29+1),"") -> 25 | CO30: {=IFERROR(INDEX($B$34:$BO$262,CN30,$CP$2),"")} | CP30: {=IFERROR(INDEX($B$34:$BO$262,CN30,$CQ$2),"")} | CQ30: {=IF(IFERROR(INDEX($B$34:$BO$262,CN30,$CO$2),"")=0,"",IFERROR(INDEX($B$34:$BO$262,CN30,$CO$2),""))} | CR30: =IFERROR(IF(CN29+1>CS2,CR29+1,0),"") -> 0 | CT30: =IFERROR(IF(OR(CO34="",COUNTIF($CW$2:$CW$81,CO34)),"",CO34),"") | CU30: {=INDEX(CT:CT,SMALL(IF($CT$2:$CT$101<>"",ROW($CT$2:$CT$101),142),ROW(CT29)))&""} | CV30: =IFERROR(VLOOKUP(CW30,$CO$6:$CQ$105,3,FALSE),"") | CW30: =IF(主要!AX39="","",主要!AX39) | CX30: =IFERROR(VLOOKUP(CW30,$CO$6:$CQ$105,2,FALSE),"")
CH31: 兽心道途 | CI31: 31 | CJ31: {=_xlfn.IFS($AZ$2>=14,35,$AZ$2>=10,34,$AZ$2>=6,33,$AZ$2>=3,32,1,0)} -> 0 | CN31: =IFERROR(IF(CN30+1>CS2,IF(CN30+1>CS2,IF(CR3+CR30>CS3,"",CR3+CR30)),CN30+1),"") -> 26 | CO31: {=IFERROR(INDEX($B$34:$BO$262,CN31,$CP$2),"")} | CP31: {=IFERROR(INDEX($B$34:$BO$262,CN31,$CQ$2),"")} | CQ31: {=IF(IFERROR(INDEX($B$34:$BO$262,CN31,$CO$2),"")=0,"",IFERROR(INDEX($B$34:$BO$262,CN31,$CO$2),""))} | CR31: =IFERROR(IF(CN30+1>CS2,CR30+1,0),"") -> 0 | CT31: =IFERROR(IF(OR(CO35="",COUNTIF($CW$2:$CW$81,CO35)),"",CO35),"") | CU31: {=INDEX(CT:CT,SMALL(IF($CT$2:$CT$101<>"",ROW($CT$2:$CT$101),142),ROW(CT30)))&""} | CV31: =IFERROR(VLOOKUP(CW31,$CO$6:$CQ$105,3,FALSE),"") | CW31: =IF(主要!AX40="","",主要!AX40) | CX31: =IFERROR(VLOOKUP(CW31,$CO$6:$CQ$105,2,FALSE),"")
B32: 1 | C32: 2 | D32: 3 | E32: 4 | F32: 5 | G32: 6 | H32: 7 | I32: 8 | J32: 9 | K32: 10 | L32: 11 | M32: 12 | N32: 13 | O32: 14 | P32: 15 | Q32: 16 | R32: 17 | S32: 18 | T32: 19 | U32: 20 | V32: 21 | W32: 22 | X32: 23 | Y32: 24 | Z32: 25 | AA32: 26 | AB32: 27 | AC32: 28 | AD32: 29 | AE32: 30 | AF32: 31 | AG32: 32 | AH32: 33 | AI32: 34 | AJ32: 35 | AK32: 36 | AL32: 37 | AM32: 38 | AN32: 39 | AO32: 40 | AP32: 41 | AQ32: 42 | AR32: 43 | AS32: 44 | AT32: 45 | AU32: 46 | AV32: 47 | AW32: 48 | AX32: 49 | AY32: 50 | AZ32: 51 | BA32: 52 | BB32: 53 | BC32: 54 | BD32: 55 | BE32: 56 | BF32: 57 | BG32: 58 | BH32: 59 | BI32: 60 | BJ32: 61 | BK32: 62 | BL32: 63 | BM32: 64 | BN32: 65 | BO32: 66 | CH32: 世界树道途 | CI32: 36 | CJ32: {=_xlfn.IFS($AZ$2>=14,39,$AZ$2>=10,38,$AZ$2>=6,37,$AZ$2>=3,36,1,0)} -> 0 | CN32: =IFERROR(IF(CN31+1>CS2,IF(CN31+1>CS2,IF(CR3+CR31>CS3,"",CR3+CR31)),CN31+1),"") -> 27 | CO32: {=IFERROR(INDEX($B$34:$BO$262,CN32,$CP$2),"")} | CP32: {=IFERROR(INDEX($B$34:$BO$262,CN32,$CQ$2),"")} | CQ32: {=IF(IFERROR(INDEX($B$34:$BO$262,CN32,$CO$2),"")=0,"",IFERROR(INDEX($B$34:$BO$262,CN32,$CO$2),""))} | CR32: =IFERROR(IF(CN31+1>CS2,CR31+1,0),"") -> 0 | CT32: =IFERROR(IF(OR(CO36="",COUNTIF($CW$2:$CW$81,CO36)),"",CO36),"") | CU32: {=INDEX(CT:CT,SMALL(IF($CT$2:$CT$101<>"",ROW($CT$2:$CT$101),142),ROW(CT31)))&""} | CV32: =IFERROR(VLOOKUP(CW32,$CO$6:$CQ$105,3,FALSE),"") | CW32: =IF(主要!AX41="","",主要!AX41) | CX32: =IFERROR(VLOOKUP(CW32,$CO$6:$CQ$105,2,FALSE),"")
B33: 野蛮人 | E33: 吟游诗人 | H33: 牧师 | K33: 德鲁伊 | N33: 战士 | Q33: 武僧 | T33: 圣武士 | W33: 游侠 | Z33: 游荡者 | AC33: 术士 | AF33: 魔契师 | AI33: 法师 | AL33: 奇械师 | AO33: 灵能使 | AR33: 血猎手 | AU33: 药剂师 | AX33: 铳士 | BA33: 邪狱使 | BD33: 拳斗士 | CH33: 狂热者道途 | CI33: 40 | CJ33: {=_xlfn.IFS($AZ$2>=14,44,$AZ$2>=10,43,$AZ$2>=6,42,$AZ$2>=3,41,1,0)} -> 0 | CN33: =IFERROR(IF(CN32+1>CS2,IF(CN32+1>CS2,IF(CR3+CR32>CS3,"",CR3+CR32)),CN32+1),"") -> 28 | CO33: {=IFERROR(INDEX($B$34:$BO$262,CN33,$CP$2),"")} | CP33: {=IFERROR(INDEX($B$34:$BO$262,CN33,$CQ$2),"")} | CQ33: {=IF(IFERROR(INDEX($B$34:$BO$262,CN33,$CO$2),"")=0,"",IFERROR(INDEX($B$34:$BO$262,CN33,$CO$2),""))} | CR33: =IFERROR(IF(CN32+1>CS2,CR32+1,0),"") -> 0 | CT33: =IFERROR(IF(OR(CO37="",COUNTIF($CW$2:$CW$81,CO37)),"",CO37),"") | CU33: {=INDEX(CT:CT,SMALL(IF($CT$2:$CT$101<>"",ROW($CT$2:$CT$101),142),ROW(CT32)))&""} | CV33: =IFERROR(VLOOKUP(CW33,$CO$6:$CQ$105,3,FALSE),"") | CW33: =IF(主要!AX42="","",主要!AX42) | CX33: =IFERROR(VLOOKUP(CW33,$CO$6:$CQ$105,2,FALSE),"")
A34: 1 | C34: 豁免熟练 | D34: 力量与体质 | F34: 豁免熟练 | G34: 敏捷与魅力 | I34: 豁免熟练 | J34: 感知与魅力 | L34: 豁免熟练 | M34: 智力与感知 | O34: 豁免熟练 | P34: 力量与体质 | R34: 豁免熟练 | S34: 力量与敏捷 | U34: 豁免熟练 | V34: 感知与魅力 | X34: 豁免熟练 | Y34: 力量与敏捷 | AA34: 豁免熟练 | AB34: 敏捷与智力 | AD34: 豁免熟练 | AE34: 体质与魅力 | AG34: 豁免熟练 | AH34: 感知与魅力 | AJ34: 豁免熟练 | AK34: 智力与感知 | AM34: 豁免熟练 | AN34: 体质与智力 | AP34: 豁免熟练 | AQ34: 智力与感知 | AS34: 豁免熟练 | AT34: 敏捷与智力 | AV34: 豁免熟练 | AW34: 智力与感知 | AY34: 豁免熟练 | AZ34: 敏捷与魅力 | BB34: 豁免熟练 | BC34: 体质与魅力 | BE34: 豁免熟练 | BF34: 力量与体质 | BH34: 豁免熟练 | BK34: 豁免熟练 | BN34: 豁免熟练 | CH34: 先祖守卫道途 | CI34: 45 | CJ34: {=_xlfn.IFS($AZ$2>=14,48,$AZ$2>=10,47,$AZ$2>=6,46,$AZ$2>=3,45,1,0)} -> 0 | CN34: =IFERROR(IF(CN33+1>CS2,IF(CN33+1>CS2,IF(CR3+CR33>CS3,"",CR3+CR33)),CN33+1),"") -> 29 | CO34: {=IFERROR(INDEX($B$34:$BO$262,CN34,$CP$2),"")} | CP34: {=IFERROR(INDEX($B$34:$BO$262,CN34,$CQ$2),"")} | CQ34: {=IF(IFERROR(INDEX($B$34:$BO$262,CN34,$CO$2),"")=0,"",IFERROR(INDEX($B$34:$BO$262,CN34,$CO$2),""))} | CR34: =IFERROR(IF(CN33+1>CS2,CR33+1,0),"") -> 0 | CT34: =IFERROR(IF(OR(CO38="",COUNTIF($CW$2:$CW$81,CO38)),"",CO38),"") | CU34: {=INDEX(CT:CT,SMALL(IF($CT$2:$CT$101<>"",ROW($CT$2:$CT$101),142),ROW(CT33)))&""} | CV34: =IFERROR(VLOOKUP(CW34,$CO$6:$CQ$105,3,FALSE),"") | CW34: =IF(主要!AX43="","",主要!AX43) | CX34: =IFERROR(VLOOKUP(CW34,$CO$6:$CQ$105,2,FALSE),"")
A35: 2 | C35: 技能熟练 | D35: 选择2项：驯兽、运动、威吓、自然、察觉或求生 | F35: 技能熟练 | G35: 任选3项 | I35: 技能熟练 | J35: 选择2项：历史，洞悉，医药，说服或宗教 | L35: 技能熟练 | M35: 选择2项：奥秘、驯兽、洞悉、医疗、自然、察觉、宗教或求生 | O35: 技能熟练 | P35: 选择2项：特技、驯兽、运动、历史、洞悉、威吓、游说、察觉或求生 | R35: 技能熟练 | S35: 选择2项：特技、运动、历史、洞悉、宗教或隐匿 | U35: 技能熟练 | V35: 选择2项：运动、洞悉、威吓、医疗、说服或宗教 | X35: 技能熟练 | Y35: 选择3项：驯兽、运动、洞悉，调查，自然、察觉、隐匿或求生 | AA35: 技能熟练 | AB35: 选择4项：特技、运动、欺瞒、洞悉、恐吓、调查、察觉、说服、巧手或隐匿 | AD35: 技能熟练 | AE35: 选择2项：奥秘、欺瞒、洞悉、威吓、游说或宗教 | AG35: 技能熟练 | AH35: 选择2项：奥秘、欺瞒、历史、威吓、调查、自然或宗教 | AJ35: 技能熟练 | AK35: 选择2项：奥秘、历史、洞悉、调查、医疗、自然或宗教 | AM35: 技能熟练 | AN35: 选择2项：奥秘、历史、调查、医药、自然、察觉或巧手。 | AP35: 技能熟练 | AQ35: 选择2项：奥秘、洞悉、威吓、调查、医药、察觉或游说 | AS35: 技能熟练 | AT35: 选择3项：特技、奥秘、运动、历史、洞悉、调查、宗教或生存 | AV35: 技能熟练 | AW35: 选择2项：奥秘、历史、调查、医药、自然或宗教。 | AY35: 技能熟练 | AZ35: 选择2项：特技、驯兽、运动、欺瞒、洞悉、威吓、察觉、游说、巧手和隐匿 | BB35: 技能熟练 | BC35: 选择2项：奥秘、运动、欺瞒、洞悉、威吓、调查、游说、宗教、隐匿 | BE35: 技能熟练 | BF35: 选择2项：特技、运动、欺瞒、威吓、察觉、巧手或隐匿 | BH35: 技能熟练 | BK35: 技能熟练 | BN35: 技能熟练 | CH35: 风暴先驱道途 | CI35: 49 | CJ35: {=_xlfn.IFS($AZ$2>=14,52,$AZ$2>=10,51,$AZ$2>=6,50,$AZ$2>=3,49,1,0)} -> 0 | CN35: =IFERROR(IF(CN34+1>CS2,IF(CN34+1>CS2,IF(CR3+CR34>CS3,"",CR3+CR34)),CN34+1),"") -> 30 | CO35: {=IFERROR(INDEX($B$34:$BO$262,CN35,$CP$2),"")} | CP35: {=IFERROR(INDEX($B$34:$BO$262,CN35,$CQ$2),"")} | CQ35: {=IF(IFERROR(INDEX($B$34:$BO$262,CN35,$CO$2),"")=0,"",IFERROR(INDEX($B$34:$BO$262,CN35,$CO$2),""))} | CR35: =IFERROR(IF(CN34+1>CS2,CR34+1,0),"") -> 0 | CT35: =IFERROR(IF(OR(CO39="",COUNTIF($CW$2:$CW$81,CO39)),"",CO39),"") | CU35: {=INDEX(CT:CT,SMALL(IF($CT$2:$CT$101<>"",ROW($CT$2:$CT$101),142),ROW(CT34)))&""} | CV35: =IFERROR(VLOOKUP(CW35,$CO$6:$CQ$105,3,FALSE),"") | CW35: =IF(主要!AX44="","",主要!AX44) | CX35: =IFERROR(VLOOKUP(CW35,$CO$6:$CQ$105,2,FALSE),"")
A36: 3 | C36: 武器熟练 | D36: 简易和军用武器 | F36: 武器熟练 | G36: 简易武器 | I36: 武器熟练 | J36: 简易武器 | L36: 武器熟练 | M36: 简易武器 | O36: 武器熟练 | P36: 简易和军用武器 | R36: 武器熟练 | S36: 简易与具备轻型词条的军用武器 | U36: 武器熟练 | V36: 简易和军用武器 | X36: 武器熟练 | Y36: 简易和军用武器 | AA36: 武器熟练 | AB36: 简易武器和具有灵巧或轻型词条的军用武器 | AD36: 武器熟练 | AE36: 简易武器 | AG36: 武器熟练 | AH36: 简易武器 | AJ36: 武器熟练 | AK36: 简易武器 | AM36: 武器熟练 | AN36: 简易武器 | AP36: 武器熟练 | AQ36: 简易武器 | AS36: 武器熟练 | AT36: 简易和军用武器 | AV36: 武器熟练 | AW36: 简易武器、短剑、手弩 | AY36: 武器熟练 | AZ36: 简易武器和军用远程武器 | BB36: 武器熟练 | BC36: 简易和军用武器 | BE36: 武器熟练 | BF36: 简易和临时武器 | BH36: 武器熟练 | BK36: 武器熟练 | BN36: 武器熟练 | CH36: 狂野魔法道途 | CI36: 53 | CJ36: {=_xlfn.IFS($AZ$2>=14,57,$AZ$2>=10,56,$AZ$2>=6,55,$AZ$2>=3,54,1,0)} -> 0 | CN36: =IFERROR(IF(CN35+1>CS2,IF(CN35+1>CS2,IF(CR3+CR35>CS3,"",CR3+CR35)),CN35+1),"") -> 31 | CO36: {=IFERROR(INDEX($B$34:$BO$262,CN36,$CP$2),"")} | CP36: {=IFERROR(INDEX($B$34:$BO$262,CN36,$CQ$2),"")} | CQ36: {=IF(IFERROR(INDEX($B$34:$BO$262,CN36,$CO$2),"")=0,"",IFERROR(INDEX($B$34:$BO$262,CN36,$CO$2),""))} | CR36: =IFERROR(IF(CN35+1>CS2,CR35+1,0),"") -> 0 | CT36: =IFERROR(IF(OR(CO40="",COUNTIF($CW$2:$CW$81,CO40)),"",CO40),"") | CU36: {=INDEX(CT:CT,SMALL(IF($CT$2:$CT$101<>"",ROW($CT$2:$CT$101),142),ROW(CT35)))&""} | CV36: =IFERROR(VLOOKUP(CW36,$CO$6:$CQ$105,3,FALSE),"") | CW36: =IF(主要!AX45="","",主要!AX45) | CX36: =IFERROR(VLOOKUP(CW36,$CO$6:$CQ$105,2,FALSE),"")
A37: 4 | C37: 工具熟练 | D37: 无 | F37: 工具熟练 | G37: 任选3项乐器 | I37: 工具熟练 | J37: 无 | L37: 工具熟练 | M37: 草药工具 | O37: 工具熟练 | P37: 无 | R37: 工具熟练 | S37: 选择1种工匠工具或乐器 | U37: 工具熟练 | V37: 无 | X37: 工具熟练 | Y37: 无 | AA37: 工具熟练 | AB37: 盗贼工具 | AD37: 工具熟练 | AE37: 无 | AG37: 工具熟练 | AH37: 无 | AJ37: 工具熟练 | AK37: 无 | AM37: 工具熟练 | AN37: 盗贼工具，修补工具，以及一种你选择的工匠工具 | AP37: 工具熟练 | AQ37: 无 | AS37: 工具熟练 | AT37: 炼金工具 | AV37: 工具熟练 | AW37: 任何一种工具熟练，再加上从以下工具中选择的一种：制毒工具，草药工具或炼金工具。 | AY37: 工具熟练 | AZ37: 无 | BB37: 工具熟练 | BC37: 无 | BE37: 工具熟练 | BF37: 任选1项赌具 | BH37: 工具熟练 | BK37: 工具熟练 | BN37: 工具熟练 | CH37: 野兽道途 | CI37: 58 | CJ37: {=_xlfn.IFS($AZ$2>=14,62,$AZ$2>=10,61,$AZ$2>=6,60,$AZ$2>=3,59,1,0)} -> 0 | CN37: =IFERROR(IF(CN36+1>CS2,IF(CN36+1>CS2,IF(CR3+CR36>CS3,"",CR3+CR36)),CN36+1),"") -> 32 | CO37: {=IFERROR(INDEX($B$34:$BO$262,CN37,$CP$2),"")} | CP37: {=IFERROR(INDEX($B$34:$BO$262,CN37,$CQ$2),"")} | CQ37: {=IF(IFERROR(INDEX($B$34:$BO$262,CN37,$CO$2),"")=0,"",IFERROR(INDEX($B$34:$BO$262,CN37,$CO$2),""))} | CR37: =IFERROR(IF(CN36+1>CS2,CR36+1,0),"") -> 0 | CT37: =IFERROR(IF(OR(CO41="",COUNTIF($CW$2:$CW$81,CO41)),"",CO41),"") | CU37: {=INDEX(CT:CT,SMALL(IF($CT$2:$CT$101<>"",ROW($CT$2:$CT$101),142),ROW(CT36)))&""} | CV37: =IFERROR(VLOOKUP(CW37,$CO$6:$CQ$105,3,FALSE),"") | CW37: =IF(主要!AX46="","",主要!AX46) | CX37: =IFERROR(VLOOKUP(CW37,$CO$6:$CQ$105,2,FALSE),"")
A38: 5 | C38: 护甲受训 | D38: 轻甲、中甲和盾牌 | F38: 护甲受训 | G38: 轻甲 | I38: 护甲受训 | J38: 轻甲、中甲和盾牌 | L38: 护甲受训 | M38: 轻甲和盾牌 | O38: 护甲受训 | P38: 轻甲、中甲、重甲和盾牌 | R38: 护甲受训 | S38: 无 | U38: 护甲受训 | V38: 轻甲、中甲、重甲和盾牌 | X38: 护甲受训 | Y38: 轻甲、中甲和盾牌 | AA38: 护甲受训 | AB38: 轻甲 | AD38: 护甲受训 | AE38: 无 | AG38: 护甲受训 | AH38: 轻甲 | AJ38: 护甲受训 | AK38: 无 | AM38: 护甲受训 | AN38: 轻甲，中甲和盾牌 | AP38: 护甲受训 | AQ38: 无 | AS38: 护甲受训 | AT38: 轻甲，中甲和盾牌 | AV38: 护甲受训 | AW38: 轻甲、中甲 | AY38: 护甲受训 | AZ38: 轻甲 | BB38: 护甲受训 | BC38: 轻甲、中甲和盾牌 | BE38: 护甲受训 | BF38: 轻甲 | BH38: 护甲受训 | BK38: 护甲受训 | BN38: 护甲受训 | CH38: 巨人道途 | CI38: 63 | CJ38: {=_xlfn.IFS($AZ$2>=14,67,$AZ$2>=10,66,$AZ$2>=6,65,$AZ$2>=3,64,1,0)} -> 0 | CN38: =IFERROR(IF(CN37+1>CS2,IF(CN37+1>CS2,IF(CR3+CR37>CS3,"",CR3+CR37)),CN37+1),"") -> 33 | CO38: {=IFERROR(INDEX($B$34:$BO$262,CN38,$CP$2),"")} | CP38: {=IFERROR(INDEX($B$34:$BO$262,CN38,$CQ$2),"")} | CQ38: {=IF(IFERROR(INDEX($B$34:$BO$262,CN38,$CO$2),"")=0,"",IFERROR(INDEX($B$34:$BO$262,CN38,$CO$2),""))} | CR38: =IFERROR(IF(CN37+1>CS2,CR37+1,0),"") -> 0 | CT38: =IFERROR(IF(OR(CO42="",COUNTIF($CW$2:$CW$81,CO42)),"",CO42),"") | CU38: {=INDEX(CT:CT,SMALL(IF($CT$2:$CT$101<>"",ROW($CT$2:$CT$101),142),ROW(CT37)))&""} | CV38: =IFERROR(VLOOKUP(CW38,$CO$6:$CQ$105,3,FALSE),"") | CW38: =IF(主要!AX47="","",主要!AX47) | CX38: =IFERROR(VLOOKUP(CW38,$CO$6:$CQ$105,2,FALSE),"")
A39: 6 | C39: 起始装备 | D39: 选择A或B：(A) 巨斧，4把手斧，探索套组以及15GP；或者(B) 75GP | F39: 起始装备 | G39: 选择A或B：(A) 皮甲，2把匕首，你选择的乐器，艺人套组 以及19GP；或者(B) 90GP | I39: 起始装备 | J39: 选择A或B：(A) 链甲衫，盾牌，硬头锤，圣徽，祭司套组 以及7GP；或(B) 110GP | L39: 起始装备 | M39: 选择A或B：(A) 皮甲，盾牌，镰刀，德鲁伊法器（长棍），探索套组，草药工具以及9GP；或者(B) 50GP | O39: 起始装备 | P39: 选择A、B或C：(A)链甲，巨剑，链枷，8杆标枪，地城套组以及4GP；或者(B) 镶钉皮甲，弯刀，短剑，长弓，20支箭矢，箭袋，地城套组 以及11GP；或者(C) 155GP | R39: 起始装备 | S39: 起始装备Starting Equipment 选择A或B：(A)矛，5把匕首，你在工具熟练中所选择的工匠工具或乐器，探索套组以及11GP；或者(B) 50GP | U39: 起始装备 | V39: 选择A或B：(A) 链甲，盾牌，长剑，6根标枪，圣徽，祭司套组以及9GP；或者(B) 150GP | X39: 起始装备 | Y39: 选择A或B：(A) 镶钉皮甲、弯刀、短剑、长弓、20支箭、箭袋、德鲁伊法器（槲寄生枝条）、探索套组以及7GP；或者(B) 150GP | AA39: 起始装备 | AB39: 选择A或B：(A)皮甲，2把匕首，短剑，短弓，20支箭矢，箭袋，盗贼工具，窃贼套组以及8GP；或者(B) 100GP | AD39: 起始装备 | AE39: 选择A或B：(A)矛，2把匕首，奥术法器（水晶），地城套组以及28 GP；或者(B) 50GP | AG39: 起始装备 | AH39: 选择A或B：(A) 皮甲，镰刀， 2把匕首 ，奥术法器（法球），书（隐秘学识），学者套组 以及15GP；或者(B) 100GP | AJ39: 起始装备 | AK39: 选择A或B：(A) 2把匕首，奥术法器（长棍），长袍，法术书，学者套组 以及5GP；或(B) 55GP | AM39: 起始装备 | AN39: 选择A或B：（A）镶钉皮甲，匕首，盗贼工具，修补工具，地城套组，和16GP；或（B）150gp | AP39: 起始装备 | AQ39: 选择A或B：（A）短矛、2把匕首，轻弩，20支弩矢，卷轴匣、地城套组与6GP；或（B）50GP | AS39: 起始装备 | AT39: 你带着以下装备开始游戏。此外，你还可以从背景中获得额外的装备。 (a) 一件军用武器 或 (b) 两件简易武器 一把轻弩和 20 发弩矢 (a) 一件镶钉皮甲 或 (b) 一件鳞甲 一套探索套装和炼金工具 你也可以选择放弃上述装备，以4d4×10GP开始游戏。 | AV39: 起始装备 | AW39: 你带着以下装备开始游戏，此外该角色还可以从其背景项中获得额外的起始装备： • 一把轻弩和20支弩矢，（b）一把短剑，或任意一把简易武器 • （a）一个材料包或（b）一件奥术法器 • （a）一个学者套组或（b）一个地城套组 • 兽皮甲、任意简易武器和两把匕首 • 一件医疗包 | AY39: 起始装备 | AZ39: 选择A或B：(A) 皮甲，4把匕首，左轮枪、50发子弹、探索套组以及11GP；或者(B) 175GP | BB39: 起始装备 | BC39: 你携带以下装备（以及你背景提供的物品）开始游戏： (a) 2把军用武器或(b) 1把军用武器加1面盾牌 (a) 链甲衫或(b) 皮甲、长弓外加20支箭矢 (a) 祭司套组或 (b) 地城套组 5把标枪 你也可以选择放弃上述装备，以5d4×10GP开始游戏。 | BE39: 起始装备 | BF39: 选择A或B：(A) 短棒，手斧，赌具（与上述工具熟练的种类相同），地城套组以及31GP；或者(B) 50GP | BH39: 起始装备 | BK39: 起始装备 | BN39: 起始装备 | CH39: 蔑法道途 | CI39: 68 | CJ39: {=_xlfn.IFS($AZ$2>=14,73,$AZ$2>=10,72,$AZ$2>=6,71,$AZ$2>=3,70,1,0)} -> 0 | CN39: =IFERROR(IF(CN38+1>CS2,IF(CN38+1>CS2,IF(CR3+CR38>CS3,"",CR3+CR38)),CN38+1),"") -> 34 | CO39: {=IFERROR(INDEX($B$34:$BO$262,CN39,$CP$2),"")} | CP39: {=IFERROR(INDEX($B$34:$BO$262,CN39,$CQ$2),"")} | CQ39: {=IF(IFERROR(INDEX($B$34:$BO$262,CN39,$CO$2),"")=0,"",IFERROR(INDEX($B$34:$BO$262,CN39,$CO$2),""))} | CR39: =IFERROR(IF(CN38+1>CS2,CR38+1,0),"") -> 0 | CT39: =IFERROR(IF(OR(CO43="",COUNTIF($CW$2:$CW$81,CO43)),"",CO43),"") | CU39: {=INDEX(CT:CT,SMALL(IF($CT$2:$CT$101<>"",ROW($CT$2:$CT$101),142),ROW(CT38)))&""} | CV39: =IFERROR(VLOOKUP(CW39,$CO$6:$CQ$105,3,FALSE),"") | CW39: =IF(主要!AX48="","",主要!AX48) | CX39: =IFERROR(VLOOKUP(CW39,$CO$6:$CQ$105,2,FALSE),"")
A40: 7 | B40: 1 | C40: 狂暴 | D40: 你可以将名为狂暴的原初之力赋予己身，为你带来超越常规的伟力和韧性。未着装重甲时，你能够以一个附赠动作进入狂暴。 你可以进入狂暴的次数见野蛮人特性表中狂暴一栏。当你完成一次短休时，你重获一次已消耗的使用次数；当你完成一次长休时，你重获所有已消耗的使用次数。 狂暴激活期间，你将遵循以下这些规则： 伤害抗性Damage Resistance。你具有钝击、穿刺、挥砍伤害的抗性。 狂暴伤害Rage Damage。当你使用力量发动一次攻击（无论这是一次武器攻击还是一次徒手打击）并对目标造成伤害时，你的伤害掷骰获得额外加值，这个加值随着你的野蛮人等级提升，见野蛮人特性表中狂暴伤害一栏。 力量优势Strength Advantage。你的力量检定和力量豁免检定具有优势。 无法专注或施法No Concentration or Spells。你无法保持专注，也不能施展法术。 持续时间Duration。狂暴持续至你的下个回合结束，如果你穿戴重甲或陷入失能状态，狂暴提前结束。如果在你的下一回合狂暴仍处于激活状态，你可以通过以下的任一方式令狂暴延长一轮： 对一名敌人进行一次攻击检定。 迫使一名敌人进行一次豁免检定。 以一个附赠动作延长你的狂暴。 每当狂暴被延长，都会持续至你的下个回合结束。你至多可以维持狂暴10分钟。 | E40: 1 | F40: 吟游诗人激励 | G40: 你可以用语言，音乐或舞蹈的形式对他人进行超自然的激励。这种激励的表现形式为数颗D6骰，这些骰子被称为诗人激励骰。 使用诗人激励Using Bardic Inspriration。 以一个附赠动作，你可以激励位于你60尺内的另一名能听见或看见你的生物。那名生物获得一枚你的诗人激励骰。一个生物同一时间只能拥有一枚诗人激励骰。在接下来的1小时内，当那名生物在一次D20检定中失败时，那名生物可以投掷诗人激励骰并将掷骰结果附加到该次d20中，这可能将失败变为成功。诗人激励骰将在投掷时已消耗。 使用次数Number of Uses。 你可以授予诗人激励骰的次数等于你的魅力调整值（最少1次），当你完成长休时，你重获所有已消耗的使用次数。 更高等级At Higher Levels。你的诗人激励骰会在你到达特定吟游诗人等级时改变，如吟游诗人特性表中的诗人骰所示。你的诗人骰会在5级时变为d8，在10级时变为d10，在15级时变为d12。 | H40: 1 | I40: 施法 | J40: 你通过祈祷，冥想与奉献习得如何施法。施法规则见第七章。下文将详述如何将这些规则应用于牧师法术，牧师法术详见本章后文职业描述中的牧师法术列表。 | K40: 1 | L40: 施法 | M40: 你通过研究自然的神秘伟力学会了如何施展法术。施法规则见第七章。下文将详述如何将这些规则应用于德鲁伊法术，德鲁伊法术详见本章后文职业描述中的德鲁伊法术列表。 | N40: 1 | O40: 战斗风格 | P40: 你不断磨练你的武艺。你获得一项你选择的战斗风格专长（见第五章）。推荐选择防御。 每当你获得战士等级时，你可以将其改为另一个战斗风格专长。 | Q40: 1 | R40: 武艺 | S40: 你的武艺修行让你将徒手打击与武僧武器的使用方式烂熟于心。武僧武器包括： 简易近战武器 拥有轻型词条的军用近战武器 未着装任何护甲也没持用盾牌时，如果你徒手或只持用武僧武器，则你获得下列增益： 附赠徒手打击Bonus Unarmed Strike。你可以用附赠动作发动一次徒手打击。 武艺骰Martial Arts Die。你使用徒手打击或武僧武器进行攻击时，可以选择用1d6骰代替原本的伤害骰。该骰子将随武僧职业等级的提升而增大，具体数据见武僧特性表中的武艺骰一列。 敏捷攻击Dexterous Attacks。你使用徒手打击或武僧武器进行攻击时，可以用敏捷代替力量进行攻击检定和伤害掷骰。此外，当你使用徒手打击的擒抱或推撞选项时，你也可以使用你的敏捷代替力量决定豁免DC。 | T40: 1 | U40: 圣疗 | V40: 你的触碰溢满祝福，可以医治伤口。你获得一个治疗能量池，其内的治疗能量在每次完成长休后自动补满。治疗能量池储备的可恢复生命值总值等于你的圣武士职业等级×5。 你能够以一个附赠动作触碰一个生物（可以是你自己），并抽取治疗能量池中的能量恢复该生物的生命值，其恢复量最多等于你治疗能量池中剩余的治疗量。 此外，你也可以使用5点治疗量来移除目标身上的中毒状态，而非恢复生命值。 | W40: 1 | X40: 施法 | Y40: 你学会运用自然世界的魔法本源进行施法。施法规则见第七章。下文将详述如何将这些规则应用于游侠法术，游侠法术详见本章后文职业描述中的游侠法术表。 | Z40: 1 | AA40: 专精 | AB40: 你获得两项由你选择的你已熟练的技能的专精。 如果你有这两项技能的熟练的话，推荐选择巧手和隐匿。 当你的游荡者等级为6级时，你额外再获得两项由你选择的你已熟练的技能的专精。 | AC40: 1 | AD40: 施法 | AE40: 你从你的天生魔法汲取魔力用于施展法术。参见第7章有关施法的规则。下述信息将详述如何将这些规则应用于术士法术，术士法术详见本章后文职业描述中的术士法表。 | AF40: 1 | AG40: 魔能祈唤 | AH40: 你在神秘学识的研习过程中发掘出了使用魔能祈唤的方式，这些禁忌的知识残章让你获得了持久的魔法能力。你获得一个自选的魔能祈唤，如书之魔契Pact of the Tome（详见后文“魔能祈唤选项“）。 先决Prerequisites。如果一个魔能祈唤具有先决，那你必须满足它才能选取。例如，若一个魔能祈唤需要你具有魔契师等级5+，你在魔契师到达5级时才可以选择该祈唤。 替换与获取魔能祈唤Replacing and Gaining Invocation。每当你获得一级魔契师等级时，你都可以用新的祈唤替换一个已学会的祈唤，但你必须满足其先决条件。如果某个祈唤是另一个祈唤的先决条件，那你无法替换它。 当你到达特定的魔契师等级时，你还可以习得更多的魔能祈唤，具体数据见魔契师特性表中“祈唤”一栏。 你不能多次重复选择同一个魔能祈唤，除非该祈唤的描述另有说明。 | AI40: 1 | AJ40: 施法 | AK40: 你已经入门了奥术魔法，学会了如何施展法术。施法规则见第七章。下文将详述如何将这些规则应用于法师法术，法师法术详见本章后文职业描述中的法师法术表。 | AL40: 1 | AM40: 工艺魔法 | AN40: 你习得戏法修复术Mending。 你可以在持握修补工具时以一个魔法动作，在你自身5尺内一个未占据空间创造一件物品，从下表中选择这件物品： 滚珠 扁瓶 小包 篮子 爪钩 绳索 铺盖 捕猎陷阱 麻袋 铃铛 壶 铲子 毯子 油灯 铁钉 滑轮组 镣铐 细线 玻璃瓶 捕网 火绒盒 吊桶 燃油 火把 铁蒺藜 纸张 小瓶 蜡烛 羊皮纸 撬棍 长杆 对应物品的规则见《玩家手册》。该特性创造的物品将在你完成一次长休时消失。 你可以使用此特性的次数等于你的智力调整值(最少一次)，你会在完成一次长休后恢复所有已使用的次数。 | AO40: 1 | AP40: 施法 | AQ40: 你学会了如何使用心灵之力引导魔法力量。施法规则见玩家手册，下文将详述如何将这些规则应用于灵能使法术，灵能使法术详见本章后文职业描述中的灵能使法术列表。 | AR40: 1 | AS40: 猎人之苦 | AT40: 你从猎人之苦之中生还——那是一个危险而漫长的仪式，它扭曲你的生命之血，使你与黑暗永远为伴，且磨砺你的感官以对抗它们。你在追踪妖精、邪魔或亡灵的感知（求生）检定，以及获知它们的信息的智力检定中具有优势。 猎人之苦也使你的身体能够以你自己的血液与生命精华作为燃料，来操控并塑造鲜血降咒之魔法。你的部分特性要求你的目标进行豁免检定以对抗该特性的效果。豁免 DC 的计算式为：鲜血秘法豁免 DC = 8 + 你的熟练加值 + 你的智力调整值 | AU40: 1 | AV40: 药剂师施法 | AW40: 你的奥术研究使你能熟练地施展魔法。关于施法规则请查阅核心规则，关于药剂师法术列表请参阅本书中的法术清单。 | AX40: 1 | AY40: 战斗风格 | AZ40: 你获得一项你选择的战斗风格专长。若你选择了一项要求你单手或双手持握近战武器的专长（如巨武器战斗），你可以在持握远程武器时使用该专长。 每当你获得铳士等级时，你可以将其改为另一个战斗风格专长。 | BA40: 1 | BB40: 极恶禁令 | BC40: 你获得以九狱之力责难生物的能力。每个你的回合一次，你可以将一个魔法缄印施加在一名位于你30尺内的生物身上。你可以在以一次武器攻击命中目标时施加缄印（无需动作），或是以一个附赠动作将缄印施加给距离内的可见目标。缄印存在1分钟或在你焚灭缄印（见下方“焚灭缄印”）时提前消失。一名具有至少一枚缄印的生物被称为受禁生物。你施加的缄印对其他生物而言处于隐形，在你眼中，缄印是一枚在你可见的受禁生物身上闪烁的荧光符文。_x000D_ 每次休息前，你只能施加有限的缄印，在你完成短休或长休时，你重获所有缄印。当你获得邪狱使等级时，你可以施加的缄印数量也随之提升，见邪狱使职业特性表缄印一栏。_x000D_ 如果一名受禁生物死亡，在你的回合中，你能够以一个附赠动作将其身上所有的缄印施加给一名位于其30尺内的可见生物。缄印的持续时间并不会因生物的死亡或缄印的转移而停止流逝。 | BD40: 1 | BE40: 拳斗 | BF40: 你在黑街和酒馆年复一年的战斗让你精通使用徒手打击和拳斗武器的战斗风格，拳斗武器包括：_x000D_ _x000D_ 简易近战武器_x000D_ 临时武器_x000D_ 若你未持械或是仅使用拳斗武器，且你未着甲或仅着装轻甲并且没有持用盾牌，你获得以下增益：_x000D_ 附赠徒手打击Bonus Unarmed Strike。你能以附赠动作发动一次徒手打击。_x000D_ 拳斗骰Fisticuffs Die。你使用徒手打击或拳斗武器进行攻击时，可以选择用1d8骰代替原本的伤害。该骰子将随拳斗士职业等级的提升而增大，具体数据见拳斗士特性表中的拳斗骰一列。_x000D_ 临时能弑Improved Improvisation。你有着将万物化作武器的天赋，这让你能运用临时武器的精通词条。所有临时武器对你而言具有削弱精通词条。 | CH40: 古神道途 | CI40: 74 | CJ40: {=_xlfn.IFS($AZ$2>=14,79,$AZ$2>=10,78,$AZ$2>=6,77,$AZ$2>=3,75,1,0)} -> 0 | CN40: =IFERROR(IF(CN39+1>CS2,IF(CN39+1>CS2,IF(CR3+CR39>CS3,"",CR3+CR39)),CN39+1),"") -> 35 | CO40: {=IFERROR(INDEX($B$34:$BO$262,CN40,$CP$2),"")} | CP40: {=IFERROR(INDEX($B$34:$BO$262,CN40,$CQ$2),"")} | CQ40: {=IF(IFERROR(INDEX($B$34:$BO$262,CN40,$CO$2),"")=0,"",IFERROR(INDEX($B$34:$BO$262,CN40,$CO$2),""))} | CR40: =IFERROR(IF(CN39+1>CS2,CR39+1,0),"") -> 0 | CT40: =IFERROR(IF(OR(CO44="",COUNTIF($CW$2:$CW$81,CO44)),"",CO44),"") | CU40: {=INDEX(CT:CT,SMALL(IF($CT$2:$CT$101<>"",ROW($CT$2:$CT$101),142),ROW(CT39)))&""} | CV40: =IFERROR(VLOOKUP(CW40,$CO$6:$CQ$105,3,FALSE),"") | CW40: =IF(主要!AX49="","",主要!AX49) | CX40: =IFERROR(VLOOKUP(CW40,$CO$6:$CQ$105,2,FALSE),"")
A41: 8 | B41: 1 | C41: 无甲防御 | D41: 你未着装任何护甲期间，你的基础护甲等级等于10+你的敏捷调整值+你的体质调整值。你可以使用盾牌并仍从此特性获益。 | E41: 1 | F41: 施法 | G41: 你从吟游艺术中学会了如何施展法术。施法规则见第七章。下文将详述如何将这些规则应用于吟游诗人法术，吟游诗人法术详见本章后文职业描述中的吟游诗人法术列表。 | I41: 戏法 | J41: 你已知三道你选择的牧师戏法。推荐选择神导术Guidance，圣火术Sacred Flame和奇术Thaumaturgy。 每当你获得一个牧师等级时，你都能从你的戏法中选择其一替换为另一道你所选择的牧师戏法。 当你的牧师等级到达4级和10级时，你都能另选一道牧师戏法并习得，如牧师特性表中戏法一列所示。 | L41: 戏法 | M41: 你已知两道你选择的德鲁伊戏法。推荐选择德鲁伊伎俩Druidcraft和燃火术Produce Flame。 你都能从此特性的戏法中选择其一替换为另一道你所选择的德鲁伊戏法。 当你的德鲁伊等级到达4级和10级时，你都能另选一道德鲁伊戏法并习得，如德鲁伊特性表中戏法一列所示。 | N41: 1 | O41: 回气 | P41: 你可以利用有限的精力与体力来重整旗鼓。以一个附赠动作，你可以用此法恢复生命值，其总值为1d10＋你的战士职业等级。 你可以使用此特性两次，并且在完成短休后恢复一次已消耗的使用次数，完成长休后恢复所有已消耗的使用次数。 当你到达特定战士等级时，你获得这项特性的额外使用次数，已列在战士特性表的回气一列。 | Q41: 1 | R41: 无甲防御 | S41: 未着装任何护甲也没持用盾牌时，你的AC值等于10＋你的敏捷调整值＋你的感知调整值。 | T41: 1 | U41: 施法 | V41: 你已经学会了如何通过祈祷与冥想来施展法术。施法规则见第七章。下文将详述如何将这些规则应用于圣武士法术，圣武士法术详见本章后文职业描述中的圣武士法术列表。 | X41: 法术位 | Y41: 游侠特性表显示了你可用于施展一环及以上法术的法术位数量。当你完成长休时，你重获所有已消耗的法术位。 | Z41: 1 | AA41: 偷袭 | AB41: 你知道如何利用敌人的分心并发动致命的精巧打击。每个回合一次，当你的攻击检定命中了一个生物时，你可以造成1d6的额外伤害。这次攻击必须使用一把灵巧或远程武器并具有优势。额外伤害的伤害类型与该武器的伤害类型一致。 除此之外，若你的目标周围5尺内有你的盟友，并且该盟友没有陷入失能状态，你的攻击检定也没有劣势的话，则你不需要优势也造成额外伤害。 你的额外伤害会随着你的游荡者等级提高而增长，具体如游荡者特性表中的偷袭一列所示。 | AD41: 戏法 | AE41: 你已知4个你选择的术士戏法。推荐选择光亮术Light、魔法伎俩Prestidigitation、电爪Shocking Grasp和术法爆发Sorcerous Burst。每当你获得一个术士等级时，你都能将通过此特性已知的其中一个戏法替换为另一个你所选择的术士戏法。 当你的术士等级达到4级和10级时，你都能另选一道术士戏法并习得，如术士特性表中戏法一列所示。 | AG41: 幽影护甲 | AH41: 你可以随意以自身为目标施展法师护甲Mage Armor 且无需消耗法术位。 | AJ41: 戏法 | AK41: 已知三道你选择的法师戏法。推荐选择光亮术Light、法师之手Mage Hand 和冷冻射线Ray of Frost 。 每当你完成一次长休时，你都能从此特性的戏法中选择其一替换为另一道你所选择的法师戏法。 当你的法师等级到达4级和10级时，你都能另选一道法师戏法并习得，如法师特性表中戏法一列所示。 | AL41: 1 | AM41: 施法 | AN41: 你已经了解到如何通过物品引导魔法能量。参见《玩家手册》有关施法的规则。下述信息将详述如何将这些规则应用于奇械师法术，奇械师法术详见后文职业描述中的奇械师法术表。 | AP41: 戏法 | AQ41: 你知晓两道你选择的灵能使戏法。推荐选择次级幻象Minor Illusion与念力飞掷Telekinetic Fling 。每当你获得一级灵能使等级，你都可以用另一道灵能使法表中的灵能使戏法替换你通过该特性得到的戏法。当你达到10级、14级灵能使等级时，你分别学会一道新的你选择的灵能使戏法，见灵能使法表中的戏法部分。 | AR41: 1 | AS41: 鲜血恶戾 | AT41: 你得到引导、甚至是牺牲你的活力精华来以鲜血秘法诅咒和操控生物的能力。你学会一种你所选的血咒（在后文中详细描述）。在你第 6、第 10、第 14 及第 18 级时，你学会一种新的血咒，且你可以选择一个已知血咒替换为另一个。 当你使用鲜血恶戾时，你选择要使用哪种血咒。在血咒影响目标前，你可以通过失去一个鲜血秘法骰的生命值来增幅你的血咒。一个增幅的血咒会得到额外效果，具体参照诅咒的描述。体内没有血液的生物对未增幅的血咒免疫。 你能够使用此特性 1 次。从第 6 级开始，你可以使用此特性 2 次，第 13 级时增为 3 次，第 17 级时增为 4 次。完成一次短休或长休后，你将重获所有消耗掉的鲜血恶戾次数。 | AV41: 戏法 | AW41: 你从药剂师法术列表中选择三个戏法并掌握之。你可以在更高等级学会更多你所选的戏法，如药剂师职业表中已知戏法所展示的那样。 | AX41: 1 | AY41: 快速拔枪 | AZ41: 你善于在他人反应前就拔枪射击，你获得以下增益： 先攻Initiative。你的先攻检定具有优势。 双重拔枪Double Draw。拔出或入鞘武器时，你可以同时拔出或入鞘两把不具有双手词条的武器，而非通常情况下的一把。 | BB41: 焚灭缄印 | BC41: 当一名你可见的受禁生物受到任意来源的伤害时（邪狱使令缄印焚灭的伤害除外），你可以立即焚灭其身上任意数量的由你施加的缄印，每焚灭一枚缄印，便对其造成1d6火焰或暗蚀伤害（由你选择）。焚灭缄印在该生物受到触发伤害之后立即造成伤害。焚灭缄印无需任何动作，但你无法在陷入失能期间如此做。缄印一经焚灭立即消失。_x000D_ 当你在本职业上到达5级时，你与你的大魔鬼之间的联系将变得更加紧密。每枚缄印焚灭时将额外造成1d6伤害（共2d6）。该伤害在你到达下列等级时再次提升1d6：11级（共3d6），20级（共4d6）。见邪狱使职业特性表缄印伤害一栏。 | BD41: 1 | BE41: 钢颚铁护 | BF41: 若你未着甲或仅着装轻甲且未持用盾牌，你的基础护甲等级等于12+你的体质调整值。 | CH41: 污霭狂怒者道途 | CI41: 80 | CJ41: {=_xlfn.IFS($AZ$2>=14,86,$AZ$2>=10,84,$AZ$2>=6,83,$AZ$2>=3,81,1,0)} -> 0 | CN41: =IFERROR(IF(CN40+1>CS2,IF(CN40+1>CS2,IF(CR3+CR40>CS3,"",CR3+CR40)),CN40+1),"") -> 36 | CO41: {=IFERROR(INDEX($B$34:$BO$262,CN41,$CP$2),"")} | CP41: {=IFERROR(INDEX($B$34:$BO$262,CN41,$CQ$2),"")} | CQ41: {=IF(IFERROR(INDEX($B$34:$BO$262,CN41,$CO$2),"")=0,"",IFERROR(INDEX($B$34:$BO$262,CN41,$CO$2),""))} | CR41: =IFERROR(IF(CN40+1>CS2,CR40+1,0),"") -> 0 | CT41: =IFERROR(IF(OR(CO45="",COUNTIF($CW$2:$CW$81,CO45)),"",CO45),"") | CU41: {=INDEX(CT:CT,SMALL(IF($CT$2:$CT$101<>"",ROW($CT$2:$CT$101),142),ROW(CT40)))&""} | CV41: =IFERROR(VLOOKUP(CW41,$CO$6:$CQ$105,3,FALSE),"") | CW41: =IF(主要!AX50="","",主要!AX50) | CX41: =IFERROR(VLOOKUP(CW41,$CO$6:$CQ$105,2,FALSE),"")
A42: 9 | B42: 1 | C42: 武器精通 | D42: 你对武器的训练使你能够运用两种自选的简易或军用近战武器的精通属性，例如巨斧和手斧。每当你完成一次长休时，你可以重新演练武器技巧，来改变你所选择的其中一个武器类型。 当你获得特定的野蛮人等级时，你还可以使用更多种类武器的精通属性，详见野蛮人特性表中武器精通一栏。 | F42: 戏法 | G42: 你已知两道你选择的吟游诗人戏法。推荐选择舞光术Dancing Light和恶言相加Vicious Mockery。 | I42: 法术位 | J42: 牧师特性表显示了你可用于施展一环及以上法术的法术位数量。当你完成长休时，你重获所有已消耗的法术位。 | L42: 法术位 | M42: 德鲁伊特性表显示了你可用于施展一环及以上法术的法术位数量。当你完成长休时，你重获所有已消耗的法术位。 | N42: 1 | O42: 武器精通 | P42: 你对武器的训练使你能够自选并使用3种已熟练武器的精通词条。每当你完成一次长休时，你都可以练习武器技艺并改变你所选择的其中一种武器类型。 当你到达特定战士等级时，你可以使用更多种类武器的精通词条，已列在战士特性表的武器精通一列。 | Q42: 2 | R42: 武僧武功 | S42: 通过运转玄功和习练武艺，你便得以掌握自身非凡的内在能量。功力点代表着你所能使用的这份能量。你的武僧等级决定了你拥有多少功力点，具体数据见武僧特性表中的功力点一列。你可以消耗功力点来增强或启动特定的武僧特性。你一开始掌握三种特性：疾风连击，坚强防御，疾步如风。细节见下。 每当你消耗1点功力时，直到你完成一次短休或者长休前其将暂时不可以再被使用。在完成休息时，你将回复所有已消耗的功力点。 你的某些特性会要求你的目标进行豁免以对抗该特性的效果，这些特性的豁免DC为8+你的感知调整值+你的熟练加值。 疾风连击Flurry of Blows。你可以消耗1点功力，以一个附赠动作发动两次徒手打击。 坚强防御Patient Defense。你能以一个附赠动作执行撤离动作。此外，你可以消耗1点功力，以一个附赠动作同时执行撤离与回避动作。 疾步如风Step of the Wind。你能以一个附赠动作执行疾走动作。此外，你可以消耗1点功力，以一个附赠动作同时执行撤离与疾走 动作，同时使你该回合内的跳跃距离翻倍。 | U42: 法术位 | V42: 圣武士特性表显示了你可用于施展一环及以上法术的法术位数量。当你完成长休时，你重获所有已消耗的法术位。 | X42: 准备法术 | Y42: 你准备可供你以此特性施展的一环及更高环阶的法术列表。最初，选择两道游侠法术。推荐选择捕获打击Ensnaring Strike和疗伤术Cure Wounds。 已准备法术数量会随你游侠等级的提升而增加，如游侠特性表中的准备法术一列所示。每当这一列的数字增加时，从游侠法术列表中选择额外法术准备，直至已准备法术的数量与表格中的数字一致。你所选择法术的环阶必须是你所拥有法术位对应的环阶。例如，如果你是一名5级游侠，则你的准备法术列表能包括六道一环或二环的游侠法术，随意组合。 如果游侠的其他特性给了你始终准备了的法术，这些法术不计入你以此法准备的法术数量，但这些法术对你而言都视为游侠法术。 | Z42: 1 | AA42: 盗贼黑话 | AB42: 你在施展自己游荡者才华的社区里学习了多样的语言。你习得盗贼黑话和第二章的语言表中的一项语言。 | AD42: 法术位 | AE42: 术士特性表显示了你可用于施展一环及以上法术的法术位数量。当你完成长休时，你重获所有已消耗的法术位。 | AG42: 魔能意志 | AH42: 你为保持专注所进行的体质豁免具有优势。 | AJ42: 法术书 | AK42: 你在法师学徒阶段获取的所有成果汇集于一本独特的书：你的法术书。它是一个重3磅的微型物件，内有100页，并且只能被你自己或者施展了鉴定术Identify的人阅读。你来决定法术书的外貌和材料，比如一本镶金边的典籍或用麻绳装订的牛皮纸集。 这本书包含所有你已知的一环及以上的法术。最初，它记录着六道法师法术。推荐选择侦测魔法Detect Magic、羽落术Feather Fall、法师护甲Mage Armor、魔法飞弹Magic Missile、睡眠术Sleep和雷鸣波Thunderwave。 1级之后每当你获得一个法师等级时，你就可以往法术书中添加两道你选择的法师法术。你所选择法术的环阶必须是你所拥有法术位对应的环阶，你所拥有的法术位如法师特性表中所示。这些法术是你定期进行奥术研究的成果。 | AM42: 必备工具 | AN42: 你通过工具来施展你的奇械师法术。你可以使用盗贼工具，修补工具，或其他你具有熟练的工匠工具作为你的施法法器，且当你施展一个奇械师法术时必须持握着其中一件法器（意味着当你施法时，法术具有“材料M”成分）。 | AP42: 法术位 | AQ42: 灵能使特性表显示了你可用于施展一环及以上法术的法术位数量。当你完成长休时，你重获所有已消耗的法术位。 | AS42: 焦虑血咒 | AT42: 以一个附赠动作，你破坏距离你 30 尺以内一生物的身体或思想，使他们更容易受到影响。 在你的下一轮结束之前，对被诅咒生物进行的魅力（恐吓）检定具有优势。 增幅。在此诅咒结束前，目标下次进行的感知豁免具有劣势。 | AV42: 初级重组 | AW42: 当你完成一次长休并查阅了你的公式书时，你可以将一个你已知的药剂师戏法和药剂师法术列表中的另一个戏法替换。 | AX42: 1 | AY42: 武器精通 | AZ42: 你对武器的训练使你能够运用两种自选的简易或军用远程武器的精通词条。每当你完成一次长休时，你可以重新演练武器技巧，来改变你所选择的其中一个武器类型。 当你到达特定的铳士等级时，你还可以使用更多种类武器的精通词条，详见铳士特性表中武器精通一栏。 | BB42: 禁令豁免 | BC42: 你后续获得的职业特性将为你的极恶禁令带来额外效应，并要求目标以进行豁免检定抵抗其效果。那些效应的豁免DC使用你的禁令豁免DC，其计算方式如下：禁令豁免DC=8+你的魅力调整值+你的熟练加值 | BD42: 2 | BE42: 锐气 | BF42: 你战胜逆境的经历让你在战斗时充满勇气，这种自信表现为你的锐气。你的拳斗士等级决定了你拥有多少点锐气，具体数据见拳斗士特性表中的锐气一列。_x000D_ 你可以消耗锐气来增强或启动特定的拳斗士特性。你一开始掌握三种特性：振奋精神，左右开弓，寓攻于走。细节见下。_x000D_ 每当你消耗1点锐气时，其将暂时不可以再被使用直至你完成一次短休或长休。在完成休息时，你将重获所有已消耗的锐气。_x000D_ 振奋精神Brace up。你能以附赠动作消耗1点锐气来从攻击中为应对攻击打起精神。当你如此做时，投掷你的拳斗骰并获得骰值加你的拳斗士等级加你的体质调整值的临时生命值。该临时生命值将在10分钟后消失（若有剩余）。_x000D_ 左右开弓One-Two Punch。你能消耗1点锐气，以附赠动作发动两次徒手打击。_x000D_ 寓攻于走Stick and Move。你能消耗1点锐气，并使用附赠动作发动一次徒手打击并执行疾行或撤离动作。 | CH42: 巨像道途 | CI42: 87 | CJ42: {=_xlfn.IFS($AZ$2>=14,92,$AZ$2>=10,91,$AZ$2>=6,90,$AZ$2>=3,88,1,0)} -> 0 | CN42: =IFERROR(IF(CN41+1>CS2,IF(CN41+1>CS2,IF(CR3+CR41>CS3,"",CR3+CR41)),CN41+1),"") -> 37 | CO42: {=IFERROR(INDEX($B$34:$BO$262,CN42,$CP$2),"")} | CP42: {=IFERROR(INDEX($B$34:$BO$262,CN42,$CQ$2),"")} | CQ42: {=IF(IFERROR(INDEX($B$34:$BO$262,CN42,$CO$2),"")=0,"",IFERROR(INDEX($B$34:$BO$262,CN42,$CO$2),""))} | CR42: =IFERROR(IF(CN41+1>CS2,CR41+1,0),"") -> 0 | CT42: =IFERROR(IF(OR(CO46="",COUNTIF($CW$2:$CW$81,CO46)),"",CO46),"") | CU42: {=INDEX(CT:CT,SMALL(IF($CT$2:$CT$101<>"",ROW($CT$2:$CT$101),142),ROW(CT41)))&""} | CV42: =IFERROR(VLOOKUP(CW42,$CO$6:$CQ$105,3,FALSE),"") | CW42: =IF(主要!AX51="","",主要!AX51) | CX42: =IFERROR(VLOOKUP(CW42,$CO$6:$CQ$105,2,FALSE),"")
A43: 10 | B43: 2 | C43: 危机感应 | D43: 当非常事态发生时，一种不可思议的感觉降临你的心头，指引你更好的躲避危机。只要你未陷入失能状态，你的敏捷豁免检定就具有优势。 | F43: 法术位 | G43: 吟游诗人特性表显示了你可用于施展一环及以上法术的法术位数量。当你完成长休时，你重获所有已消耗的法术位。 | I43: 准备法术 | J43: 你准备可供你以此特性施展的一环及更高环阶的法术列表。最初，选择四道牧师法术。推荐选择祝福术Bless，疗伤术Cure Wounds，光导箭Guiding Bolt和虔诚护盾Shield of Faith。 已准备法术数量会随你牧师等级的提升而增加，如牧师特性表中的准备法术一列所示。每当这一列的数字增加时，从牧师法术列表中选择额外法术准备，直至已准备法术的数量与表格中的数字一致。你所选择法术的环阶必须是你所拥有法术位对应的环阶。例如，如果你是一名3级牧师，则你的准备法术列表能包括六道一环或二环的牧师法术，随意组合。 如果牧师的其他特性给了你始终准备了的法术，这些法术不计入你以此法准备的法术数量，但这些法术对你而言都视为牧师法术。 | L43: 准备法术 | M43: 你准备可供你以此特性施展的一环及更高环阶的法术列表。最初，选择四道德鲁伊法术。推荐选择化兽为友Animal Friendship、疗伤术Cure Wound、妖火Faerie Fire和雷鸣波Thunderwave。 已准备法术数量会随你德鲁伊等级的提升而增加，如德鲁伊特性表中的准备法术一列所示。每当这一列的数字增加时，从德鲁伊法术列表中选择额外法术准备，直至已准备法术的数量与表格中的数字一致。你所选择法术的环阶必须是你所拥有法术位对应的环阶。例如，如果你是一名3级德鲁伊，则你的准备法术列表能包括六道一环或二环的德鲁伊法术，随意组合。 如果德鲁伊的其他特性给了你始终准备了的法术，这些法术不计入你以此法准备的法术数量，但这些法术对你而言都视为德鲁伊法术。 | N43: 2 | O43: 动作如潮 | P43: 你可以在短期内让自己突破身为凡骨的极限。在你的回合中，你可以执行一个额外的动作，但不能是魔法动作。 你使用此特性后，你必须在完成一次短休或长休后才能再次使用。第17级起，你可以在每次休息之间使用此特性两次，但每回合只能使用一次。 | Q43: 2 | R43: 无甲移动 | S43: 当未着装任何护甲也没持用盾牌时，你的速度提升10尺。该加值将随着武僧职业等级的提升而增加，具体数值见武僧特性表。 | U43: 准备法术 | V43: 你准备可供你以此特性施展的一环及更高环阶的法术列表。最初，选择两道圣武士法术推荐选择英雄气概Heroism和炽焰斩Searing Smite。 已准备法术数量会随你圣武士等级的提升而增加，如圣武士特性表中的准备法术一列所示。每当这一列的数字增加时，法术列表中选择额外法术准备，直至已准备法术的数量与表格中的数字一致。你所选择法术的环阶必须是你所拥有法术位对应的环阶。例如，如果你是一名5级的圣武士，则你的准备法术列表能包括六道一环或二环的牧师法术，随意组合。 如果圣武士的其他特性给了你始终准备了的法术，这些法术不计入你以此法准备的法术数量，但这些法术对你而言都视为圣武士法术。 | X43: 改变你的准备法术 | Y43: 每当你完成一次长休时，你可以将你准备列表上的一道法术替换为其他游侠法术，新替换的法术必须是你拥有法术位的法术。 | Z43: 1 | AA43: 武器精通 | AB43: 你对武器的训练使你能够运用两种自选熟练武器的精通属性，比如选择匕首和短弓。 当你完成一次长休时，你可以改变你所选择的武器类型。比如你可以改为使用弯刀和短剑。 | AD43: 准备法术 | AE43: 你准备可供你以此特性施展的一环及更高环阶的法术列表。最初，选择两道术士法术。推荐选择燃烧之手Burning Hands和侦测魔法Detect Magic 。 已准备法术数量会随你术士等级的提升而增加，如术士特性表中的准备法术一列所示。每当这一列的数字增加时，从术士法术列表中选择额外法术准备，直至已准备法术的数量与表格中的数字一致。你所选择法术的环阶必须是你所拥有法术位对应的环阶。例如，如果你是一位3级术士，则你的准备法术列表能包括六道一环或二环的术士法术，随意组合。 如果术士的其他特性给了你始终准备了的法术，这些法术不计入你以此法准备的法术数量，但这些法术对你而言都视为术士法术。 | AG43: 刃之魔契 | AH43: 以一个附赠动作，你在手中咒唤出一把契约武器——一把与你连结了的简易或军用近战武器——或者与一个你所触摸的魔法武器建立连结。你不能与一把已经被其它生物同调或是和另一魔契师建立连结的魔法武器建立连结。直到连结结束，你拥有其熟练项，且你可以将其用作施法的法器。 当你用你连结的武器发动攻击时，你能使用魅力调整值进行攻击检定和伤害掷骰，取代使用力量或敏捷，且你可以令该武器造成暗蚀、心灵或光耀伤害，来取代原先的伤害类型。 你与武器的连结会在你再次使用此特性的附赠动作时，武器在你5尺外1分钟或更久或是你死亡时结束。一个被咒唤出的武器会在连结结束时消失。 | AJ43: 法术位 | AK43: 法师特性表显示了你可用于施展一环及以上法术的法术位数量。你在完成一次长休时恢复所有已消耗的法术位。 | AM43: 戏法 | AN43: 你习得两个你选择的奇械师戏法。推荐酸液飞溅Acid Splash和魔法伎俩Prestidigitation。 每当你完成一次长休时，你都能将通过此特性得到的其中一个戏法替换为另一个你所选择的奇械师戏法。 当你的奇械师等级达到10级和14级时，你都能习得另一个你所选择的奇械师戏法，如奇械师特性表中戏法一列所示。 | AP43: 一环及以上的准备法术 | AQ43: 你准备可供你以此特性施展的一环及更高环阶的法术列表。最初，选择四道灵能使法术。推荐选择魅惑人类、命令术、不谐低语与法师护甲。已准备法术数量会随你灵能使等级的提升而增加，如灵能使特性表中的准备法术一列所示。每当这一列的数字增加时，从灵能使法术列表中选择额外法术准备，直至已准备法术的数量与表格中的数字一致。你所选择法术的环阶必须是你所拥有法术位对应的环阶。例如，如果你是一位3级灵能使，则你的准备法术列表能包括六道一环或二环的灵能使法术，随意组合。如果灵能使的其他特性给了你始终准备着的法术，这些法术不计入你以此法准备的法术数量，但这些法术对你而言都视为灵能使法术。 | AS43: 捆缚血咒 | AT43: 以一个附赠动作，你试图束缚 30 尺内一个你能看见的、体型至多比你大一级的生物。 目标必须通过一次力量豁免，失败则速度降低为 0，且其无法使用反应，直至你下回合结束。 增幅。此诅咒持续一分钟，且可以影响任何体型的生物。其在自己的每回合结束时可以进行力量豁免。豁免成功时此诅咒结束。 | AV43: 公式书 | AW43: 你有一本书或是一本笔记收藏，用以研习和准备你的药剂师法术，提升你的隐秘理论，并记录你的玄奥实践。你可以使用公式书作为你施展药剂师法术的法器。你可以用任何你喜欢的方式描述你的公式书。你的公式书外型的范例包括： • 一本纸面泛黄，皮面精装的大部头书，绑着一把铁锁。 • 各式各样零零散散的潦草笔记纸，被一根绳子宽松地捆在一起。 • 一本边缘整齐，字迹优美的崭新日记本。 • 一个有两把小金锁头的皮革公文包。 • 一个外侧有外科手术标志的医疗包。 • 一个挂在肩膀上的破旧挎包，每个口袋里都装了小瓶和试管。 如果书损坏或遗失了，你可以在长休中用墨水和纸重新制造它。 | AX43: 2 | AY43: 夺命重弹 | AZ43: 你远程武器的攻击检定在d20中掷出19或20时即可造成重击。 铳士第9级起，你远程武器的攻击检定在d20中掷出18-20时即可造成重击。铳士第17级起，你远程武器的攻击检定在d20中掷出17-20时即可造成重击。 | BA43: 1 | BB43: 叉舌 | BC43: 你可以说、读、写炼狱语，这是你的本能。_x000D_ 此外，你可以说另外两门你选择的语言，但是你无法读或写它们。当你完成长休时，你可以通过大魔鬼赐予的知识替换其中一门语言。当你如此做时，你选择另一门你知道其名字的语言，魔法性的忘记上一门语言并获得新的语言替代其。一旦你以此法替换了一门语言，在你完成一次长休前，你无法再如此做。 （译注：何等废话文学的特性……）_x000D_ 9级起，该特性赋予你另一门语言（即炼狱语外共三门）。不仅如此，你在确定生物意图或诚意的感知（洞悉）检定上具有优势。 | BD43: 2 | BE43: 浴血奋战 | BF43: 当你受到伤害时，你能以反应重获所有已消耗的锐气。若当你执行此反应时你处于浴血，你还会获得等于你拳斗士等级四倍的临时生命值。该临时生命值将在你完成长休时消失（若有剩余）。_x000D_ 此特性一经使用，直至完成短休或长休你都无法再次使用。 | CH43: 肌肉法师道途 | CI43: 93 | CJ43: {=_xlfn.IFS($AZ$2>=14,97,$AZ$2>=10,96,$AZ$2>=6,95,$AZ$2>=3,94,1,0)} -> 0 | CN43: =IFERROR(IF(CN42+1>CS2,IF(CN42+1>CS2,IF(CR3+CR42>CS3,"",CR3+CR42)),CN42+1),"") -> 38 | CO43: {=IFERROR(INDEX($B$34:$BO$262,CN43,$CP$2),"")} | CP43: {=IFERROR(INDEX($B$34:$BO$262,CN43,$CQ$2),"")} | CQ43: {=IF(IFERROR(INDEX($B$34:$BO$262,CN43,$CO$2),"")=0,"",IFERROR(INDEX($B$34:$BO$262,CN43,$CO$2),""))} | CR43: =IFERROR(IF(CN42+1>CS2,CR42+1,0),"") -> 0 | CT43: =IFERROR(IF(OR(CO47="",COUNTIF($CW$2:$CW$81,CO47)),"",CO47),"") | CU43: {=INDEX(CT:CT,SMALL(IF($CT$2:$CT$101<>"",ROW($CT$2:$CT$101),142),ROW(CT42)))&""} | CV43: =IFERROR(VLOOKUP(CW43,$CO$6:$CQ$105,3,FALSE),"") | CW43: =IF(主要!AX52="","",主要!AX52) | CX43: =IFERROR(VLOOKUP(CW43,$CO$6:$CQ$105,2,FALSE),"")
A44: 11 | B44: 2 | C44: 鲁莽攻击 | D44: 你可以抛弃一切对防御的顾虑来发起更加狂乱的攻击。你在你的回合中进行第一次攻击检定时，可以不顾一切地发起攻势。若如此做，直至你的下个回合开始，你使用力量进行的攻击检定具有优势，但在此期间所有以你为目标的攻击检定也具有优势。 | F44: 准备法术 | G44: 你准备可供你以此特性施展的一环及更高环阶的法术列表。最初，选择四道吟游诗人法术。推荐选择魅惑类人Charm person，七彩喷射Color Spray，不谐低语Dissonant Whispers和治愈真言Healing Word。 已准备法术数量会随你吟游诗人等级的提升而增加，如吟游诗人特性表中的准备法术一列所示。每当这一列的数字增加时，从吟游诗人法术列表中选择额外法术准备，直至已准备法术的数量与表格中的数字一致。你所选择法术的环阶必须是你所拥有法术位对应的环阶。例如，如果你是一名3级吟游诗人，则你的准备法术列表能包括六道一环或二环的吟游诗人法术，随意组合。 如果吟游诗人的其他特性给了你始终准备了的法术，这些法术不计入你以此法准备的法术数量，但这些法术对你而言都视为吟游诗人法术。 | I44: 改变你的准备法术 | J44: 每当你完成一次长休时，你可以将你准备列表上的一道或更多法术替换为其他牧师法术，新替换的法术必须是你拥有法术位的法术。 | L44: 改变你的准备法术 | M44: 当你完成一次长休时，你可以将你准备列表上的一道或更多法术替换为其他德鲁伊法术，新替换的法术必须是你拥有法术位的法术。 | N44: 2 | O44: 战术思维 | P44: 在战场内外，你都能够运用你的战术思维。当你在一次属性检定上失败时，你可以消耗一次回气次数让你更接近成功。你掷1d10并将骰值加入到结果之中，而非恢复生命值。这可能会让结果变为成功。如果检定依旧失败，则不会消耗回气次数。 | Q44: 2 | R44: 运转周天 | S44: 当你投掷先攻时，你可以回复所有已消耗的功力点。若你如此做，掷你的武艺骰，并且回复其结果+你的武僧等级的生命值。 使用此特性后，你必须完成一次长休才能再次使用。 | U44: 改变你的准备法术 | V44: 每当你完成一次长休时，你可以将你准备列表上的一道或更多法术替换为其他圣武士法术，新替换的法术必须是你拥有法术位的法术。 | X44: 施法属性 | Y44: 你游侠法术的施法属性是感知。 | Z44: 2 | AA44: 灵巧动作 | AB44: 你精妙的思维与身手使你的行动无比迅速。在你的回合内，你能够以附赠动作执行疾走，撤离或躲藏动作之一。 | AD44: 改变你的准备法术 | AE44: 每当你获得一个术士等级时，你就可以将你准备列表上的一道法术替换为另一道术士法术，你必须拥有替换后法术对应环阶的法术位才可以替换。 | AG44: 链之魔契 | AH44: 你习得法术寻获魔宠Find Familiar且能以一个魔法动作施展它，且无需消耗法术位。 每当你施展该法术，并为你的魔宠选择形态时，除了通常的形态选项，你还可以改为选择下列特殊形态之一：小魔鬼Imp、伪龙Pseudodragon、小恶魔Quasit、骷髅Skeleton、史拉蟾蝌蚪Slaad Tadpole 、求索斯芬克斯Sphinx of Wonder 、小仙灵Sprite或毒蛇Venomous Snake （魔宠的数据见附录B）。 此外，当你执行攻击动作时可以放弃自己动作攻击中的一次攻击，转而让你的魔宠使用其反应发动一次攻击。 | AJ44: 准备法术 | AK44: 你准备可供你以此特性施展的一环及更高环阶的法术列表。为此，从书中选择四道法师法术。你所选择法术的环阶必须是你所拥有法术位对应的环阶 已准备法术数量会随你法师等级的提升而增加，如法师特性表中的准备法术一列所示。每当这一列的数字增加时，从法师法术列表中选择额外法术准备，直至已准备法术的数量与表格中的数字一致。你所选择法术的环阶必须是你所拥有法术位对应的环阶。例如，如果你是一名3级法师，则你的准备法术列表能包括六道一环或二环的法师法术，随意组合。 如果法师的其他特性给了你始终准备了的法术，这些法术不计入你以此法准备的法术数量，但这些法术对你而言都视为法师法术。 | AM44: 法术位 | AN44: 奇械师特性表显示了你可用于施展一环及以上法术的法术位数量。你在完成一次长休时恢复所有已消耗的法术位。 | AP44: 改变你的准备法术 | AQ44: 每当你获得一个灵能使等级时，你就可以将你准备列表上的一道法术替换为另一道灵能使法术，你必须拥有替换后法术对应环阶的法术位才可以替换。 | AS44: 胀痛血咒 | AT44: 以一个附赠动作，你诅咒 30 尺内一个你能看见的生物，令其痛苦地膨胀直至你的下回合结束。在此诅咒生效期间，该生物在力量及敏捷检定中具有劣势，并且，如果其在回合内近战多于一次，受到 1d8 点暗蚀伤害。 增幅。此诅咒持续一分钟。被诅咒的生物在自己的每回合结束时可以进行体质豁免。豁免成功时此诅咒结束。 | AV44: 法术的准备和施展 | AW44: 药剂师职业表展示了你有多少能用以施展一环到五环药剂师法术的法术位。职业表也展示了这些法术位的环阶；你所有法术位的环阶总是相同的。要施展一个你的一环或更高环阶的药剂师法术，你必须消耗一个法术位。当你完成一次短休或长休后，你恢复所有已消耗的法术位。 从药剂师法术列表中，你可以准备一系列药剂师法术供你自由施展。当你这样做时，选择数量等同于你智力调整值+你药剂师职业等级（最少为1）的药剂师法术。你准备的一个法术，其环阶不能超过药剂师职业表所展示的你当前职业等级所对应的法术环阶。 举例来说，如果你是一个五级药剂师，你拥有三个3环法术位。智力属性为16时，你的准备法术列表便囊括了1环、2环、3环中任意选择的八个法术。要施展1环法术疗伤术，你必须消耗这些法术环位中的一个，并以3环版本释放它。施展一个法术并不会将它从你的准备法术列表中移除。 当你长休后，你可以改变你的准备法术列表。准备一系列新的药剂师法术需要为你列表中每个法术每个法术环阶消耗至少一分钟的时间。 | AX44: 2 | AY44: 风险 | AZ44: 借助名为风险骰的特殊骰子，你可以施展令人难以置信的大胆壮举。 风险骰Risk Dice。 你具有四枚d8风险骰。每当你使用风险骰时，其被消耗。当你完成短休或长休时，重获所有已消耗的风险骰。你的风险骰将变动，且其可用数量会增多，如铳士特性表中风险骰一列所示。 战技Maneuvers。你可以消耗风险骰来施展战技。你的战技选项见后文详述。 豁免检定Saving Throw。若某个战技要求豁免检定，其DC等于8加你的敏捷调整值加你的熟练加值。 | BA44: 2 | BB44: 战斗精通 | BC44: 你的大魔鬼赐予了你以某种特定方式战斗的强大技艺。选择以下邪狱使战斗精通之一：_x000D_ 傲慢Bravado。若你未着装任何护甲，你的护甲等级等于10+你的敏捷调整值+你的魅力调整值。你可以使用盾牌并仍从此特性获益。_x000D_ 蛮横Brutal。当你使用双手持握一把近战武器发动的攻击，命中了一个体型至多比你大一级的生物时，你可以令目标水平移动5尺。你可以选择在这之后立即消耗你的移动力移动到该生物移动前所处的空间。_x000D_ 无阻Inexorable。每有一名敌对生物位于你5尺内，你进行的豁免检定就会获得+1加值，至多以此获得+5加值。_x000D_ 欺诈Lies。你可以选择一种近战武器，例如战斧、巨剑、矛。当你使用所选类型的武器攻击时，可以用魅力调整值代替力量或敏捷来进行攻击检定和伤害掷骰。当你完成一次长休时，你可以选择一个新的武器类型，代替原先所选的武器类型。_x000D_ 轻盈Lissome。当你以一次近战武器攻击命一名生物时，你可以消耗你的移动力移动5尺，此次移动不会引发借机攻击。_x000D_ 无拘Unfettered。当你尝试用极恶禁令特性施加或焚灭缄印时，其范围不再是30尺而是改为60尺。当你在6级获得炼狱交移特性时，其范围不再是触碰而是改为30尺。此外，若你5尺内有敌对生物，你发动的远程攻击不会因此具有劣势。 | BD44: 2 | BE44: 傲然致胜 | BF44: 当你的力量、敏捷、体质或魅力检定失败时，你能消耗1点锐气尝试以傲然之姿迈向成功。投掷你的拳斗骰并将骰值加入属性检定中，这可能使你的检定改为成功。若属性检定仍然失败，你重获消耗的那点锐气且直至完成短休或长休都无法再次使用该特性。 | CH44: 腹酿道途 | CI44: 98 | CJ44: {=_xlfn.IFS($AZ$2>=14,102,$AZ$2>=10,101,$AZ$2>=6,100,$AZ$2>=3,99,1,0)} -> 0 | CN44: =IFERROR(IF(CN43+1>CS2,IF(CN43+1>CS2,IF(CR3+CR43>CS3,"",CR3+CR43)),CN43+1),"") -> 39 | CO44: {=IFERROR(INDEX($B$34:$BO$262,CN44,$CP$2),"")} | CP44: {=IFERROR(INDEX($B$34:$BO$262,CN44,$CQ$2),"")} | CQ44: {=IF(IFERROR(INDEX($B$34:$BO$262,CN44,$CO$2),"")=0,"",IFERROR(INDEX($B$34:$BO$262,CN44,$CO$2),""))} | CR44: =IFERROR(IF(CN43+1>CS2,CR43+1,0),"") -> 0 | CT44: =IFERROR(IF(OR(CO48="",COUNTIF($CW$2:$CW$81,CO48)),"",CO48),"") | CU44: {=INDEX(CT:CT,SMALL(IF($CT$2:$CT$101<>"",ROW($CT$2:$CT$101),142),ROW(CT43)))&""} | CV44: =IFERROR(VLOOKUP(CW44,$CO$6:$CQ$105,3,FALSE),"") | CW44: =IF(主要!AX53="","",主要!AX53) | CX44: =IFERROR(VLOOKUP(CW44,$CO$6:$CQ$105,2,FALSE),"")
A45: 12 | B45: 3 | C45: 野蛮人子职 | D45: 你选择获得一项野蛮人子职：狂战士道途，兽心道途，世界树道途或狂热者道途。子职的内容见后文。子职是一种特化，在特定的野蛮人等级给予你对应的独特能力。此后你将获得你所选的子职所有能力——只要其所需等级不超过你的野蛮人等级。野蛮人特性表列出了你从子职中获得新特性的野蛮人等级。 | F45: 改变你的准备法术 | G45: 每当你获得一个吟游诗人等级时，你就可以将你准备列表上的一道法术替换为另一道吟游诗人法术，你必须拥有替换后法术对应环阶的法术位才可以替换。 | I45: 施法属性 | J45: 你牧师法术的施法属性是感知。 | L45: 施法属性 | M45: 你德鲁伊法术的施法属性是感知。 | N45: 3 | O45: 战士子职 | P45: 你选择获得一项战士子职：战斗大师、 勇士 、 奥法骑士或 灵能武士。子职的内容见后文。子职是一种特化，在特定的战士等级给予你对应的独特能力。此后你将获得你所选的子职所有能力——只要其所需等级不超过你的战士等级。战士特性表列出了你从子职中获得新特性的战士等级。 | Q45: 3 | R45: 拨挡攻击 | S45: 当你被一次伤害中包含钝击，穿刺或挥砍伤害的攻击检定命中时，你可以执行反应减少此次攻击对你造成伤害的总值，减值等于1d10+你的敏捷调整值+你的武僧等级。 若被拨挡攻击的伤害减少至0，则你可以消耗1点功力将此次攻击的部分伤害重新定向。如果是近战攻击，选择你周围5尺内的一个你可见的生物；如果是远程攻击，选择60尺内一个不位于全身掩护后的你可见的生物。该生物必须成功通过一次敏捷豁免，否则受到相当于你2个武艺骰+你的敏捷调整值的伤害。其伤害类型与原先攻击的伤害类型相同。 | U45: 施法属性 | V45: 你圣武士法术的施法属性是魅力。 | X45: 施法法器 | Y45: 你可以使用德鲁伊法器作为你游侠法术的施法法器。 | Z45: 3 | AA45: 游荡者子职 | AB45: 你选择获得一项游荡者子职：诡术师，刺客， 魂刃 或 盗贼。子职的内容见后文。子职是一种特化，在特定的游荡者等级给予你对应的独特能力。此后你将获得你所选的子职所有能力——只要其所需等级不超过你的游荡者等级。游荡者特性表列出了你从子职中获得新特性的游荡者等级。 | AD45: 施法属性 | AE45: 你术士法术的施法属性是魅力。 | AG45: 书之魔契 | AH45: 在一次短休或长休结束时，你将幽影聚在手中，编织为一本书册。这本书（由你决定外观）中承载着只有你能理解的骇人魔法，令你获得以下增益。书册会在你以此特性咒唤另一本书或死亡时消失。 戏法和仪式Cantrips and Rituals。当书册出现时，选择三道戏法和两道带有仪式标签的一环法术。这些法术可以来自任何职业的法术列表，且不能是你已经准备了的法术。当这本书册在你的角色身上时，你总是准备了这些法术，且对你而言这些法术是魔契师法术。 施法法器Spallcasting Forcus。你可以将此书册作为施法法器。 | AJ45: 改变你的准备法术 | AK45: 每当你完成一次长休时，你可以将你准备列表上的一道或更多法术替换为你法术书上的其他法师法术。 | AM45: 准备一环或以上的法术 | AN45: 准备可供你以此特性施展的1+环的法术列表。为此，选择两个一环奇械师法术。推荐疗伤术Cure Wounds和油腻术Grease 。 你列表中的法术数量会在你提升奇械师等级时增加，如奇械师特性表中的准备法术一列所示。每当这一列的数字增加时，选择额外的奇械师法术，直至你列表中的法术数量的数量与表格中的数字一致。选择的法术必须有相对应环阶的法术位。例如，如果你是一位5级奇械师，你的准备法术列表能包括6道一环或二环的奇械师法术，随意组合。 如果其他奇械师特性给了你永远已准备的法术，这些法术不计入你以此法准备的法术数量，但除此以外对你来说都视为奇械师法术。 | AP45: 施法属性 | AQ45: 你灵能使法术的施法属性是智力。 | AS45: 暴露诅咒 | AT45: 当距你 30 尺内一你能看到的生物受到攻击或法术的伤害时，你可以使用你的反应来暂时削弱其抵抗力。直到目标下一回合结束，其失去对该攻击或法术造成的所有伤害类型的抵抗力（包括该攻击或法术）。 增幅。目标失去对该攻击或法术的所有的伤害类型的免疫力，但在其下一回合结束前，对这些伤害类型具有抵抗力。 | AV45: 施法属性 | AW45: 药剂师法术的施法属性是智力。 | AY45: 咬紧牙关 | AZ45: 以一个附赠动作，你可以消耗一枚风险骰获得数值等于风险骰骰值加你的铳士等级的临时生命值。 | BA45: 2 | BB45: 禁令 | BC45: 你可以将炼狱的魔法力量注入缄印以增强其效应。_x000D_ 已知禁令恩惠Interdict Boons Known。你自禁令恩惠选项中习得一种自选的禁令恩惠。当你获得本职业等级时，你选择获得额外的禁令恩惠，具体数据见邪狱使表中“禁令恩惠”一栏。你必须满足每个新恩惠的先决等级。例如，当你到达7级时，你可以习得一个2级或7级的恩惠。_x000D_ 每当你获得一级邪狱使等级时，你都可以用新的恩惠替换一个已知的恩惠，但你必须可以习得新恩惠。_x000D_ 使用禁令恩惠Use Interdict Boons。 一些恩惠允许你消耗未施加的缄印来增强能力，另一些恩惠则增强你的缄印或是赋予你对抗受禁生物时生效的增益。_x000D_ 那些授予被动的（或者说“始终开启的”）增益的恩惠，例如2级的“极速惩戒”恩惠，标有“被动”标签。你无需消耗缄印或是执行动作即可从被动恩惠中获得增益。而所有其他没有被动标签的恩惠，例如2级的“缓弱缄印”恩惠必须在某个回合激活（例如通过消耗缄印）。无论你已知的恩惠有几个，每回合你只能激活一个非被动恩惠。 | BD45: 3 | BE45: 重磅巨拳 | BF45: 当你以徒手打击命中一名生物时，你能在应用徒手打击的伤害选项的同时选择应用擒抱或推撞选项中的一项。 | CH45: 实验道途 | CI45: 103 | CJ45: {=_xlfn.IFS($AZ$2>=14,107,$AZ$2>=10,106,$AZ$2>=6,105,$AZ$2>=3,104,1,0)} -> 0 | CN45: =IFERROR(IF(CN44+1>CS2,IF(CN44+1>CS2,IF(CR3+CR44>CS3,"",CR3+CR44)),CN44+1),"") -> 40 | CO45: {=IFERROR(INDEX($B$34:$BO$262,CN45,$CP$2),"")} | CP45: {=IFERROR(INDEX($B$34:$BO$262,CN45,$CQ$2),"")} | CQ45: {=IF(IFERROR(INDEX($B$34:$BO$262,CN45,$CO$2),"")=0,"",IFERROR(INDEX($B$34:$BO$262,CN45,$CO$2),""))} | CR45: =IFERROR(IF(CN44+1>CS2,CR44+1,0),"") -> 0 | CT45: =IFERROR(IF(OR(CO49="",COUNTIF($CW$2:$CW$81,CO49)),"",CO49),"") | CU45: {=INDEX(CT:CT,SMALL(IF($CT$2:$CT$101<>"",ROW($CT$2:$CT$101),142),ROW(CT44)))&""} | CV45: =IFERROR(VLOOKUP(CW45,$CO$6:$CQ$105,3,FALSE),"") | CW45: =IF(主要!AX54="","",主要!AX54) | CX45: =IFERROR(VLOOKUP(CW45,$CO$6:$CQ$105,2,FALSE),"")
A46: 13 | B46: 3 | C46: 原初学识 | D46: 除了1级选择的技能以外，你可以从野蛮人技能列表中额外获得一个技能的熟练。 此外，狂暴激活期间，你可以在尝试完成特定的事项时与原初之力相连。每当你使用以下技能进行一次属性检定时，你可以使用力量进行检定而非通常使用的其他属性：特技，威吓，察觉，隐匿或求生。当你使用这项能力时，你的力量代表着一种环绕你身的原初之力，强化了你的灵敏度、气质和感知力。 | F46: 施法属性 | G46: 你吟游诗人法术的施法属性是魅力 。 | I46: 施法法器 | J46: 你可以使用圣徽作为你牧师法术的施法法器 。 | L46: 施法法器 | M46: 你可以使用德鲁伊法器作为你德鲁伊法术的施法法器。 | N46: 4 | O46: 属性值提升 | P46: 你获得属性值提升专长（见第五章）或其它你满足条件的专长。如战士特性表所示，你还会在第6、第8、第12、第14、第16级时再次获得本特性。 | Q46: 3 | R46: 武僧子职 | S46: 你选择获得一项武僧子职：命流武者、暗影武者、 四象武者和散打武者。子职的内容见后文。子职是一种特化，在特定的武僧等级给予你对应的独特能力。以后你将获得你所选的子职的所有能力——只要其所需等级不超过你的武僧等级。武僧特性表列出了你从子职中获得新特性的武僧等级。 | U46: 施法法器 | V46: 你可以使用圣徽作为你圣武士法术的施法法器 。 | W46: 1 | X46: 宿敌 | Y46: 你始终准备了法术猎人印记Hunter’s Mark。你可以无需法术位地施展此法术共计两次，并在完成一次长休后恢复此能力的所有使用次数。 你能无需法术位施展该法术的次数会在你获得特定游侠等级时提升，见游侠特性表中的宿敌一栏。 | Z46: 3 | AA46: 稳定瞄准 | AB46: 以一个附赠动作，你在当前回合为你的下一次攻击提供优势。你只能在你本回合还没有移动的时候使用这个附赠动作，而且在你使用这个附赠动作后，你的速度在当前回合里归0。 | AD46: 施法法器 | AE46: 你可以使用奥术法器作为你术士法术的施法法器。 | AG46: 符之魔契 | AH46: 你的宗主赐予你一个护身符，一个当需要的时候可以帮助佩戴者的护身符。当佩戴者在一次属性检定中失败，他们可以在骰掷结果上增加一个d4骰，这可能将结果变为成功。这一能力可使用的次数等于你的熟练加值，且所有已消耗的次数将会在你完成一次长休之后全部恢复。 如果你弄丢了护身符，你可以进行一个1小时的仪式从你的宗主那里得到一个替代品。这一仪式可以在一个短休或一个长休过程中完成，且它将会破坏之前的护身符。护身符将会在你死亡时消散为灰尘。 | AJ46: 施法属性 | AK46: 你法师法术的施法属性是智力。 | AM46: 改变准备法术 | AN46: 每当你结束一次长休时，你可以改变你的法术准备列表，将任意数量的法术替换为你具有对应法术位的奇械师法术。 | AP46: 灵能施法 | AQ46: 当你施展一道灵能使法术时，那道法术不需要言语或材料成分，哪怕该法术在其法术成分中标注了“V”和“M”，除非法术材料成分会被消耗或有特定价格。 | AS46: 盲目血咒 | AT46: 当距你 30 尺内一个你能看见的生物进行一次攻击时，你可以使用你的反应来掷一个鲜血秘法骰，并在目标的掷骰结果中减去你的掷骰结果。你可以在目标掷出骰子后，DM 宣布结果之前决定是否使用此特性。若目标免疫目盲状态，则目标同样也会免疫该特性。 增幅。你对该生物的所有攻击检定使用此诅咒，直至回合结束。你为每次受影响的攻击各掷一次鲜血秘法骰。 | AV46: 法器 | AW46: 你可以使用奥术法器（详见第5章）来作为施展药剂师法术的法器。 | AY46: 盲射 | AZ46: 你能够以附赠动作消耗一枚风险骰来获得30尺盲视，持续至当前回合结束。 | BA46: 2 | BB46: 缓弱缄印 | BC46: 当一名你可见的生物对你或位于你30尺内的盟友造成伤害时，你能够以反应消耗一枚缄印，来减少目标受到的伤害，减少量等于1d10+你的邪狱使等级的一半（向下取整）。 | BD46: 3 | BE46: 拳斗士子职 | BF46: 你选择获得一项拳斗士子职。子职的内容见后文。子职是一种特化，在特定的拳斗士等级给予你对应的独特能力。此后你将获得你所选的子职所有能力——只要其所需等级不超过你的拳斗士等级。 | CH46: 腐鸦道途 | CI46: 108 | CJ46: {=_xlfn.IFS($AZ$2>=14,129,$AZ$2>=10,128,$AZ$2>=6,127,$AZ$2>=3,126,1,0)} -> 0 | CN46: =IFERROR(IF(CN45+1>CS2,IF(CN45+1>CS2,IF(CR3+CR45>CS3,"",CR3+CR45)),CN45+1),"") -> 41 | CO46: {=IFERROR(INDEX($B$34:$BO$262,CN46,$CP$2),"")} | CP46: {=IFERROR(INDEX($B$34:$BO$262,CN46,$CQ$2),"")} | CQ46: {=IF(IFERROR(INDEX($B$34:$BO$262,CN46,$CO$2),"")=0,"",IFERROR(INDEX($B$34:$BO$262,CN46,$CO$2),""))} | CR46: =IFERROR(IF(CN45+1>CS2,CR45+1,0),"") -> 0 | CT46: =IFERROR(IF(OR(CO50="",COUNTIF($CW$2:$CW$81,CO50)),"",CO50),"") | CU46: {=INDEX(CT:CT,SMALL(IF($CT$2:$CT$101<>"",ROW($CT$2:$CT$101),142),ROW(CT45)))&""} | CV46: =IFERROR(VLOOKUP(CW46,$CO$6:$CQ$105,3,FALSE),"") | CW46: =IF(主要!AX55="","",主要!AX55) | CX46: =IFERROR(VLOOKUP(CW46,$CO$6:$CQ$105,2,FALSE),"")
A47: 14 | B47: 4 | C47: 属性值提升 | D47: 你获得属性值提升专长（见第五章）或其他你满足条件的专长。如野蛮人特性表所示，你还会在第8，第12，第16级时再次获得本特性。 | F47: 施法法器 | G47: 可以使用乐器作为你吟游诗人法术的施法法器。 | H47: 1 | I47: 圣职 | J47: 你让自己投身于以下一种由你自己选择的神圣职能： 保护者 Protcetor。通过战斗训练，你获得军用武器熟练与重甲受训。 奇术使 Thaumaturage。你从牧师法术列表中额外学会一道戏法。此外，你与神性的神秘链接使你在智力（奥秘和宗教）检定中获得加值。加值等于你的感知调整值（最小为1）。 | K47: 1 | L47: 德鲁伊语 | M47: 你学会了德鲁伊语，一门德鲁伊之间的秘密语言。在学会这门古老语言的同时，你也解锁了和动物交谈的魔法：你始终准备了法术动物交谈Speak With Animals。 你可以使用德鲁伊语来传递隐藏的信息。你和其他知晓这门语言的对象能够自动辨认出信息。其他人需要通过DC15的智力（调查）检定才能意识到信息的存在，但不借助魔法则无法解读。 | N47: 5 | O47: 额外攻击 | P47: 你在自己回合内执行攻击动作时，可以发动两次攻击而非一次。 | Q47: 4 | R47: 属性值提升 | S47: 你获得属性值提升专长（见第五章）或其它你满足条件的专长。如武僧特性表所示，你在第8，第12，第16级时会再次获得本特性。 | T47: 1 | U47: 武器精通 | V47: 你对武器的训练使你能够运用两种自选熟练武器的精通属性，比如选择长剑和标枪。 当你完成一次长休时，你可以改变你所选择的武器类型。比如你可以改为使用长戟和连枷。 | W47: 1 | X47: 武器精通 | Y47: 你对武器的训练使你能够自选并使用2种已熟练武器的精通词条，例如长弓和短剑。 当你完成一次长休时，你可以改变你所选择的武器类型。比如你可以将其改为弯刀和长剑。 | Z47: 4 | AA47: 属性值提升 | AB47: 你获得属性值提升专长（见第五章）或其它你满足条件的专长。如游荡者特性表所示，你还会在第8，第10，第12，第16级时再次获得本特性。 | AC47: 1 | AD47: 先天术法 | AE47: 你过去经历的某件事在你身上留下了不可磨灭的印记，为你注入了难以控制的涌动魔力。以一个附赠动作，你可以将魔力释放而出，持续1分钟。在这1分钟期间，你获得以下增益： 你的术士法术豁免DC+1。 你施展的术士法术的攻击检定具有优势。 你可以使用此特性两次，你在完成一次长休时重获所有已消耗的使用次数。 | AG47: =IF(自定义调整栏!$E$3="O","月之仪态","") -> 月之仪态 | AH47: 你不再需要睡眠，同样不能以任何方式强行陷入睡眠。为了获得长休的益处，你可以在8小时内执行一些轻度活动，像是阅读你的 影之书Book of Shadows 或是放哨之类的。 先决条件：书之魔契 | AJ47: 施法法器 | AK47: 你可以使用奥术法器或你的法术书作为你法师法术的施法法器。 | AM47: 施法属性 | AN47: 奇械师法术的施法属性是智力。 | AO47: 1 | AP47: 灵能力量 | AQ47: 你的体内潜藏着一股灵能力量之源。这股力量由你的灵能骰展示。你的灵能使等级决定了灵能骰大小与数量，如灵能使特性表格中展示。 你的灵能骰可用来强化或为特定灵能使特性充能。你在起始时拥有两项特性：念力驱使与心灵连接，每一项详述于下。有些心灵异能会消耗灵能骰，具体见各项异能详述，当你所有的灵能骰都消耗光时，你无法使用一项需要你使用一枚灵能骰的异能。 你在完成一次短休时恢复一枚灵能骰，你在完成一次长休时回复所有灵能骰。有的使用灵能骰的特性要求你的目标进行豁免检定。异能豁免DC与本职业的施法特性中的法术豁免DC相同。 念力驱使Telekinetic Propel。 以一个附赠动作，选择30尺内一名你可见的不超过大型的除你以外的生物。若如此做，目标必须成功通过一次力量豁免，否则就会被你向自己的方向或背向自己的方向直线移动5尺。此外，你执行此附赠动作时可以投掷一枚灵能骰，移动距离等于灵能骰点数的5倍。灵能骰只在目标豁免失败时被消耗。 心灵连接Telepathic Connection。你具有30尺心灵感应。以一个附赠动作，你可以投掷一枚灵能骰。你的心灵感应等于灵能骰点数的10倍的距离，持续1小时。你在每次长休后首次执行此附赠动作时，你无需消耗灵能骰。其他所有时间你使用该特性时，你消耗灵能骰。 | AS47: 傀儡血咒 | AT47: 当距你 30 尺内一个你能看见的生物生命值降为 0 点时，你可以使用你的反应来迫使该生物立即对其攻击范围内一个你选择的目标发动一次武器攻击。 增幅。你可以先移动该生物至多其速度一半的距离，并且该生物的攻击骰得到等同于你鲜血秘法调整值的加值（至少为 1）。 | AU47: 2 | AV47: 隐秘理论 | AW47: 你已经发现了一些隐秘理论，这些失落学问的只言片语可以用来强化你的魔法能力。 你获得两种你所选的隐秘理论。可供你所选的理论在职业描述最后有详述。 当你获得特定药剂师等级时，你可以额外获得你选择的理论，如药剂师职业表所展示的已知理论栏所示。除此之外，每当你获得一个该职业等级时，你可以选择一个你已经学习的理论，并用你当前等级可学习的另一个理论替换之。 | AY47: 翻滚闪避 | AZ47: 作为一个附赠动作，你可以消耗一枚风险骰移动至多15尺并为你正持握的远程武器换弹。此次移动不会引发借机攻击且不受困难地形影响。 | BA47: 2 | BB47: 凌虐 | BC47: 当你焚灭受禁生物身上的缄印时，你可以激活此恩惠（无需动作）。目标在其下回合结束前进行的下一次豁免检定承受等于你熟练加值的减值。 | BD47: 4 | BE47: 属性值提升 | BF47: 你获得属性值提升专长或其他你满足条件的专长。你还会在第8，第12，第16级时再次获得本特性。 | CH47: 炼狱道途 | CI47: 130 | CJ47: {=_xlfn.IFS($AZ$2>=14,134,$AZ$2>=10,133,$AZ$2>=6,132,$AZ$2>=3,131,1,0)} -> 0 | CN47: =IFERROR(IF(CN46+1>CS2,IF(CN46+1>CS2,IF(CR3+CR46>CS3,"",CR3+CR46)),CN46+1),"") -> 42 | CO47: {=IFERROR(INDEX($B$34:$BO$262,CN47,$CP$2),"")} | CP47: {=IFERROR(INDEX($B$34:$BO$262,CN47,$CQ$2),"")} | CQ47: {=IF(IFERROR(INDEX($B$34:$BO$262,CN47,$CO$2),"")=0,"",IFERROR(INDEX($B$34:$BO$262,CN47,$CO$2),""))} | CR47: =IFERROR(IF(CN46+1>CS2,CR46+1,0),"") -> 0 | CT47: =IFERROR(IF(OR(CO51="",COUNTIF($CW$2:$CW$81,CO51)),"",CO51),"") | CU47: {=INDEX(CT:CT,SMALL(IF($CT$2:$CT$101<>"",ROW($CT$2:$CT$101),142),ROW(CT46)))&""} | CV47: =IFERROR(VLOOKUP(CW47,$CO$6:$CQ$105,3,FALSE),"") | CW47: =IF(主要!AX56="","",主要!AX56) | CX47: =IFERROR(VLOOKUP(CW47,$CO$6:$CQ$105,2,FALSE),"")
A48: 15 | B48: 5 | C48: 额外攻击 | D48: 当你在自己的回合执行攻击动作时，你可以发动两次攻击而非一次。 | E48: 2 | F48: 专精 | G48: 你获得两项由你选择的你熟练技能的专精（见术语汇编）。如果你具有表演和游说的熟练，推荐选择这两项。 当你的吟游诗人等级到达9级时，你再额外获得两项由你选择的你熟练技能的专精。 | H48: 2 | I48: 引导神力 | J48: 你能从外层位面引导神圣能量，并用其引动魔法效应。你起始时具有两种选项：神圣火花与驱散亡灵，其效果如下所示。每当你使用你的引导神力时，你选择要创造哪种效应。你会在更高的牧师等级获得更多选项。 你可以使用引导神力两次，你在完成一次短休时恢复一次使用次数，而在完成一次长休时重获所有已使用的次数。你在达到特定的牧师等级时获得额外的使用次数，具体见牧师特性表中引导神力一栏。 如果某个引导神力效应需要目标进行豁免，则其豁免DC等于本职业的施法特性中的法术豁免DC。 | K48: 1 | L48: 原初职能 | M48: 你将自己投身于所选择的以下一项神圣的角色之中： 术师Magician。你从德鲁伊法术列表中额外学会一道戏法。此外，你与自然的神秘连接让你在智力（奥秘和自然）检定上获得加值。加值等于你的感知调整值（最低为1）。 卫士Warden。你受到了战斗的训练，获得军用武器熟练和中甲熟练。 | N48: 5 | O48: 战术转进 | P48: 每当你使用附赠动作进行回气时，你可以移动至多相当于你速度一半的距离，且不会引发借机攻击。 | Q48: 4 | R48: 轻身坠 | S48: 当你要承受坠落伤害时，你可以使用反应将伤害减少等同于五倍武僧职业等级的数值。 | T48: 2 | U48: 战斗风格 | V48: 你获得一项战斗风格专长（见第五章）。 | W48: 2 | X48: 熟练探险家 | Y48: 得益于你的旅途，你获得以下增益。 专精Expertise。选择一项你熟练但不具备专精的技能。你在那个技能上获得专精。 语言Languages。 你习得第二章中的语言表中的两种语言 | Z48: 5 | AA48: 诡诈打击 | AB48: 你学会了如何使你的偷袭更加狡诈的方法。当你造成偷袭伤害时，你可以选择下列一种诡诈打击的效果加入到本次偷袭中。每种效果都需要花费一定数量的偷袭伤害骰才能生效。你必须在投掷伤害前扣除所花费的偷袭的伤害骰，而效果会在这次攻击的伤害产生后立即发生。例如，如果你在本次偷袭中选择了淬毒效果，那么你在投掷偷袭伤害骰前需要先减少一颗1d6。 如果一种诡诈打击的效果要求目标进行豁免，其DC为8+你的熟练加值+你的敏捷调整值。 淬毒Poison（花费：1d6）。你为你的打击附上毒素，强迫目标进行一次体质豁免。若失败，目标将陷入一分钟的中毒状态。目标可以在每次自己的回合结束时重新进行豁免，若成功，中毒状态终止。为了使用这个效果，你必须携带一套制毒工具在身上。 摔绊Trip（花费：1d6）。若偷袭的目标是大型及以下，它必须成功通过一次敏捷豁免，否则陷入倒地状态。 撤步Withdraw (花费：1d6)。攻击后你立刻移动至多等于你速度的一半的距离，并且不会引发借机攻击。 | AC48: 2 | AD48: 魔力泉涌 | AE48: 你汲取体内的魔力之源，从中涌现的魔力体现为你的可用术法点。你可以使用术法点创造各种魔法效应。 你拥有2点术法点，你在到达更高等级时获得更多术法点，如同术士特性表中术法点一栏所示。你无法拥有比表格中对应数量更多的术法点。你在完成一次长休后重获所有已消耗的术法点。 你可以消耗你的术法点来使用以下特性，例如超魔法。 法术位转化为术法点Converting Spell Slots to Sorcery Points。你可以消耗一个法术位来获得等同于其环位的术法点（无需动作）。 创造法术位Creating Spell Slots。以一个附赠动作，你可以将未消耗的术法点转化为一个法术位。创造法术位表格中展示了创造法术位所需的术法点以及创造它所需的最小术士等级。你无法创造高于五环的法术位。 你以此特性创造的任何法术位都在完成一次长休时消失。 创造法术位Creating Spell Slots 法术位环阶 术法点消耗 最小术士等级 1 2 2 2 3 3 3 5 5 4 6 7 5 7 9 | AG48: =IF(自定义调整栏!$E$3="O","永生者赠礼","") -> 永生者赠礼 | AH48: 当你被恢复生命值时，只要此时你的魔宠与你之间的距离不超过100尺，所有决定你恢复生命值点数的骰，都被视为骰出了最大值。 先决条件：链之魔契 | AJ48: 扩展与替换法术书 | AK48: 你获得职业等级时添加到法术书中的法术反映了你自己进行的魔法研究，但你可能会在冒险过程中发现其他可以添加至法术书中的法术。例如，你可能在一张法术卷轴Spell Scroll中发现一道法师法术，然后将该法术抄到你的法术书中。 | AL48: 2 | AM48: 仿制魔法物品 | AN48: 你知晓一些用来制造魔法物品的奥术方案。 已知方案Plans Known。当你获得此特性时，从魔法物品方案表（奇械师等级2+）中选择四个方案习得（见《城主指南》以了解物品的描述）。推荐次元袋Bag of Holding，水下呼吸帽Cap of Water Breathing，传讯石Sending Stones和+1战法师魔杖 Wand of the War Mage+1 。每当你提升一个奇械师等级时，你可以将其中一个你已知的方案替换为一个你能够选择的新方案。 当你达到特定奇械师等级时，你知晓另外的你选择的方案，如奇械师特性表中已知方案一列所示。 创造物品Creating an Item。当你结束长休时，你可以在持握修补工具时创造一件或两件不同的魔法物品。每件物品都基于你在此特性已知的其中一个方案。 如果一件创造物品需要同调，你可以在创造它时立刻与其同调。如果你决定以后再与这个物品进行同调，你就必须进行通常的同调程序了。 当你达到奇械师特性表中魔法物品列所示的特定的奇械师等级时，你在长休结束时可以创造的魔法物品数量会增加。每件你创造的物品都必须基于你已知的不同方案。 如果你尝试超过此特性的最大魔法物品数量，最旧的物品将会消失，随后新的物品出现。 持续时间Duration。以此特性创造的魔法物品作用如同正常的魔法物品，只是它的魔法不是永久的。当你死亡，魔法物品会在1d4天后消失。 如果你以此特性创造的一件物品是一个容器，比如次元袋Bag of Holding ，它消失时，其中的物品将无害地出现在它周围的空间中。 施法法器Spellcasting Focus。 你可以使用任何以此法创造的魔杖或武器代替使用工匠工具来作为施法法器 | AO48: 1 | AP48: 精妙念力 | AQ48: 你知晓戏法法师之手。你可以施展该法术而不需要言语成分，你可以在施展法术时令幽灵手隐形。 | AS48: 印记血咒 | AT48: 以一个附赠动作，你可以标记距你 30 尺内一个生物。直至你下回合结束，当你对目标造成血仪伤害时，你额外造成一个鲜血秘法骰的血仪伤害。 增幅。你在下回合结束前，对目标进行的下次攻击骰具有优势。 | AU48: 2 | AV48: 后天耐受性 | AW48: 你进行对抗毒素的豁免时具有优势，并且拥有毒素伤害的抗性。此外，你自动通过来自你自己的药剂师法术的豁免检定，并且永远不会因自己的药剂师法术收到伤害。 | AY48: 擦掠弹 | AZ48: 当你使用武器进行的远程攻击检定失手时，你可以消耗一枚风险骰（无需动作）对该生物造成等于风险骰骰值加你的敏捷调整值（至少为1）的伤害，伤害类型为武器伤害类型，此伤害仅可通过提升属性调整值提高。每回合你仅可使用一次该战技。 | BA48: 2 | BB48: 噬魂夺魄 | BC48: 当你焚灭受禁生物身上的缄印时，你可以激活此恩惠（无需动作）以获得等于你邪狱使等级的临时生命值。 | BD48: 4 | BE48: 反求诸己 | BF48: 你能以附赠动作反求诸己。你具有对钝击、穿刺和挥砍伤害的抗性，且你免疫等级低于6级的力竭效应，持续10分钟。_x000D_ 此特性一经使用，直至完成长休你都无法再次使用，除非你获得1级力竭（无需动作）来重置该特性的使用权。 | CH48: 噬影徒 | CI48: 135 | CJ48: {=_xlfn.IFS($AZ$2>=14,138,$AZ$2>=10,137,$AZ$2>=6,136,$AZ$2>=3,135,1,0)} -> 0 | CN48: =IFERROR(IF(CN47+1>CS2,IF(CN47+1>CS2,IF(CR3+CR47>CS3,"",CR3+CR47)),CN47+1),"") -> 43 | CO48: {=IFERROR(INDEX($B$34:$BO$262,CN48,$CP$2),"")} | CP48: {=IFERROR(INDEX($B$34:$BO$262,CN48,$CQ$2),"")} | CQ48: {=IF(IFERROR(INDEX($B$34:$BO$262,CN48,$CO$2),"")=0,"",IFERROR(INDEX($B$34:$BO$262,CN48,$CO$2),""))} | CR48: =IFERROR(IF(CN47+1>CS2,CR47+1,0),"") -> 0 | CT48: =IFERROR(IF(OR(CO52="",COUNTIF($CW$2:$CW$81,CO52)),"",CO52),"") | CU48: {=INDEX(CT:CT,SMALL(IF($CT$2:$CT$101<>"",ROW($CT$2:$CT$101),142),ROW(CT47)))&""} | CV48: =IFERROR(VLOOKUP(CW48,$CO$6:$CQ$105,3,FALSE),"") | CW48: =IF(主要!AX57="","",主要!AX57) | CX48: =IFERROR(VLOOKUP(CW48,$CO$6:$CQ$105,2,FALSE),"")
A49: 16 | B49: 5 | C49: 快速移动 | D49: 当你未着装重甲时，你的速度提升10尺。 | E49: 2 | F49: 万事通 | G49: 你可以将你熟练加值的一半（向下取整）添加到任何你不具备其技能熟练并无法通过其他方式应用熟练加值的属性检定中。 例如，如果你要进行力量（运动）检定，且不具有运动熟练，则你可以将熟练加值的一半添加到检定中。 | I49: 神圣火花 | J49: 以一个魔法动作，你将你的圣徽指向30尺内一个你可见的其他生物，并将神圣能量凝聚于该生物。投掷1d8加上你的感知调整值，你为该生物恢复该数值的生命或迫使其进行一次体质豁免，失败则受到等同该数值的黯蚀或光耀伤害（由你选择），成功则伤害减半（向下取整）。 神圣火花在以下牧师等级获得额外的d8骰：7级（2d8），13级（3d8）以及18级（4d8）。 | K49: 2 | L49: 荒野变形 | M49: 大自然的魔力使你得以化形为一只野兽。以一个附赠动作，你变形为一只你已经通过该特性学会的野兽形态（见下文“已知形态”）。你能保持该形态长达你德鲁伊等级一半的小时数，或者直到你再次使用荒野变形，陷入失能，或死亡。你也可以使用一个附赠动作提早结束荒野变形。 | N49: 9 | O49: 不屈 | P49: 当你在一次豁免检定中失败时，你可以重投并获得等同你战士等级的加值。你必须使用新的掷骰结果，你使用此特性后，你必须在完成一次长休后才能再次使用。 第13级起，你可以在两次长休之间使用此特性两次；第17级起，你可以在两次长休之间使用此特性三次。 | Q49: 5 | R49: 额外攻击 | S49: 当你在自己的回合执行攻击动作时，你可以发动两次攻击而非一次。 | T49: 2 | U49: 圣武斩 | V49: 你始终准备了法术至圣斩Divine Smite 。此外，你可以不消耗法术位地施展该法术一次，而后你必须完成一次长休才能再次这么做。 | W49: 2 | X49: 战斗风格 | Y49: 你获得一项战斗风格专长（见第五章）。 | Z49: 5 | AA49: 直觉闪避 | AB49: 当一个你能看见的攻击者用一次攻击检定命中你时，你可以用你的反应将这次攻击对你造成的伤害减半（向下取整）。 | AC49: 2 | AD49: 超魔法 | AE49: 由于你的魔法直接从你体内流向外界，你可以修改你的法术来适应自己的需要。你从超魔法选项中选择并获得2个你所选的超魔法选项。你使用你所选的超魔法来临时改变你施展的法术。要使用一个超魔法选项，你必须消耗等同于其描述中需求的术法点。 当你施展一道法术时，你只能在其上应用一次超魔法选项，除非超魔法选项中另有说明。 每当你获得一级术士等级时，你可以将一个超魔法选项更改为另一个超魔法选项。当你到达10级和17级术士等级时，你可以分别再获得2个超魔法选项。 | AG49: =IF(自定义调整栏!$E$3="O","进阶契约武器","") -> 进阶契约武器 | AH49: 你可以使用你刃之魔契职业特性召唤出来的任何武器作为你施展邪术师法术的法器使用。 此外，若你的契约武器不是一件在攻击检定与其伤害掷骰上具有加值的魔法武器，你的契约武器在攻击检定与其伤害骰上获得+1加值。 不仅如此，当你塑造新的武器时，你可以塑造出一把短弓、长弓、轻弩、或重弩。 （校对注：不选用此魔能祈唤依旧能将魔法武器的此类武器以及其他远程武器作为你的契约武器使用。） 先决条件：刃之魔契特性 | AJ49: 将一道法术抄写到法术书中 | AK49: 如果它是你能进行准备的法术位环阶且你能抽出时间来抄写它，则你可以将其抄写到你的法术书中。每个法术环阶的抄录过程都需要2小时并花费50GP。在此之后，你就可以像准备法术书中的其他法术一样准备该法术了。 | AL49: 2 | AM49: 魔法物品方案（奇械师等级2+） | AN49: 魔法物品方案 同调 炼金壶 Alchemy Jug 否 次元袋 Bag of Holding 否 水下呼吸帽 Cap of Water Breathing 否 非药水、卷轴，且无诅咒的普通魔法物品* 多种 夜视镜 Goggles of Night 否 百变工具Manifold Tool+ 是 连射武器Repeating Shot+ 是 回力武器 Returning Weapon 否 攀爬绳 Rope of Climbing 否 短讯石 Sending Stones 否 +1盾牌 Shield+1 否 侦测魔法魔杖 Wand of Magic Detection 否 探秘魔杖 Wand of Secrets 否 +1战法师魔杖 Wand of the War Mage+1 是 +1武器 Weapon+1 否 +1神威绑带 Wraps of Unarmed Power+1 否 | AO49: 2 | AP49: 灵能才赋 | AQ49: 你学会了更多由你的灵能骰充能的灵能技巧。你获得两项由你选择的灵能才赋，比如延伸意识Expanded Awareness与本我暗示Id Insinuation。才赋详述于后“灵能才赋选项”部分。 你在每一回合中只能使用一种才赋，且除非有其它描述，否则一回合中只能使用一道才赋。 每当你获得灵能使等级时，你可以将一道灵能才赋替换为另一道你未知晓的灵能才赋。你在5，10，13与17级时分别得到一种额外才赋。 | AS49: 乱心血咒 | AT49: 以一个附赠动作，你诅咒距你 30 尺内一个你能看见、且正专注于一个法术的生物。该生物在你下回合结束前为维持专注而进行的下次体质豁免具有劣势。 增幅。诅咒生物在你下回合结束前为维持专注而进行的所有体质豁免检定具有劣势。 | AU49: 2 | AV49: 毒力强劲 | AW49: 当你为一个造成毒素伤害的药剂师法术掷骰伤害骰出1时，你可以重新掷骰该伤害骰。你只能使用新结果，即使新掷骰结果也是1。 | AY49: 牛仔精神 | AZ49: 当你在智力、感知或魅力属性检定或豁免检定中失败时，你可以消耗一枚风险骰并将其加入检定结果中，这可能使检定改为成功。每回合你仅可使用一次该战技。 | BA49: 2 | BB49: 冥河寂寒 | BC49: 当你焚灭受禁生物身上的缄印时，你能够以反应令目标被超常的寒意充满。目标无法执行反应，直至其下回合结束。 | BD49: 5 | BE49: 额外攻击 | BF49: 当你在自己的回合执行攻击动作时，你可以发动两次攻击而非一次。 | CH49: 舞蹈学院 | CI49: 25 | CJ49: {=_xlfn.IFS($AZ$3>=14,28,$AZ$3>=6,27,$AZ$3>=3,25,1,0)} -> 0 | CN49: =IFERROR(IF(CN48+1>CS2,IF(CN48+1>CS2,IF(CR3+CR48>CS3,"",CR3+CR48)),CN48+1),"") -> 44 | CO49: {=IFERROR(INDEX($B$34:$BO$262,CN49,$CP$2),"")} | CP49: {=IFERROR(INDEX($B$34:$BO$262,CN49,$CQ$2),"")} | CQ49: {=IF(IFERROR(INDEX($B$34:$BO$262,CN49,$CO$2),"")=0,"",IFERROR(INDEX($B$34:$BO$262,CN49,$CO$2),""))} | CR49: =IFERROR(IF(CN48+1>CS2,CR48+1,0),"") -> 0 | CT49: =IFERROR(IF(OR(CO53="",COUNTIF($CW$2:$CW$81,CO53)),"",CO53),"") | CU49: {=INDEX(CT:CT,SMALL(IF($CT$2:$CT$101<>"",ROW($CT$2:$CT$101),142),ROW(CT48)))&""} | CV49: =IFERROR(VLOOKUP(CW49,$CO$6:$CQ$105,3,FALSE),"") | CW49: =IF(主要!AX58="","",主要!AX58) | CX49: =IFERROR(VLOOKUP(CW49,$CO$6:$CQ$105,2,FALSE),"")
A50: 17 | B50: 7 | C50: 野性直觉 | D50: 你的直觉变得格外敏锐。你的先攻检定具有优势。 | E50: 3 | F50: 吟游诗人子职 | G50: 你选择获得一项吟游诗人子职：舞蹈学院，魅心学院，逸闻学院或勇气学院 。子职的内容见后文。子职是一种特化，在特定的吟游诗人等级给予你对应的独特能力。此后你将获得你所选的子职所有能力——只要其所需等级不超过你的吟游诗人等级。吟游诗人特性 表列出了你从子职中获得新特性的吟游诗人等级。 吟游诗人们会形成被称为“学院 ”的松散联系，用以维持他们的传承。 | I50: 驱散亡灵 | J50: 以一个魔法动作，你展现圣徽，斥退诸亡灵生物。你30尺内每个由你选择的亡灵都必须进行一次感知豁免，失败则陷入恐慌和失能状态，持续一分钟。在这段持续时间内，被驱散的生物会尽可能远离你。此效应在其受到伤害时提前结束，你陷入失能状态或是死亡也会结束此效应。 | L50: 使用次数 | M50: 你能够使用两次荒野变形。你在完成短休后重获一次已消耗的使用次数，当你完成一次长休时，你重获全部已消耗的使用次数。 你到达特定的德鲁伊等级时会获得额外的使用次数，如德鲁伊表格中荒野变形一栏所示。 | N50: 9 | O50: 战术主宰 | P50: 每当你用武器发动攻击，且你可以使用此武器的精通词条时，你可以将此次攻击的精通属性改为推离，削弱或缓速 中的一种。 | Q50: 5 | R50: 震慑拳 | S50: 每回合一次，当你使用徒手打击或武僧武器命中一个生物后，你可以消耗1点功力尝试发动震慑拳。目标必须进行一次体质豁免，豁免失败则陷入震慑状态，直至你的下个回合开始。若豁免成功，则目标的速度减半，直至你的下个回合开始，并且下一次对该目标进行的攻击检定具有优势。 | T50: 3 | U50: 引导神力 | V50: 你获得直接从外层位面引导神圣能量的能力，并能用这些能量产生魔法效应。你起始时具有一种选项：神圣感知，其效果如下所示。其他的圣武士特性会给予更多引导神力选项。每当你使用你的引导神力时，你可以选择要创造哪种因此职业习得的效应。 你可以使用两次引导神力，你在完成一次短休后恢复1次使用次数，完成长休后恢复所有已使用的次数。当你的圣武士等级到达11级时，你会获得额外的引导神力次数。 如果一项引导神力效应需要进行豁免，其豁免DC等同于你施法职业特性的法术豁免DC。 | W50: 3 | X50: 游侠子职 | Y50: 你选择获得一项游侠子职：驯兽师， 妖精漫游者， 幽域追猎者或 猎人。子职的内容见后文。子职是一种特化，在特定的游侠等级给予你对应的独特能力。此后你将获得你所选的子职所有能力——只要其所需等级不超过你的游侠等级。游侠特性表列出了你从子职中获得新特性的游侠等级。 | Z50: 7 | AA50: 反射闪避 | AB50: 你可以灵敏地躲避特定的危险。当你受到一个允许你进行敏捷豁免来只承受一半伤害的效应影响时，你在豁免成功时不受伤害，豁免失败时只承受一半伤害。你无法在失能时使用此特性。 | AD50: 谨慎法术 | AE50: 消耗：1术法点 当你施展一个强迫其他生物进行豁免的法术时，你可以保护某些生物免受法术的危害。你消耗1术法点并选择最多等同于你魅力调整值数量的生物（至少1个）。被选择的生物自动通过法术的豁免检定。如果法术在豁免成功后仍然造成半伤，这些生物不会承受任何伤害。 | AG50: =IF(自定义调整栏!$E$4="O","链主赋能","") -> 链主赋能 | AH50: 当你施展 寻获魔宠find familiar 时，你将一定程度的魔能力量灌注给被召唤的魔宠，给予这个生物以下的能力： • 该魔宠获得40尺的飞行速度、或40尺的游泳速度（由你选择）。 • 你可以使用一个附赠动作，指挥你的魔宠进行一次攻击动作。 • 该魔宠的武器攻击被视为魔法性的，用于克服对于非魔法攻击的免疫和抗性。 • 若该魔宠强迫一个生物进行豁免检定，它使用你的法术豁免DC。 • 若该魔宠受到伤害，你可以使用你的反应给予它仅对于那次伤害的抗性。 先决条件：链之魔契 | AJ50: 替换法术书 | AK50: 你可以将法术从你自己的法术书复制到另一本书中。这就像将新法术复制到你的法术书中一样，但更快也更简单，因为你已经知道如何施展这些法术。复制过程只需每个法术环阶花费1小时和10GP。 如果你失去了你的法术书，则你可以使用相同的过程将你已准备的法师法术转录到新的法术书中。你仍需要找到新的法术来填满新书的剩余部分。出于这个原因，许多法师都会保留一本备用法术书。 | AL50: 3 | AM50: 奇械师子职 | AN50: 你选择获得一项奇械师子职。炼金师Alchemist，装甲师Armorer，魔炮师Artillerist，战地匠师Battle Smith和制图师Cartographer，子职业会在此职业之后详细描述。子职是一种特化，在特定的奇械师等级给予你对应的独特能力。此后你将获得每一个你所选的子职的能力，只要其所需等级等于或低于你的奇械师等级。 | AP50: 生物反馈 | AQ50: 当你施展了一道死灵或变化学派的灵能使法术时，你可以消耗至多智力调整值枚灵能骰。你获得等同于骰值外加你的智力调整值（最小值为1）临时生命值。 | AR50: 1 | AS50: 战斗风格 | AT50: 你获得一项战斗风格专长，选择1项：箭术、对决、巨武器战斗或双武器战斗。 | AU50: 2 | AV50: 生命体征 | AW50: 当30尺范围内你可见的一个生物在一次豁免检定或死亡豁免中失败时，你可以使用你的反应将你的智力调整值加到该生物的掷骰结果中，此举有可能使该检定由失败转为成功。你不能对同一个生物再次使用该理论直到你完成一次短休。 | AY50: 千钧一发 | AZ50: 当你可见的生物以攻击检定命中你时，你能够以反应消耗一枚风险骰来躲避危害。掷骰并将结果加入对抗那次攻击的AC，这可能令那次攻击改为失手。 | BA50: 2 | BB50: 极速惩戒（被动） | BC50: 当一名受禁生物引发你的借机攻击时，你能够不消耗反应的发动借机攻击，但你不能在无法执行反应时发动该攻击。该恩惠一经使用，直至你的下一回合开始你才能再如此做。 | BD50: 5 | BE50: 万钧痛击 | BF50: 当你以徒手打击或拳斗武器发动一次攻击时，你能消耗1点锐气来毫无保留的攻击。若命中，你重获消耗的那点锐气，且你那次攻击造成最大伤害。 | CH50: 魅心学院 | CI50: 29 | CJ50: {=_xlfn.IFS($AZ$3>=14,32,$AZ$3>=6,31,$AZ$3>=3,30,1,0)} -> 0 | CN50: =IFERROR(IF(CN49+1>CS2,IF(CN49+1>CS2,IF(CR3+CR49>CS3,"",CR3+CR49)),CN49+1),"") -> 45 | CO50: {=IFERROR(INDEX($B$34:$BO$262,CN50,$CP$2),"")} | CP50: {=IFERROR(INDEX($B$34:$BO$262,CN50,$CQ$2),"")} | CQ50: {=IF(IFERROR(INDEX($B$34:$BO$262,CN50,$CO$2),"")=0,"",IFERROR(INDEX($B$34:$BO$262,CN50,$CO$2),""))} | CR50: =IFERROR(IF(CN49+1>CS2,CR49+1,0),"") -> 0 | CT50: =IFERROR(IF(OR(CO54="",COUNTIF($CW$2:$CW$81,CO54)),"",CO54),"") | CU50: {=INDEX(CT:CT,SMALL(IF($CT$2:$CT$101<>"",ROW($CT$2:$CT$101),142),ROW(CT49)))&""} | CV50: =IFERROR(VLOOKUP(CW50,$CO$6:$CQ$105,3,FALSE),"") | CW50: =IF(主要!AX59="","",主要!AX59) | CX50: =IFERROR(VLOOKUP(CW50,$CO$6:$CQ$105,2,FALSE),"")
A51: 18 | B51: 7 | C51: 莽驰 | D51: 作为你进入狂暴的附赠动作的一部分，你可以移动至多等于你速度一半的距离。 | E51: 4 | F51: 属性值提升 | G51: 你获得属性值提升专长（见第五章）或其他你满足条件的专长。如吟游诗人特性表所示，你还会在第8，第12，第16级时再次获得本特性。 | H51: 3 | I51: 牧师子职 | J51: 你选择获得一项牧师子职：生命领域，光明领域， 诡术领域 或 战争领域。子职的内容见后文。子职是一种特化，在特定的牧师等级给予你对应的独特能力。此后你将获得你所选的子职所有能力——只要其所需等级不超过你的牧师等级。牧师特性表列出了你从子职中获得新特性的牧师等级。 牧师的每个子职都以某神明、神殿或宗教青睐的“领域”命名。 | L51: 已知形态 | M51: 你一开始掌握了该特性的四种形态，从最大挑战等级1/4且没有飞行速度的野兽（见附录B的生物数据卡）之中选取。推荐老鼠Rat、骑乘用马Riding Horse、蜘蛛Spider和狼Wolf四种形态。当你完成一次长休时，你可以将一种你掌握的形态换为另一种能够选用的形态。 当你到达特定的德鲁伊等级后，你可以掌握新的形态，形态的最大挑战等级也会随之提升，如野兽形态表所示。此外，在8级时，你可以使用具有飞行速度的形态。 当选择已知形态时，如果地下城主允许，你可以查阅《怪物图鉴》或其他来源并从中选择。 | N51: 11 | O51: 额外攻击（二） | P51: 你在自己回合内执行攻击动作时，可以发动三次攻击而非一次。 | Q51: 6 | R51: 真力注拳 | S51: 当你使用徒手打击造成伤害时，你可以选择造成力场伤害或是其原本的伤害类型。 | U51: 神圣感知 | V51: 以一个附赠动作，你可以扩展你的意识侦测天界生物，邪魔以及不死生物。持续10分钟内或直到你陷入失能状态为止，你能感知到自身周围60尺内这些生物的位置，以及它们的生物类型。你也可以侦测任何受到圣居Hallow一类的法术祝福或亵渎的地点或物件。 | W51: 4 | X51: 属性值提升 | Y51: 你获得属性值提升专长（见第五章）或其它你满足条件的专长。你还会在你的游侠等级达到第8、第12和第16级时再次获得本特性。 | Z51: 7 | AA51: 可靠才能 | AB51: 每当你进行属性检定，并且可以运用你的某项技能熟练项或工具熟练项时，你可以将D20投出的9及以下的结果视为10。 | AD51: 远程法术 | AE51: 消耗：1术法点 当你施展一个射程至少为5尺的法术时，你可以消耗1术法点来将法术的射程翻倍。 当你施展一个射程为触及的法术时，你可以消耗1术法点来将法术的射程改为30尺。 | AG51: =IF(自定义调整栏!$E$4="O","符令责斥","") -> 符令责斥 | AH51: 当该护符的佩戴者被一个位于你30尺以内你可见的攻击者命中时，你可以使用你的反应来对该攻击者造成等同于你熟练加值的心灵伤害，并将其推离护符佩戴者至多10尺距离。 先决条件：符之魔契 | AI51: 1 | AJ51: 仪式学家 | AK51: 你能以仪式施展你法术书中任何带有仪式Ritual标签的法术。你不需要准备这些法术，但你以此法施展法术时必须阅读这本书。 | AL51: 4 | AM51: 属性值提升 | AN51: 你获得属性值提升专长（见第五章）或其他你满足条件的专长。如奇械师特性表所示，你还会在第8，第12，第16级时再次获得本特性。 | AP51: 强化预知 | AQ51: 当你施展了一道防护或预言学派的灵能使法术时，你能够消耗一枚灵能骰。投掷其并选择一名60尺内你可见的生物（可以是你自己）。直至你的下个回合结束，该生物的下次D20检定获得等于灵能骰骰值的加值。 | AR51: 2 | AS51: 猩红仪式 | AT51: 你学会消耗你自身的活力来对你的武器释放猩红仪式。以一个附赠动作，你激活任何一种你已知的猩红仪式，为一把武器注入元素能量，效果持续到你完成下次短休或长休。当你激活一个血仪时，你失去一个鲜血秘法骰的生命值。这个伤害不能被任何方式减少。 当仪式生效时，你用该武器进行的攻击是魔法攻击，并且造成等用于你鲜血秘法骰的额外伤害，一把武器只能容纳一个激活的猩红仪式。其他生物无法从你的猩红仪式中获益。当你第一次获得此特性时，你从下列的猩红仪式中学会一种。你在第 7 级时学会一种额外的猩红仪式，并在 14 级时再额外学会一种猩红仪式。 | AU51: 2 | AV51: 精准解剖术 | AW51: 当你进行一次武器攻击时，你可以在攻击和伤害掷骰上使用你的智力调整值，而不是力量或敏捷属性。 | AX51: 3 | AY51: 铳士子职 | AZ51: 你选择获得一项铳士子职：死瞳客，豪赌客，密间客，魔弹客，花枪客或白帽客。子职的内容见后文。子职是一种特化，在特定的铳士等级给予你对应的独特能力。此后你将获得你所选的子职所有能力——只要其所需等级不超过你的铳士等级。 | BA51: 3 | BB51: 极恶之契 | BC51: 你与一位大魔鬼签下极恶之契，受邀加入墟寂教团。从筑灭师（阿斯蒙蒂斯Asmodeus）、狱言家（摩洛克Moloch）、恐惧屠戮者（迪斯帕特Dispater）、猩红骑士（苏特赫Sutekh）、影宗（贝利亚Belial）中选择一名作为你的大魔鬼宗主。每个子职均在后文有所详述。 你将获得你选择的子职的3级特性，并在7级，11级和15级再次获得你所选子职的相应特性。_x000D_ 那些行走于地狱之路者仅凭自身的虔诚便可能获得邪狱使之力。无需誓言也无需导师指导，一些邪狱使甚至不知道墟寂教团的存在。但真正成为墟寂行者意味着向特定的九狱统治者宣誓。这通常需要教团的高级成员主持复杂的仪式，但一些虔诚的邪狱使可能通过自己做出背叛的恶绩来吸引大魔鬼的注意。_x000D_ 在邪狱使的路途上，无论是通过仪式或是恶绩，他们终将直面七宗城的统治者之一。此时他们将以鲜血——通常是邪狱使自己的——签署契约。让这名流失在外的骑士与墟寂教团相联系，并将他们的名字加入到九狱名单之中。_x000D_ 虽然这种经历听起来令人生畏，但九狱的统治者通常是随和的主宰，极少向他们选召之人索取任何东西。七宗城的统治者们极其忙碌，甚少关注他们手下的日常生活——甚至包括那些违反戒律的行为。只要这些骑士们还在散播龃龉、对抗天族大军，他们就能成功推进九狱的计划。 | BD51: 6 | BE51: 锐不可当 | BF51: 当你以徒手打击或以临时武器发动的攻击造成伤害时，你可以选择造成力场伤害或是其原本的伤害类型。 | CH51: 逸闻学院 | CI51: 33 | CJ51: {=_xlfn.IFS($AZ$3>=14,36,$AZ$3>=6,35,$AZ$3>=3,34,1,0)} -> 0 | CN51: =IFERROR(IF(CN50+1>CS2,IF(CN50+1>CS2,IF(CR3+CR50>CS3,"",CR3+CR50)),CN50+1),"") -> 46 | CO51: {=IFERROR(INDEX($B$34:$BO$262,CN51,$CP$2),"")} | CP51: {=IFERROR(INDEX($B$34:$BO$262,CN51,$CQ$2),"")} | CQ51: {=IF(IFERROR(INDEX($B$34:$BO$262,CN51,$CO$2),"")=0,"",IFERROR(INDEX($B$34:$BO$262,CN51,$CO$2),""))} | CR51: =IFERROR(IF(CN50+1>CS2,CR50+1,0),"") -> 0 | CT51: =IFERROR(IF(OR(CO55="",COUNTIF($CW$2:$CW$81,CO55)),"",CO55),"") | CU51: {=INDEX(CT:CT,SMALL(IF($CT$2:$CT$101<>"",ROW($CT$2:$CT$101),142),ROW(CT50)))&""} | CV51: =IFERROR(VLOOKUP(CW51,$CO$6:$CQ$105,3,FALSE),"") | CW51: =IF(主要!AX60="","",主要!AX60) | CX51: =IFERROR(VLOOKUP(CW51,$CO$6:$CQ$105,2,FALSE),"")
